Workbook
Name TOTAL_MO_INC: Inputs!$Z$1
Name SAFE: Inputs!$Z$1
Name TOTAL_EQ: Inputs!$Z$1
Name Y_ANN: Inputs!$Z$1
Name YEARS: Inputs!$Z$1
Name MARGINABLE: Inputs!$Z$1
Name START_DATE: Inputs!$Z$1
Name BIWEEKLY: Inputs!$Z$1

Sheet Inputs
A1: Key | B1: Value | C1: Notes | Z1: =SUM(Holdings!K2:K1000) -> 133.11583
A2: StartDate | B2: 45897
A3: BiweeklyContribution | B3: 2200
A4: BlendedYield_Annual | B4: 0.65
A5: Years | B5: 5
A6: MarginablePct | B6: 0.575
A7: SafeMarginPct | B7: 0.15
A8: ReservePctForPaycheck | B8: 0.1
A9: WeeklyGoal_$ | B9: =B11/52 -> 5384.6154
A10: MonthlyGoal_$ | B10: =B11/12 -> 23333.333
A11: AnnualGoal_$ | B11: 280000

Sheet Options – Open Positions
A1: Trade ID | B1: Ticker | C1: Open Date | D1: Expiry | E1: Strategy | F1: Multiplier | G1: Net Qty | H1: Leg # | I1: Type | J1: Side | K1: Strike | L1: Premium | M1: Leg Qty | N1: Status
A2: INTC-70C-50 | B2: INTC | C2: 45919 | E2: Long Call | F2: 100 | G2: 50 | H2: 1 | I2: CALL | J2: BUY | K2: 70 | L2: 0 | M2: 50 | N2: OPEN
A3: IBIT-54/53P | B3: IBIT | C3: 45926 | E3: Bear Put Debit | F3: 100 | G3: 1 | H3: 1 | I3: PUT | J3: BUY | K3: 54 | L3: 0 | M3: 1 | N3: OPEN
A4: IBIT-54/53P | B4: IBIT | C4: 45926 | E4: Bear Put Debit | F4: 100 | G4: 1 | H4: 2 | I4: PUT | J4: SELL | K4: 53 | L4: 0 | M4: 1 | N4: OPEN
A5: QQQ-490/460P | B5: QQQ | C5: 45926 | E5: Bear Put Debit | F5: 100 | G5: 1 | H5: 1 | I5: PUT | J5: BUY | K5: 490 | L5: 0 | M5: 1 | N5: OPEN
A6: QQQ-490/460P | B6: QQQ | C6: 45926 | E6: Bear Put Debit | F6: 100 | G6: 1 | H6: 2 | I6: PUT | J6: SELL | K6: 460 | L6: 0 | M6: 1 | N6: OPEN
A7: SPY-580/550P | B7: SPY | C7: 45926 | E7: Bear Put Debit | F7: 100 | G7: 1 | H7: 1 | I7: PUT | J7: BUY | K7: 580 | L7: 0 | M7: 1 | N7: OPEN
A8: SPY-580/550P | B8: SPY | C8: 45926 | E8: Bear Put Debit | F8: 100 | G8: 1 | H8: 2 | I8: PUT | J8: SELL | K8: 550 | L8: 0 | M8: 1 | N8: OPEN
A9: ULTY-5.5P | B9: ULTY | C9: 45926 | E9: Long Put | F9: 100 | G9: 1 | H9: 1 | I9: PUT | J9: BUY | K9: 5.5 | L9: 0 | M9: 1 | N9: OPEN
A10: NVDA-175/185C | B10: NVDA | C10: 45933 | E10: Bear Call Credit | F10: 100 | G10: 1 | H10: 1 | I10: CALL | J10: SELL | K10: 175 | L10: 0 | M10: 1 | N10: OPEN
A11: NVDA-175/185C | B11: NVDA | C11: 45933 | E11: Bear Call Credit | F11: 100 | G11: 1 | H11: 2 | I11: CALL | J11: BUY | K11: 185 | L11: 0 | M11: 1 | N11: OPEN
A12: NVDA-145/140P | B12: NVDA | C12: 45933 | E12: Bear Put Debit | F12: 100 | G12: 1 | H12: 1 | I12: PUT | J12: BUY | K12: 145 | L12: 0 | M12: 1 | N12: OPEN
A13: NVDA-145/140P | B13: NVDA | C13: 45933 | E13: Bear Put Debit | F13: 100 | G13: 1 | H13: 2 | I13: PUT | J13: SELL | K13: 140 | L13: 0 | M13: 1 | N13: OPEN
... A15: GLD-327/321P | B15: GLD | C15: 45940 | E15: Bull Put Credit | F15: 100 | G15: 1 | H15: 2 | I15: PUT | J15: BUY | K15: 321 | L15: 0 | M15: 1 | N15: OPEN

Sheet Options – Payoff
A1: Selected Trade ID | B1: QQQ-490/460P | F1: Summary
A2: Center Price | B2: 50
A3: Step | B3: 1 | F3: Net Entry | G3: Width | H3: Max Profit | I3: Max Loss | J3: BE1 | K3: BE2
A4: Points | B4: 121 | F4: =OPTIONS_SUMMARY($B$1) -> #NAME? | G4: =OPTIONS_SUMMARY($B$1) -> #NAME? | H4: =OPTIONS_SUMMARY($B$1) -> #NAME? | I4: =OPTIONS_SUMMARY($B$1) -> #NAME? | J4: =OPTIONS_SUMMARY($B$1) -> #NAME? | K4: =OPTIONS_SUMMARY($B$1) -> #NAME?
A7: S_T | B7: P/L ($) | C7: ProfitOnly | D7: LossOnly | E7: Zero
A8: {=SEQUENCE($B$4,1,$B$2-INT($B$4/2)*$B$3,$B$3)} -> -10 | B8: =OPTIONS_PAYOFF($B$1, A8) -> #NAME? | C8: =IF(B8>0, B8, NA()) -> #NAME? | D8: =IF(B8<0, B8, NA()) -> #NAME? | E8: =0 -> 0
A9: -9 | B9: =OPTIONS_PAYOFF($B$1, A9) -> #NAME? | C9: =IF(B9>0, B9, NA()) -> #NAME? | D9: =IF(B9<0, B9, NA()) -> #NAME? | E9: =0 -> 0
A10: -8 | B10: =OPTIONS_PAYOFF($B$1, A10) -> #NAME? | C10: =IF(B10>0, B10, NA()) -> #NAME? | D10: =IF(B10<0, B10, NA()) -> #NAME? | E10: =0 -> 0
A11: -7 | B11: =OPTIONS_PAYOFF($B$1, A11) -> #NAME? | C11: =IF(B11>0, B11, NA()) -> #NAME? | D11: =IF(B11<0, B11, NA()) -> #NAME? | E11: =0 -> 0
A12: -6 | B12: =OPTIONS_PAYOFF($B$1, A12) -> #NAME? | C12: =IF(B12>0, B12, NA()) -> #NAME? | D12: =IF(B12<0, B12, NA()) -> #NAME? | E12: =0 -> 0
A13: -5 | B13: =OPTIONS_PAYOFF($B$1, A13) -> #NAME? | C13: =IF(B13>0, B13, NA()) -> #NAME? | D13: =IF(B13<0, B13, NA()) -> #NAME? | E13: =0 -> 0
A14: -4 | B14: =OPTIONS_PAYOFF($B$1, A14) -> #NAME? | C14: =IF(B14>0, B14, NA()) -> #NAME? | D14: =IF(B14<0, B14, NA()) -> #NAME? | E14: =0 -> 0
A15: -3 | B15: =OPTIONS_PAYOFF($B$1, A15) -> #NAME? | C15: =IF(B15>0, B15, NA()) -> #NAME? | D15: =IF(B15<0, B15, NA()) -> #NAME? | E15: =0 -> 0
A16: -2 | B16: =OPTIONS_PAYOFF($B$1, A16) -> #NAME? | C16: =IF(B16>0, B16, NA()) -> #NAME? | D16: =IF(B16<0, B16, NA()) -> #NAME? | E16: =0 -> 0
A17: -1 | B17: =OPTIONS_PAYOFF($B$1, A17) -> #NAME? | C17: =IF(B17>0, B17, NA()) -> #NAME? | D17: =IF(B17<0, B17, NA()) -> #NAME? | E17: =0 -> 0
A18: 0 | B18: =OPTIONS_PAYOFF($B$1, A18) -> #NAME? | C18: =IF(B18>0, B18, NA()) -> #NAME? | D18: =IF(B18<0, B18, NA()) -> #NAME? | E18: =0 -> 0
A19: 1 | B19: =OPTIONS_PAYOFF($B$1, A19) -> #NAME? | C19: =IF(B19>0, B19, NA()) -> #NAME? | D19: =IF(B19<0, B19, NA()) -> #NAME? | E19: =0 -> 0
A20: 2 | B20: =OPTIONS_PAYOFF($B$1, A20) -> #NAME? | C20: =IF(B20>0, B20, NA()) -> #NAME? | D20: =IF(B20<0, B20, NA()) -> #NAME? | E20: =0 -> 0
... A128: 110 | B128: =OPTIONS_PAYOFF($B$1, A128) -> #NAME? | C128: =IF(B128>0, B128, NA()) -> #NAME? | D128: =IF(B128<0, B128, NA()) -> #NAME? | E128: =0 -> 0

Sheet Options – Payoff (v2)
A1: Selected Trade ID | B1: SPY-580/550P | F1: Summary
A2: Center Price | B2: 50
A3: Step | B3: 1 | F3: Net Entry | G3: Width | H3: Max Profit | I3: Max Loss | J3: BE1 | K3: BE2
A4: Points | B4: 121 | F4: =OPTIONS_SUMMARY_V2($B$1) -> 0 | G4: =OPTIONS_SUMMARY_V2($B$1) -> 0 | H4: =OPTIONS_SUMMARY_V2($B$1) -> 0 | I4: =OPTIONS_SUMMARY_V2($B$1) -> Loading... | J4: =OPTIONS_SUMMARY_V2($B$1) -> 0 | K4: =OPTIONS_SUMMARY_V2($B$1) -> Loading...
F5: 3000 | G5: 3000 | H5: 3000 | J5: 3000
F6: 3000 | G6: 3000 | H6: 3000 | J6: 3000
A7: S_T | B7: P/L ($) | C7: ProfitOnly | D7: LossOnly | E7: Zero | F7: 0 | G7: 0 | H7: 0 | J7: 0
A8: {=SEQUENCE($B$4,1,$B$2-INT($B$4/2)*$B$3,$B$3)} -> -10 | B8: =OPTIONS_PAYOFF_V2($B$1, A8) -> 3000 | C8: =IF(B8>0, B8, NA()) -> 3000 | D8: =IF(B8<0, B8, NA()) -> #N/A | E8: =0 -> 0 | F8: 550 | G8: 550 | H8: 550 | J8: 550
A9: -9 | B9: =OPTIONS_PAYOFF_V2($B$1, A9) -> 3000 | C9: =IF(B9>0, B9, NA()) -> 3000 | D9: =IF(B9<0, B9, NA()) -> #N/A | E9: =0 -> 0
A10: -8 | B10: =OPTIONS_PAYOFF_V2($B$1, A10) -> Loading... | C10: =IF(B10>0, B10, NA()) -> Loading... | D10: =IF(B10<0, B10, NA()) -> Loading... | E10: =0 -> 0
A11: -7 | B11: =OPTIONS_PAYOFF_V2($B$1, A11) -> 3000 | C11: =IF(B11>0, B11, NA()) -> 3000 | D11: =IF(B11<0, B11, NA()) -> #N/A | E11: =0 -> 0
A12: -6 | B12: =OPTIONS_PAYOFF_V2($B$1, A12) -> 3000 | C12: =IF(B12>0, B12, NA()) -> 3000 | D12: =IF(B12<0, B12, NA()) -> #N/A | E12: =0 -> 0
A13: -5 | B13: =OPTIONS_PAYOFF_V2($B$1, A13) -> 3000 | C13: =IF(B13>0, B13, NA()) -> 3000 | D13: =IF(B13<0, B13, NA()) -> #N/A | E13: =0 -> 0
A14: -4 | B14: =OPTIONS_PAYOFF_V2($B$1, A14) -> Loading... | C14: =IF(B14>0, B14, NA()) -> Loading... | D14: =IF(B14<0, B14, NA()) -> Loading... | E14: =0 -> 0
A15: -3 | B15: =OPTIONS_PAYOFF_V2($B$1, A15) -> Loading... | C15: =IF(B15>0, B15, NA()) -> Loading... | D15: =IF(B15<0, B15, NA()) -> Loading... | E15: =0 -> 0
A16: -2 | B16: =OPTIONS_PAYOFF_V2($B$1, A16) -> 3000 | C16: =IF(B16>0, B16, NA()) -> 3000 | D16: =IF(B16<0, B16, NA()) -> #N/A | E16: =0 -> 0
A17: -1 | B17: =OPTIONS_PAYOFF_V2($B$1, A17) -> 3000 | C17: =IF(B17>0, B17, NA()) -> 3000 | D17: =IF(B17<0, B17, NA()) -> #N/A | E17: =0 -> 0
A18: 0 | B18: =OPTIONS_PAYOFF_V2($B$1, A18) -> 3000 | C18: =IF(B18>0, B18, NA()) -> 3000 | D18: =IF(B18<0, B18, NA()) -> #N/A | E18: =0 -> 0
A19: 1 | B19: =OPTIONS_PAYOFF_V2($B$1, A19) -> 3000 | C19: =IF(B19>0, B19, NA()) -> 3000 | D19: =IF(B19<0, B19, NA()) -> #N/A | E19: =0 -> 0
A20: 2 | B20: =OPTIONS_PAYOFF_V2($B$1, A20) -> 3000 | C20: =IF(B20>0, B20, NA()) -> 3000 | D20: =IF(B20<0, B20, NA()) -> #N/A | E20: =0 -> 0
... A128: 110 | B128: =OPTIONS_PAYOFF_V2($B$1, A128) -> Loading... | C128: =IF(B128>0, B128, NA()) -> Loading... | D128: =IF(B128<0, B128, NA()) -> Loading... | E128: =0 -> 0

Sheet Prices
A1: Symbol | B1: LastPrice | C1: LastUpdated
A2: YSPY | B2: =IFERROR(__xludf.DUMMYFUNCTION("IFERROR(GOOGLEFINANCE(A2,""price""),"""")"),19.95) -> 19.95 | C2: =IF(B2<>"", NOW(), "") -> 45909.394
A3: IWMY | B3: =IFERROR(__xludf.DUMMYFUNCTION("IFERROR(GOOGLEFINANCE(A3,""price""),"""")"),23.14) -> 23.14 | C3: =IF(B3<>"", NOW(), "") -> 45909.394
A4: ULTY | B4: =IFERROR(__xludf.DUMMYFUNCTION("IFERROR(GOOGLEFINANCE(A4,""price""),"""")"),5.55) -> 5.55 | C4: =IF(B4<>"", NOW(), "") -> 45909.394
A5: TQQY | B5: =IFERROR(__xludf.DUMMYFUNCTION("IFERROR(GOOGLEFINANCE(A5,""price""),"""")"),18.75) -> 18.75 | C5: =IF(B5<>"", NOW(), "") -> 45909.394
A6: PLTY | B6: =IFERROR(__xludf.DUMMYFUNCTION("IFERROR(GOOGLEFINANCE(A6,""price""),"""")"),62.2) -> 62.2 | C6: =IF(B6<>"", NOW(), "") -> 45909.394
A7: COIW | B7: =IFERROR(__xludf.DUMMYFUNCTION("IFERROR(GOOGLEFINANCE(A7,""price""),"""")"),39.51) -> 39.51 | C7: =IF(B7<>"", NOW(), "") -> 45909.394
B8: =IFERROR(__xludf.DUMMYFUNCTION("IFERROR(GOOGLEFINANCE(A8,""price""),"""")"),"") | C8: =IF(B8<>"", NOW(), "")
B9: =IFERROR(__xludf.DUMMYFUNCTION("IFERROR(GOOGLEFINANCE(A9,""price""),"""")"),"") | C9: =IF(B9<>"", NOW(), "")
B10: =IFERROR(__xludf.DUMMYFUNCTION("IFERROR(GOOGLEFINANCE(A10,""price""),"""")"),"") | C10: =IF(B10<>"", NOW(), "")
B11: =IFERROR(__xludf.DUMMYFUNCTION("IFERROR(GOOGLEFINANCE(A11,""price""),"""")"),"") | C11: =IF(B11<>"", NOW(), "")
B12: =IFERROR(__xludf.DUMMYFUNCTION("IFERROR(GOOGLEFINANCE(A12,""price""),"""")"),"") | C12: =IF(B12<>"", NOW(), "")
B13: =IFERROR(__xludf.DUMMYFUNCTION("IFERROR(GOOGLEFINANCE(A13,""price""),"""")"),"") | C13: =IF(B13<>"", NOW(), "")
B14: =IFERROR(__xludf.DUMMYFUNCTION("IFERROR(GOOGLEFINANCE(A14,""price""),"""")"),"") | C14: =IF(B14<>"", NOW(), "")
B15: =IFERROR(__xludf.DUMMYFUNCTION("IFERROR(GOOGLEFINANCE(A15,""price""),"""")"),"") | C15: =IF(B15<>"", NOW(), "")
B16: =IFERROR(__xludf.DUMMYFUNCTION("IFERROR(GOOGLEFINANCE(A16,""price""),"""")"),"") | C16: =IF(B16<>"", NOW(), "")
B17: =IFERROR(__xludf.DUMMYFUNCTION("IFERROR(GOOGLEFINANCE(A17,""price""),"""")"),"") | C17: =IF(B17<>"", NOW(), "")
B18: =IFERROR(__xludf.DUMMYFUNCTION("IFERROR(GOOGLEFINANCE(A18,""price""),"""")"),"") | C18: =IF(B18<>"", NOW(), "")
B19: =IFERROR(__xludf.DUMMYFUNCTION("IFERROR(GOOGLEFINANCE(A19,""price""),"""")"),"") | C19: =IF(B19<>"", NOW(), "")
B20: =IFERROR(__xludf.DUMMYFUNCTION("IFERROR(GOOGLEFINANCE(A20,""price""),"""")"),"") | C20: =IF(B20<>"", NOW(), "")
B21: =IFERROR(__xludf.DUMMYFUNCTION("IFERROR(GOOGLEFINANCE(A21,""price""),"""")"),"") | C21: =IF(B21<>"", NOW(), "")
B22: =IFERROR(__xludf.DUMMYFUNCTION("IFERROR(GOOGLEFINANCE(A22,""price""),"""")"),"") | C22: =IF(B22<>"", NOW(), "")
B23: =IFERROR(__xludf.DUMMYFUNCTION("IFERROR(GOOGLEFINANCE(A23,""price""),"""")"),"") | C23: =IF(B23<>"", NOW(), "")
B24: =IFERROR(__xludf.DUMMYFUNCTION("IFERROR(GOOGLEFINANCE(A24,""price""),"""")"),"") | C24: =IF(B24<>"", NOW(), "")
B25: =IFERROR(__xludf.DUMMYFUNCTION("IFERROR(GOOGLEFINANCE(A25,""price""),"""")"),"") | C25: =IF(B25<>"", NOW(), "")
B26: =IFERROR(__xludf.DUMMYFUNCTION("IFERROR(GOOGLEFINANCE(A26,""price""),"""")"),"") | C26: =IF(B26<>"", NOW(), "")
B27: =IFERROR(__xludf.DUMMYFUNCTION("IFERROR(GOOGLEFINANCE(A27,""price""),"""")"),"") | C27: =IF(B27<>"", NOW(), "")
B28: =IFERROR(__xludf.DUMMYFUNCTION("IFERROR(GOOGLEFINANCE(A28,""price""),"""")"),"") | C28: =IF(B28<>"", NOW(), "")
B29: =IFERROR(__xludf.DUMMYFUNCTION("IFERROR(GOOGLEFINANCE(A29,""price""),"""")"),"") | C29: =IF(B29<>"", NOW(), "")
B30: =IFERROR(__xludf.DUMMYFUNCTION("IFERROR(GOOGLEFINANCE(A30,""price""),"""")"),"") | C30: =IF(B30<>"", NOW(), "")
B31: =IFERROR(__xludf.DUMMYFUNCTION("IFERROR(GOOGLEFINANCE(A31,""price""),"""")"),"") | C31: =IF(B31<>"", NOW(), "")
B32: =IFERROR(__xludf.DUMMYFUNCTION("IFERROR(GOOGLEFINANCE(A32,""price""),"""")"),"") | C32: =IF(B32<>"", NOW(), "")
B33: =IFERROR(__xludf.DUMMYFUNCTION("IFERROR(GOOGLEFINANCE(A33,""price""),"""")"),"") | C33: =IF(B33<>"", NOW(), "")
B34: =IFERROR(__xludf.DUMMYFUNCTION("IFERROR(GOOGLEFINANCE(A34,""price""),"""")"),"") | C34: =IF(B34<>"", NOW(), "")
B35: =IFERROR(__xludf.DUMMYFUNCTION("IFERROR(GOOGLEFINANCE(A35,""price""),"""")"),"") | C35: =IF(B35<>"", NOW(), "")
B36: =IFERROR(__xludf.DUMMYFUNCTION("IFERROR(GOOGLEFINANCE(A36,""price""),"""")"),"") | C36: =IF(B36<>"", NOW(), "")
B37: =IFERROR(__xludf.DUMMYFUNCTION("IFERROR(GOOGLEFINANCE(A37,""price""),"""")"),"") | C37: =IF(B37<>"", NOW(), "")
B38: =IFERROR(__xludf.DUMMYFUNCTION("IFERROR(GOOGLEFINANCE(A38,""price""),"""")"),"") | C38: =IF(B38<>"", NOW(), "")
B39: =IFERROR(__xludf.DUMMYFUNCTION("IFERROR(GOOGLEFINANCE(A39,""price""),"""")"),"") | C39: =IF(B39<>"", NOW(), "")
B40: =IFERROR(__xludf.DUMMYFUNCTION("IFERROR(GOOGLEFINANCE(A40,""price""),"""")"),"") | C40: =IF(B40<>"", NOW(), "")
B41: =IFERROR(__xludf.DUMMYFUNCTION("IFERROR(GOOGLEFINANCE(A41,""price""),"""")"),"") | C41: =IF(B41<>"", NOW(), "")
B42: =IFERROR(__xludf.DUMMYFUNCTION("IFERROR(GOOGLEFINANCE(A42,""price""),"""")"),"") | C42: =IF(B42<>"", NOW(), "")
B43: =IFERROR(__xludf.DUMMYFUNCTION("IFERROR(GOOGLEFINANCE(A43,""price""),"""")"),"") | C43: =IF(B43<>"", NOW(), "")
B44: =IFERROR(__xludf.DUMMYFUNCTION("IFERROR(GOOGLEFINANCE(A44,""price""),"""")"),"") | C44: =IF(B44<>"", NOW(), "")
B45: =IFERROR(__xludf.DUMMYFUNCTION("IFERROR(GOOGLEFINANCE(A45,""price""),"""")"),"") | C45: =IF(B45<>"", NOW(), "")
B46: =IFERROR(__xludf.DUMMYFUNCTION("IFERROR(GOOGLEFINANCE(A46,""price""),"""")"),"") | C46: =IF(B46<>"", NOW(), "")
B47: =IFERROR(__xludf.DUMMYFUNCTION("IFERROR(GOOGLEFINANCE(A47,""price""),"""")"),"") | C47: =IF(B47<>"", NOW(), "")
B48: =IFERROR(__xludf.DUMMYFUNCTION("IFERROR(GOOGLEFINANCE(A48,""price""),"""")"),"") | C48: =IF(B48<>"", NOW(), "")
B49: =IFERROR(__xludf.DUMMYFUNCTION("IFERROR(GOOGLEFINANCE(A49,""price""),"""")"),"") | C49: =IF(B49<>"", NOW(), "")
B50: =IFERROR(__xludf.DUMMYFUNCTION("IFERROR(GOOGLEFINANCE(A50,""price""),"""")"),"") | C50: =IF(B50<>"", NOW(), "")
B51: =IFERROR(__xludf.DUMMYFUNCTION("IFERROR(GOOGLEFINANCE(A51,""price""),"""")"),"") | C51: =IF(B51<>"", NOW(), "")
B52: =IFERROR(__xludf.DUMMYFUNCTION("IFERROR(GOOGLEFINANCE(A52,""price""),"""")"),"") | C52: =IF(B52<>"", NOW(), "")
B53: =IFERROR(__xludf.DUMMYFUNCTION("IFERROR(GOOGLEFINANCE(A53,""price""),"""")"),"") | C53: =IF(B53<>"", NOW(), "")
B54: =IFERROR(__xludf.DUMMYFUNCTION("IFERROR(GOOGLEFINANCE(A54,""price""),"""")"),"") | C54: =IF(B54<>"", NOW(), "")
B55: =IFERROR(__xludf.DUMMYFUNCTION("IFERROR(GOOGLEFINANCE(A55,""price""),"""")"),"") | C55: =IF(B55<>"", NOW(), "")
B56: =IFERROR(__xludf.DUMMYFUNCTION("IFERROR(GOOGLEFINANCE(A56,""price""),"""")"),"") | C56: =IF(B56<>"", NOW(), "")
B57: =IFERROR(__xludf.DUMMYFUNCTION("IFERROR(GOOGLEFINANCE(A57,""price""),"""")"),"") | C57: =IF(B57<>"", NOW(), "")
B58: =IFERROR(__xludf.DUMMYFUNCTION("IFERROR(GOOGLEFINANCE(A58,""price""),"""")"),"") | C58: =IF(B58<>"", NOW(), "")
B59: =IFERROR(__xludf.DUMMYFUNCTION("IFERROR(GOOGLEFINANCE(A59,""price""),"""")"),"") | C59: =IF(B59<>"", NOW(), "")
B60: =IFERROR(__xludf.DUMMYFUNCTION("IFERROR(GOOGLEFINANCE(A60,""price""),"""")"),"") | C60: =IF(B60<>"", NOW(), "")
B61: =IFERROR(__xludf.DUMMYFUNCTION("IFERROR(GOOGLEFINANCE(A61,""price""),"""")"),"") | C61: =IF(B61<>"", NOW(), "")
B62: =IFERROR(__xludf.DUMMYFUNCTION("IFERROR(GOOGLEFINANCE(A62,""price""),"""")"),"") | C62: =IF(B62<>"", NOW(), "")
B63: =IFERROR(__xludf.DUMMYFUNCTION("IFERROR(GOOGLEFINANCE(A63,""price""),"""")"),"") | C63: =IF(B63<>"", NOW(), "")
B64: =IFERROR(__xludf.DUMMYFUNCTION("IFERROR(GOOGLEFINANCE(A64,""price""),"""")"),"") | C64: =IF(B64<>"", NOW(), "")
B65: =IFERROR(__xludf.DUMMYFUNCTION("IFERROR(GOOGLEFINANCE(A65,""price""),"""")"),"") | C65: =IF(B65<>"", NOW(), "")
B66: =IFERROR(__xludf.DUMMYFUNCTION("IFERROR(GOOGLEFINANCE(A66,""price""),"""")"),"") | C66: =IF(B66<>"", NOW(), "")
B67: =IFERROR(__xludf.DUMMYFUNCTION("IFERROR(GOOGLEFINANCE(A67,""price""),"""")"),"") | C67: =IF(B67<>"", NOW(), "")
B68: =IFERROR(__xludf.DUMMYFUNCTION("IFERROR(GOOGLEFINANCE(A68,""price""),"""")"),"") | C68: =IF(B68<>"", NOW(), "")
B69: =IFERROR(__xludf.DUMMYFUNCTION("IFERROR(GOOGLEFINANCE(A69,""price""),"""")"),"") | C69: =IF(B69<>"", NOW(), "")
B70: =IFERROR(__xludf.DUMMYFUNCTION("IFERROR(GOOGLEFINANCE(A70,""price""),"""")"),"") | C70: =IF(B70<>"", NOW(), "")
B71: =IFERROR(__xludf.DUMMYFUNCTION("IFERROR(GOOGLEFINANCE(A71,""price""),"""")"),"") | C71: =IF(B71<>"", NOW(), "")
B72: =IFERROR(__xludf.DUMMYFUNCTION("IFERROR(GOOGLEFINANCE(A72,""price""),"""")"),"") | C72: =IF(B72<>"", NOW(), "")
B73: =IFERROR(__xludf.DUMMYFUNCTION("IFERROR(GOOGLEFINANCE(A73,""price""),"""")"),"") | C73: =IF(B73<>"", NOW(), "")
B74: =IFERROR(__xludf.DUMMYFUNCTION("IFERROR(GOOGLEFINANCE(A74,""price""),"""")"),"") | C74: =IF(B74<>"", NOW(), "")
B75: =IFERROR(__xludf.DUMMYFUNCTION("IFERROR(GOOGLEFINANCE(A75,""price""),"""")"),"") | C75: =IF(B75<>"", NOW(), "")
B76: =IFERROR(__xludf.DUMMYFUNCTION("IFERROR(GOOGLEFINANCE(A76,""price""),"""")"),"") | C76: =IF(B76<>"", NOW(), "")
B77: =IFERROR(__xludf.DUMMYFUNCTION("IFERROR(GOOGLEFINANCE(A77,""price""),"""")"),"") | C77: =IF(B77<>"", NOW(), "")
B78: =IFERROR(__xludf.DUMMYFUNCTION("IFERROR(GOOGLEFINANCE(A78,""price""),"""")"),"") | C78: =IF(B78<>"", NOW(), "")
B79: =IFERROR(__xludf.DUMMYFUNCTION("IFERROR(GOOGLEFINANCE(A79,""price""),"""")"),"") | C79: =IF(B79<>"", NOW(), "")
B80: =IFERROR(__xludf.DUMMYFUNCTION("IFERROR(GOOGLEFINANCE(A80,""price""),"""")"),"") | C80: =IF(B80<>"", NOW(), "")
B81: =IFERROR(__xludf.DUMMYFUNCTION("IFERROR(GOOGLEFINANCE(A81,""price""),"""")"),"") | C81: =IF(B81<>"", NOW(), "")
B82: =IFERROR(__xludf.DUMMYFUNCTION("IFERROR(GOOGLEFINANCE(A82,""price""),"""")"),"") | C82: =IF(B82<>"", NOW(), "")
B83: =IFERROR(__xludf.DUMMYFUNCTION("IFERROR(GOOGLEFINANCE(A83,""price""),"""")"),"") | C83: =IF(B83<>"", NOW(), "")
B84: =IFERROR(__xludf.DUMMYFUNCTION("IFERROR(GOOGLEFINANCE(A84,""price""),"""")"),"") | C84: =IF(B84<>"", NOW(), "")
B85: =IFERROR(__xludf.DUMMYFUNCTION("IFERROR(GOOGLEFINANCE(A85,""price""),"""")"),"") | C85: =IF(B85<>"", NOW(), "")
B86: =IFERROR(__xludf.DUMMYFUNCTION("IFERROR(GOOGLEFINANCE(A86,""price""),"""")"),"") | C86: =IF(B86<>"", NOW(), "")
B87: =IFERROR(__xludf.DUMMYFUNCTION("IFERROR(GOOGLEFINANCE(A87,""price""),"""")"),"") | C87: =IF(B87<>"", NOW(), "")
B88: =IFERROR(__xludf.DUMMYFUNCTION("IFERROR(GOOGLEFINANCE(A88,""price""),"""")"),"") | C88: =IF(B88<>"", NOW(), "")
B89: =IFERROR(__xludf.DUMMYFUNCTION("IFERROR(GOOGLEFINANCE(A89,""price""),"""")"),"") | C89: =IF(B89<>"", NOW(), "")
B90: =IFERROR(__xludf.DUMMYFUNCTION("IFERROR(GOOGLEFINANCE(A90,""price""),"""")"),"") | C90: =IF(B90<>"", NOW(), "")
B91: =IFERROR(__xludf.DUMMYFUNCTION("IFERROR(GOOGLEFINANCE(A91,""price""),"""")"),"") | C91: =IF(B91<>"", NOW(), "")
B92: =IFERROR(__xludf.DUMMYFUNCTION("IFERROR(GOOGLEFINANCE(A92,""price""),"""")"),"") | C92: =IF(B92<>"", NOW(), "")
B93: =IFERROR(__xludf.DUMMYFUNCTION("IFERROR(GOOGLEFINANCE(A93,""price""),"""")"),"") | C93: =IF(B93<>"", NOW(), "")
B94: =IFERROR(__xludf.DUMMYFUNCTION("IFERROR(GOOGLEFINANCE(A94,""price""),"""")"),"") | C94: =IF(B94<>"", NOW(), "")
B95: =IFERROR(__xludf.DUMMYFUNCTION("IFERROR(GOOGLEFINANCE(A95,""price""),"""")"),"") | C95: =IF(B95<>"", NOW(), "")
B96: =IFERROR(__xludf.DUMMYFUNCTION("IFERROR(GOOGLEFINANCE(A96,""price""),"""")"),"") | C96: =IF(B96<>"", NOW(), "")
B97: =IFERROR(__xludf.DUMMYFUNCTION("IFERROR(GOOGLEFINANCE(A97,""price""),"""")"),"") | C97: =IF(B97<>"", NOW(), "")
B98: =IFERROR(__xludf.DUMMYFUNCTION("IFERROR(GOOGLEFINANCE(A98,""price""),"""")"),"") | C98: =IF(B98<>"", NOW(), "")
B99: =IFERROR(__xludf.DUMMYFUNCTION("IFERROR(GOOGLEFINANCE(A99,""price""),"""")"),"") | C99: =IF(B99<>"", NOW(), "")
B100: =IFERROR(__xludf.DUMMYFUNCTION("IFERROR(GOOGLEFINANCE(A100,""price""),"""")"),"") | C100: =IF(B100<>"", NOW(), "")
...

Sheet Dividends
A1: Symbol | B1: IndicatedYield(annual %) | C1: TTM_Dividend($) | D1: NextExDate
A2: YSPY | B2: =IFERROR(__xludf.DUMMYFUNCTION("GOOGLEFINANCE(A2,""yieldpct"")"),"#N/A") -> #N/A | C2: =IFERROR(__xludf.DUMMYFUNCTION("GOOGLEFINANCE(A2, ""dividend"")"),"#N/A") -> #N/A | D2: 45898 | E2: 45900.1
A3: IWMY | B3: =IFERROR(__xludf.DUMMYFUNCTION("(SUBSTITUTE(index(importhtml(""http://finviz.com/quote.ashx?t=""&A3,""table"",10),7,2),""*"",""""))"),"#REF!") -> #REF! | C3: 18.727 | D3: 45897 | E3: 45900.1
A4: ULTY | B4: =IFERROR(__xludf.DUMMYFUNCTION("GOOGLEFINANCE(A4,""yieldpct"")"),"#N/A") -> #N/A | C4: 7.343 | D4: 45897 | E4: 45900.1
A5: TQQY | B5: =IFERROR(__xludf.DUMMYFUNCTION("GOOGLEFINANCE(A5,""yieldpct"")"),"#N/A") -> #N/A | C5: 4.867 | D5: 45898 | E5: 45900.1
A6: PLTY | B6: =IFERROR(__xludf.DUMMYFUNCTION("GOOGLEFINANCE(A6,""yieldpct"")"),"#N/A") -> #N/A | C6: 48.397 | D6: 45883 | E6: 45900.1
A7: COIW | B7: =IFERROR(__xludf.DUMMYFUNCTION("GOOGLEFINANCE(A7,""yieldpct"")"),"#N/A") -> #N/A | C7: 13.773 | D7: 45894 | E7: 45900.1
B8: =IFERROR(__xludf.DUMMYFUNCTION("IFERROR(GOOGLEFINANCE(A8,""yield"")*100,"""")"),"") | C8: =IFERROR(__xludf.DUMMYFUNCTION("IFERROR(GOOGLEFINANCE(A8,""trail_dividend""),"""")"),"") | D8: =IFERROR(__xludf.DUMMYFUNCTION("IFERROR(INDEX(IMPORTXML(""https://finance.yahoo.com/quote/""&A8, ""//td[@data-test='EX_DIVIDEND_DATE-value']""),1),"""")"),"")
B9: =IFERROR(__xludf.DUMMYFUNCTION("IFERROR(GOOGLEFINANCE(A9,""yield"")*100,"""")"),"") | C9: =IFERROR(__xludf.DUMMYFUNCTION("IFERROR(GOOGLEFINANCE(A9,""trail_dividend""),"""")"),"") | D9: =IFERROR(__xludf.DUMMYFUNCTION("IFERROR(INDEX(IMPORTXML(""https://finance.yahoo.com/quote/""&A9, ""//td[@data-test='EX_DIVIDEND_DATE-value']""),1),"""")"),"")
B10: =IFERROR(__xludf.DUMMYFUNCTION("IFERROR(GOOGLEFINANCE(A10,""yield"")*100,"""")"),"") | C10: =IFERROR(__xludf.DUMMYFUNCTION("IFERROR(GOOGLEFINANCE(A10,""trail_dividend""),"""")"),"") | D10: =IFERROR(__xludf.DUMMYFUNCTION("IFERROR(INDEX(IMPORTXML(""https://finance.yahoo.com/quote/""&A10, ""//td[@data-test='EX_DIVIDEND_DATE-value']""),1),"""")"),"")
B11: =IFERROR(__xludf.DUMMYFUNCTION("IFERROR(GOOGLEFINANCE(A11,""yield"")*100,"""")"),"") | C11: =IFERROR(__xludf.DUMMYFUNCTION("IFERROR(GOOGLEFINANCE(A11,""trail_dividend""),"""")"),"") | D11: =IFERROR(__xludf.DUMMYFUNCTION("IFERROR(INDEX(IMPORTXML(""https://finance.yahoo.com/quote/""&A11, ""//td[@data-test='EX_DIVIDEND_DATE-value']""),1),"""")"),"")
B12: =IFERROR(__xludf.DUMMYFUNCTION("IFERROR(GOOGLEFINANCE(A12,""yield"")*100,"""")"),"") | C12: =IFERROR(__xludf.DUMMYFUNCTION("IFERROR(GOOGLEFINANCE(A12,""trail_dividend""),"""")"),"") | D12: =IFERROR(__xludf.DUMMYFUNCTION("IFERROR(INDEX(IMPORTXML(""https://finance.yahoo.com/quote/""&A12, ""//td[@data-test='EX_DIVIDEND_DATE-value']""),1),"""")"),"")
B13: =IFERROR(__xludf.DUMMYFUNCTION("IFERROR(GOOGLEFINANCE(A13,""yield"")*100,"""")"),"") | C13: =IFERROR(__xludf.DUMMYFUNCTION("IFERROR(GOOGLEFINANCE(A13,""trail_dividend""),"""")"),"") | D13: =IFERROR(__xludf.DUMMYFUNCTION("IFERROR(INDEX(IMPORTXML(""https://finance.yahoo.com/quote/""&A13, ""//td[@data-test='EX_DIVIDEND_DATE-value']""),1),"""")"),"")
B14: =IFERROR(__xludf.DUMMYFUNCTION("IFERROR(GOOGLEFINANCE(A14,""yield"")*100,"""")"),"") | C14: =IFERROR(__xludf.DUMMYFUNCTION("IFERROR(GOOGLEFINANCE(A14,""trail_dividend""),"""")"),"") | D14: =IFERROR(__xludf.DUMMYFUNCTION("IFERROR(INDEX(IMPORTXML(""https://finance.yahoo.com/quote/""&A14, ""//td[@data-test='EX_DIVIDEND_DATE-value']""),1),"""")"),"")
B15: =IFERROR(__xludf.DUMMYFUNCTION("IFERROR(GOOGLEFINANCE(A15,""yield"")*100,"""")"),"") | C15: =IFERROR(__xludf.DUMMYFUNCTION("IFERROR(GOOGLEFINANCE(A15,""trail_dividend""),"""")"),"") | D15: =IFERROR(__xludf.DUMMYFUNCTION("IFERROR(INDEX(IMPORTXML(""https://finance.yahoo.com/quote/""&A15, ""//td[@data-test='EX_DIVIDEND_DATE-value']""),1),"""")"),"")
B16: =IFERROR(__xludf.DUMMYFUNCTION("IFERROR(GOOGLEFINANCE(A16,""yield"")*100,"""")"),"") | C16: =IFERROR(__xludf.DUMMYFUNCTION("IFERROR(GOOGLEFINANCE(A16,""trail_dividend""),"""")"),"") | D16: =IFERROR(__xludf.DUMMYFUNCTION("IFERROR(INDEX(IMPORTXML(""https://finance.yahoo.com/quote/""&A16, ""//td[@data-test='EX_DIVIDEND_DATE-value']""),1),"""")"),"")
B17: =IFERROR(__xludf.DUMMYFUNCTION("IFERROR(GOOGLEFINANCE(A17,""yield"")*100,"""")"),"") | C17: =IFERROR(__xludf.DUMMYFUNCTION("IFERROR(GOOGLEFINANCE(A17,""trail_dividend""),"""")"),"") | D17: =IFERROR(__xludf.DUMMYFUNCTION("IFERROR(INDEX(IMPORTXML(""https://finance.yahoo.com/quote/""&A17, ""//td[@data-test='EX_DIVIDEND_DATE-value']""),1),"""")"),"")
B18: =IFERROR(__xludf.DUMMYFUNCTION("IFERROR(GOOGLEFINANCE(A18,""yield"")*100,"""")"),"") | C18: =IFERROR(__xludf.DUMMYFUNCTION("IFERROR(GOOGLEFINANCE(A18,""trail_dividend""),"""")"),"") | D18: =IFERROR(__xludf.DUMMYFUNCTION("IFERROR(INDEX(IMPORTXML(""https://finance.yahoo.com/quote/""&A18, ""//td[@data-test='EX_DIVIDEND_DATE-value']""),1),"""")"),"")
B19: =IFERROR(__xludf.DUMMYFUNCTION("IFERROR(GOOGLEFINANCE(A19,""yield"")*100,"""")"),"") | C19: =IFERROR(__xludf.DUMMYFUNCTION("IFERROR(GOOGLEFINANCE(A19,""trail_dividend""),"""")"),"") | D19: =IFERROR(__xludf.DUMMYFUNCTION("IFERROR(INDEX(IMPORTXML(""https://finance.yahoo.com/quote/""&A19, ""//td[@data-test='EX_DIVIDEND_DATE-value']""),1),"""")"),"")
B20: =IFERROR(__xludf.DUMMYFUNCTION("IFERROR(GOOGLEFINANCE(A20,""yield"")*100,"""")"),"") | C20: =IFERROR(__xludf.DUMMYFUNCTION("IFERROR(GOOGLEFINANCE(A20,""trail_dividend""),"""")"),"") | D20: =IFERROR(__xludf.DUMMYFUNCTION("IFERROR(INDEX(IMPORTXML(""https://finance.yahoo.com/quote/""&A20, ""//td[@data-test='EX_DIVIDEND_DATE-value']""),1),"""")"),"")
B21: =IFERROR(__xludf.DUMMYFUNCTION("IFERROR(GOOGLEFINANCE(A21,""yield"")*100,"""")"),"") | C21: =IFERROR(__xludf.DUMMYFUNCTION("IFERROR(GOOGLEFINANCE(A21,""trail_dividend""),"""")"),"") | D21: =IFERROR(__xludf.DUMMYFUNCTION("IFERROR(INDEX(IMPORTXML(""https://finance.yahoo.com/quote/""&A21, ""//td[@data-test='EX_DIVIDEND_DATE-value']""),1),"""")"),"")
B22: =IFERROR(__xludf.DUMMYFUNCTION("IFERROR(GOOGLEFINANCE(A22,""yield"")*100,"""")"),"") | C22: =IFERROR(__xludf.DUMMYFUNCTION("IFERROR(GOOGLEFINANCE(A22,""trail_dividend""),"""")"),"") | D22: =IFERROR(__xludf.DUMMYFUNCTION("IFERROR(INDEX(IMPORTXML(""https://finance.yahoo.com/quote/""&A22, ""//td[@data-test='EX_DIVIDEND_DATE-value']""),1),"""")"),"")
B23: =IFERROR(__xludf.DUMMYFUNCTION("IFERROR(GOOGLEFINANCE(A23,""yield"")*100,"""")"),"") | C23: =IFERROR(__xludf.DUMMYFUNCTION("IFERROR(GOOGLEFINANCE(A23,""trail_dividend""),"""")"),"") | D23: =IFERROR(__xludf.DUMMYFUNCTION("IFERROR(INDEX(IMPORTXML(""https://finance.yahoo.com/quote/""&A23, ""//td[@data-test='EX_DIVIDEND_DATE-value']""),1),"""")"),"")
B24: =IFERROR(__xludf.DUMMYFUNCTION("IFERROR(GOOGLEFINANCE(A24,""yield"")*100,"""")"),"") | C24: =IFERROR(__xludf.DUMMYFUNCTION("IFERROR(GOOGLEFINANCE(A24,""trail_dividend""),"""")"),"") | D24: =IFERROR(__xludf.DUMMYFUNCTION("IFERROR(INDEX(IMPORTXML(""https://finance.yahoo.com/quote/""&A24, ""//td[@data-test='EX_DIVIDEND_DATE-value']""),1),"""")"),"")
B25: =IFERROR(__xludf.DUMMYFUNCTION("IFERROR(GOOGLEFINANCE(A25,""yield"")*100,"""")"),"") | C25: =IFERROR(__xludf.DUMMYFUNCTION("IFERROR(GOOGLEFINANCE(A25,""trail_dividend""),"""")"),"") | D25: =IFERROR(__xludf.DUMMYFUNCTION("IFERROR(INDEX(IMPORTXML(""https://finance.yahoo.com/quote/""&A25, ""//td[@data-test='EX_DIVIDEND_DATE-value']""),1),"""")"),"")
B26: =IFERROR(__xludf.DUMMYFUNCTION("IFERROR(GOOGLEFINANCE(A26,""yield"")*100,"""")"),"") | C26: =IFERROR(__xludf.DUMMYFUNCTION("IFERROR(GOOGLEFINANCE(A26,""trail_dividend""),"""")"),"") | D26: =IFERROR(__xludf.DUMMYFUNCTION("IFERROR(INDEX(IMPORTXML(""https://finance.yahoo.com/quote/""&A26, ""//td[@data-test='EX_DIVIDEND_DATE-value']""),1),"""")"),"")
B27: =IFERROR(__xludf.DUMMYFUNCTION("IFERROR(GOOGLEFINANCE(A27,""yield"")*100,"""")"),"") | C27: =IFERROR(__xludf.DUMMYFUNCTION("IFERROR(GOOGLEFINANCE(A27,""trail_dividend""),"""")"),"") | D27: =IFERROR(__xludf.DUMMYFUNCTION("IFERROR(INDEX(IMPORTXML(""https://finance.yahoo.com/quote/""&A27, ""//td[@data-test='EX_DIVIDEND_DATE-value']""),1),"""")"),"")
B28: =IFERROR(__xludf.DUMMYFUNCTION("IFERROR(GOOGLEFINANCE(A28,""yield"")*100,"""")"),"") | C28: =IFERROR(__xludf.DUMMYFUNCTION("IFERROR(GOOGLEFINANCE(A28,""trail_dividend""),"""")"),"") | D28: =IFERROR(__xludf.DUMMYFUNCTION("IFERROR(INDEX(IMPORTXML(""https://finance.yahoo.com/quote/""&A28, ""//td[@data-test='EX_DIVIDEND_DATE-value']""),1),"""")"),"")
B29: =IFERROR(__xludf.DUMMYFUNCTION("IFERROR(GOOGLEFINANCE(A29,""yield"")*100,"""")"),"") | C29: =IFERROR(__xludf.DUMMYFUNCTION("IFERROR(GOOGLEFINANCE(A29,""trail_dividend""),"""")"),"") | D29: =IFERROR(__xludf.DUMMYFUNCTION("IFERROR(INDEX(IMPORTXML(""https://finance.yahoo.com/quote/""&A29, ""//td[@data-test='EX_DIVIDEND_DATE-value']""),1),"""")"),"")
B30: =IFERROR(__xludf.DUMMYFUNCTION("IFERROR(GOOGLEFINANCE(A30,""yield"")*100,"""")"),"") | C30: =IFERROR(__xludf.DUMMYFUNCTION("IFERROR(GOOGLEFINANCE(A30,""trail_dividend""),"""")"),"") | D30: =IFERROR(__xludf.DUMMYFUNCTION("IFERROR(INDEX(IMPORTXML(""https://finance.yahoo.com/quote/""&A30, ""//td[@data-test='EX_DIVIDEND_DATE-value']""),1),"""")"),"")
B31: =IFERROR(__xludf.DUMMYFUNCTION("IFERROR(GOOGLEFINANCE(A31,""yield"")*100,"""")"),"") | C31: =IFERROR(__xludf.DUMMYFUNCTION("IFERROR(GOOGLEFINANCE(A31,""trail_dividend""),"""")"),"") | D31: =IFERROR(__xludf.DUMMYFUNCTION("IFERROR(INDEX(IMPORTXML(""https://finance.yahoo.com/quote/""&A31, ""//td[@data-test='EX_DIVIDEND_DATE-value']""),1),"""")"),"")
B32: =IFERROR(__xludf.DUMMYFUNCTION("IFERROR(GOOGLEFINANCE(A32,""yield"")*100,"""")"),"") | C32: =IFERROR(__xludf.DUMMYFUNCTION("IFERROR(GOOGLEFINANCE(A32,""trail_dividend""),"""")"),"") | D32: =IFERROR(__xludf.DUMMYFUNCTION("IFERROR(INDEX(IMPORTXML(""https://finance.yahoo.com/quote/""&A32, ""//td[@data-test='EX_DIVIDEND_DATE-value']""),1),"""")"),"")
B33: =IFERROR(__xludf.DUMMYFUNCTION("IFERROR(GOOGLEFINANCE(A33,""yield"")*100,"""")"),"") | C33: =IFERROR(__xludf.DUMMYFUNCTION("IFERROR(GOOGLEFINANCE(A33,""trail_dividend""),"""")"),"") | D33: =IFERROR(__xludf.DUMMYFUNCTION("IFERROR(INDEX(IMPORTXML(""https://finance.yahoo.com/quote/""&A33, ""//td[@data-test='EX_DIVIDEND_DATE-value']""),1),"""")"),"")
B34: =IFERROR(__xludf.DUMMYFUNCTION("IFERROR(GOOGLEFINANCE(A34,""yield"")*100,"""")"),"") | C34: =IFERROR(__xludf.DUMMYFUNCTION("IFERROR(GOOGLEFINANCE(A34,""trail_dividend""),"""")"),"") | D34: =IFERROR(__xludf.DUMMYFUNCTION("IFERROR(INDEX(IMPORTXML(""https://finance.yahoo.com/quote/""&A34, ""//td[@data-test='EX_DIVIDEND_DATE-value']""),1),"""")"),"")
B35: =IFERROR(__xludf.DUMMYFUNCTION("IFERROR(GOOGLEFINANCE(A35,""yield"")*100,"""")"),"") | C35: =IFERROR(__xludf.DUMMYFUNCTION("IFERROR(GOOGLEFINANCE(A35,""trail_dividend""),"""")"),"") | D35: =IFERROR(__xludf.DUMMYFUNCTION("IFERROR(INDEX(IMPORTXML(""https://finance.yahoo.com/quote/""&A35, ""//td[@data-test='EX_DIVIDEND_DATE-value']""),1),"""")"),"")
B36: =IFERROR(__xludf.DUMMYFUNCTION("IFERROR(GOOGLEFINANCE(A36,""yield"")*100,"""")"),"") | C36: =IFERROR(__xludf.DUMMYFUNCTION("IFERROR(GOOGLEFINANCE(A36,""trail_dividend""),"""")"),"") | D36: =IFERROR(__xludf.DUMMYFUNCTION("IFERROR(INDEX(IMPORTXML(""https://finance.yahoo.com/quote/""&A36, ""//td[@data-test='EX_DIVIDEND_DATE-value']""),1),"""")"),"")
B37: =IFERROR(__xludf.DUMMYFUNCTION("IFERROR(GOOGLEFINANCE(A37,""yield"")*100,"""")"),"") | C37: =IFERROR(__xludf.DUMMYFUNCTION("IFERROR(GOOGLEFINANCE(A37,""trail_dividend""),"""")"),"") | D37: =IFERROR(__xludf.DUMMYFUNCTION("IFERROR(INDEX(IMPORTXML(""https://finance.yahoo.com/quote/""&A37, ""//td[@data-test='EX_DIVIDEND_DATE-value']""),1),"""")"),"")
B38: =IFERROR(__xludf.DUMMYFUNCTION("IFERROR(GOOGLEFINANCE(A38,""yield"")*100,"""")"),"") | C38: =IFERROR(__xludf.DUMMYFUNCTION("IFERROR(GOOGLEFINANCE(A38,""trail_dividend""),"""")"),"") | D38: =IFERROR(__xludf.DUMMYFUNCTION("IFERROR(INDEX(IMPORTXML(""https://finance.yahoo.com/quote/""&A38, ""//td[@data-test='EX_DIVIDEND_DATE-value']""),1),"""")"),"")
B39: =IFERROR(__xludf.DUMMYFUNCTION("IFERROR(GOOGLEFINANCE(A39,""yield"")*100,"""")"),"") | C39: =IFERROR(__xludf.DUMMYFUNCTION("IFERROR(GOOGLEFINANCE(A39,""trail_dividend""),"""")"),"") | D39: =IFERROR(__xludf.DUMMYFUNCTION("IFERROR(INDEX(IMPORTXML(""https://finance.yahoo.com/quote/""&A39, ""//td[@data-test='EX_DIVIDEND_DATE-value']""),1),"""")"),"")
B40: =IFERROR(__xludf.DUMMYFUNCTION("IFERROR(GOOGLEFINANCE(A40,""yield"")*100,"""")"),"") | C40: =IFERROR(__xludf.DUMMYFUNCTION("IFERROR(GOOGLEFINANCE(A40,""trail_dividend""),"""")"),"") | D40: =IFERROR(__xludf.DUMMYFUNCTION("IFERROR(INDEX(IMPORTXML(""https://finance.yahoo.com/quote/""&A40, ""//td[@data-test='EX_DIVIDEND_DATE-value']""),1),"""")"),"")
B41: =IFERROR(__xludf.DUMMYFUNCTION("IFERROR(GOOGLEFINANCE(A41,""yield"")*100,"""")"),"") | C41: =IFERROR(__xludf.DUMMYFUNCTION("IFERROR(GOOGLEFINANCE(A41,""trail_dividend""),"""")"),"") | D41: =IFERROR(__xludf.DUMMYFUNCTION("IFERROR(INDEX(IMPORTXML(""https://finance.yahoo.com/quote/""&A41, ""//td[@data-test='EX_DIVIDEND_DATE-value']""),1),"""")"),"")
B42: =IFERROR(__xludf.DUMMYFUNCTION("IFERROR(GOOGLEFINANCE(A42,""yield"")*100,"""")"),"") | C42: =IFERROR(__xludf.DUMMYFUNCTION("IFERROR(GOOGLEFINANCE(A42,""trail_dividend""),"""")"),"") | D42: =IFERROR(__xludf.DUMMYFUNCTION("IFERROR(INDEX(IMPORTXML(""https://finance.yahoo.com/quote/""&A42, ""//td[@data-test='EX_DIVIDEND_DATE-value']""),1),"""")"),"")
B43: =IFERROR(__xludf.DUMMYFUNCTION("IFERROR(GOOGLEFINANCE(A43,""yield"")*100,"""")"),"") | C43: =IFERROR(__xludf.DUMMYFUNCTION("IFERROR(GOOGLEFINANCE(A43,""trail_dividend""),"""")"),"") | D43: =IFERROR(__xludf.DUMMYFUNCTION("IFERROR(INDEX(IMPORTXML(""https://finance.yahoo.com/quote/""&A43, ""//td[@data-test='EX_DIVIDEND_DATE-value']""),1),"""")"),"")
B44: =IFERROR(__xludf.DUMMYFUNCTION("IFERROR(GOOGLEFINANCE(A44,""yield"")*100,"""")"),"") | C44: =IFERROR(__xludf.DUMMYFUNCTION("IFERROR(GOOGLEFINANCE(A44,""trail_dividend""),"""")"),"") | D44: =IFERROR(__xludf.DUMMYFUNCTION("IFERROR(INDEX(IMPORTXML(""https://finance.yahoo.com/quote/""&A44, ""//td[@data-test='EX_DIVIDEND_DATE-value']""),1),"""")"),"")
B45: =IFERROR(__xludf.DUMMYFUNCTION("IFERROR(GOOGLEFINANCE(A45,""yield"")*100,"""")"),"") | C45: =IFERROR(__xludf.DUMMYFUNCTION("IFERROR(GOOGLEFINANCE(A45,""trail_dividend""),"""")"),"") | D45: =IFERROR(__xludf.DUMMYFUNCTION("IFERROR(INDEX(IMPORTXML(""https://finance.yahoo.com/quote/""&A45, ""//td[@data-test='EX_DIVIDEND_DATE-value']""),1),"""")"),"")
B46: =IFERROR(__xludf.DUMMYFUNCTION("IFERROR(GOOGLEFINANCE(A46,""yield"")*100,"""")"),"") | C46: =IFERROR(__xludf.DUMMYFUNCTION("IFERROR(GOOGLEFINANCE(A46,""trail_dividend""),"""")"),"") | D46: =IFERROR(__xludf.DUMMYFUNCTION("IFERROR(INDEX(IMPORTXML(""https://finance.yahoo.com/quote/""&A46, ""//td[@data-test='EX_DIVIDEND_DATE-value']""),1),"""")"),"")
B47: =IFERROR(__xludf.DUMMYFUNCTION("IFERROR(GOOGLEFINANCE(A47,""yield"")*100,"""")"),"") | C47: =IFERROR(__xludf.DUMMYFUNCTION("IFERROR(GOOGLEFINANCE(A47,""trail_dividend""),"""")"),"") | D47: =IFERROR(__xludf.DUMMYFUNCTION("IFERROR(INDEX(IMPORTXML(""https://finance.yahoo.com/quote/""&A47, ""//td[@data-test='EX_DIVIDEND_DATE-value']""),1),"""")"),"")
B48: =IFERROR(__xludf.DUMMYFUNCTION("IFERROR(GOOGLEFINANCE(A48,""yield"")*100,"""")"),"") | C48: =IFERROR(__xludf.DUMMYFUNCTION("IFERROR(GOOGLEFINANCE(A48,""trail_dividend""),"""")"),"") | D48: =IFERROR(__xludf.DUMMYFUNCTION("IFERROR(INDEX(IMPORTXML(""https://finance.yahoo.com/quote/""&A48, ""//td[@data-test='EX_DIVIDEND_DATE-value']""),1),"""")"),"")
B49: =IFERROR(__xludf.DUMMYFUNCTION("IFERROR(GOOGLEFINANCE(A49,""yield"")*100,"""")"),"") | C49: =IFERROR(__xludf.DUMMYFUNCTION("IFERROR(GOOGLEFINANCE(A49,""trail_dividend""),"""")"),"") | D49: =IFERROR(__xludf.DUMMYFUNCTION("IFERROR(INDEX(IMPORTXML(""https://finance.yahoo.com/quote/""&A49, ""//td[@data-test='EX_DIVIDEND_DATE-value']""),1),"""")"),"")
B50: =IFERROR(__xludf.DUMMYFUNCTION("IFERROR(GOOGLEFINANCE(A50,""yield"")*100,"""")"),"") | C50: =IFERROR(__xludf.DUMMYFUNCTION("IFERROR(GOOGLEFINANCE(A50,""trail_dividend""),"""")"),"") | D50: =IFERROR(__xludf.DUMMYFUNCTION("IFERROR(INDEX(IMPORTXML(""https://finance.yahoo.com/quote/""&A50, ""//td[@data-test='EX_DIVIDEND_DATE-value']""),1),"""")"),"")
B51: =IFERROR(__xludf.DUMMYFUNCTION("IFERROR(GOOGLEFINANCE(A51,""yield"")*100,"""")"),"") | C51: =IFERROR(__xludf.DUMMYFUNCTION("IFERROR(GOOGLEFINANCE(A51,""trail_dividend""),"""")"),"") | D51: =IFERROR(__xludf.DUMMYFUNCTION("IFERROR(INDEX(IMPORTXML(""https://finance.yahoo.com/quote/""&A51, ""//td[@data-test='EX_DIVIDEND_DATE-value']""),1),"""")"),"")
B52: =IFERROR(__xludf.DUMMYFUNCTION("IFERROR(GOOGLEFINANCE(A52,""yield"")*100,"""")"),"") | C52: =IFERROR(__xludf.DUMMYFUNCTION("IFERROR(GOOGLEFINANCE(A52,""trail_dividend""),"""")"),"") | D52: =IFERROR(__xludf.DUMMYFUNCTION("IFERROR(INDEX(IMPORTXML(""https://finance.yahoo.com/quote/""&A52, ""//td[@data-test='EX_DIVIDEND_DATE-value']""),1),"""")"),"")
B53: =IFERROR(__xludf.DUMMYFUNCTION("IFERROR(GOOGLEFINANCE(A53,""yield"")*100,"""")"),"") | C53: =IFERROR(__xludf.DUMMYFUNCTION("IFERROR(GOOGLEFINANCE(A53,""trail_dividend""),"""")"),"") | D53: =IFERROR(__xludf.DUMMYFUNCTION("IFERROR(INDEX(IMPORTXML(""https://finance.yahoo.com/quote/""&A53, ""//td[@data-test='EX_DIVIDEND_DATE-value']""),1),"""")"),"")
B54: =IFERROR(__xludf.DUMMYFUNCTION("IFERROR(GOOGLEFINANCE(A54,""yield"")*100,"""")"),"") | C54: =IFERROR(__xludf.DUMMYFUNCTION("IFERROR(GOOGLEFINANCE(A54,""trail_dividend""),"""")"),"") | D54: =IFERROR(__xludf.DUMMYFUNCTION("IFERROR(INDEX(IMPORTXML(""https://finance.yahoo.com/quote/""&A54, ""//td[@data-test='EX_DIVIDEND_DATE-value']""),1),"""")"),"")
B55: =IFERROR(__xludf.DUMMYFUNCTION("IFERROR(GOOGLEFINANCE(A55,""yield"")*100,"""")"),"") | C55: =IFERROR(__xludf.DUMMYFUNCTION("IFERROR(GOOGLEFINANCE(A55,""trail_dividend""),"""")"),"") | D55: =IFERROR(__xludf.DUMMYFUNCTION("IFERROR(INDEX(IMPORTXML(""https://finance.yahoo.com/quote/""&A55, ""//td[@data-test='EX_DIVIDEND_DATE-value']""),1),"""")"),"")
B56: =IFERROR(__xludf.DUMMYFUNCTION("IFERROR(GOOGLEFINANCE(A56,""yield"")*100,"""")"),"") | C56: =IFERROR(__xludf.DUMMYFUNCTION("IFERROR(GOOGLEFINANCE(A56,""trail_dividend""),"""")"),"") | D56: =IFERROR(__xludf.DUMMYFUNCTION("IFERROR(INDEX(IMPORTXML(""https://finance.yahoo.com/quote/""&A56, ""//td[@data-test='EX_DIVIDEND_DATE-value']""),1),"""")"),"")
B57: =IFERROR(__xludf.DUMMYFUNCTION("IFERROR(GOOGLEFINANCE(A57,""yield"")*100,"""")"),"") | C57: =IFERROR(__xludf.DUMMYFUNCTION("IFERROR(GOOGLEFINANCE(A57,""trail_dividend""),"""")"),"") | D57: =IFERROR(__xludf.DUMMYFUNCTION("IFERROR(INDEX(IMPORTXML(""https://finance.yahoo.com/quote/""&A57, ""//td[@data-test='EX_DIVIDEND_DATE-value']""),1),"""")"),"")
B58: =IFERROR(__xludf.DUMMYFUNCTION("IFERROR(GOOGLEFINANCE(A58,""yield"")*100,"""")"),"") | C58: =IFERROR(__xludf.DUMMYFUNCTION("IFERROR(GOOGLEFINANCE(A58,""trail_dividend""),"""")"),"") | D58: =IFERROR(__xludf.DUMMYFUNCTION("IFERROR(INDEX(IMPORTXML(""https://finance.yahoo.com/quote/""&A58, ""//td[@data-test='EX_DIVIDEND_DATE-value']""),1),"""")"),"")
B59: =IFERROR(__xludf.DUMMYFUNCTION("IFERROR(GOOGLEFINANCE(A59,""yield"")*100,"""")"),"") | C59: =IFERROR(__xludf.DUMMYFUNCTION("IFERROR(GOOGLEFINANCE(A59,""trail_dividend""),"""")"),"") | D59: =IFERROR(__xludf.DUMMYFUNCTION("IFERROR(INDEX(IMPORTXML(""https://finance.yahoo.com/quote/""&A59, ""//td[@data-test='EX_DIVIDEND_DATE-value']""),1),"""")"),"")
B60: =IFERROR(__xludf.DUMMYFUNCTION("IFERROR(GOOGLEFINANCE(A60,""yield"")*100,"""")"),"") | C60: =IFERROR(__xludf.DUMMYFUNCTION("IFERROR(GOOGLEFINANCE(A60,""trail_dividend""),"""")"),"") | D60: =IFERROR(__xludf.DUMMYFUNCTION("IFERROR(INDEX(IMPORTXML(""https://finance.yahoo.com/quote/""&A60, ""//td[@data-test='EX_DIVIDEND_DATE-value']""),1),"""")"),"")
B61: =IFERROR(__xludf.DUMMYFUNCTION("IFERROR(GOOGLEFINANCE(A61,""yield"")*100,"""")"),"") | C61: =IFERROR(__xludf.DUMMYFUNCTION("IFERROR(GOOGLEFINANCE(A61,""trail_dividend""),"""")"),"") | D61: =IFERROR(__xludf.DUMMYFUNCTION("IFERROR(INDEX(IMPORTXML(""https://finance.yahoo.com/quote/""&A61, ""//td[@data-test='EX_DIVIDEND_DATE-value']""),1),"""")"),"")
B62: =IFERROR(__xludf.DUMMYFUNCTION("IFERROR(GOOGLEFINANCE(A62,""yield"")*100,"""")"),"") | C62: =IFERROR(__xludf.DUMMYFUNCTION("IFERROR(GOOGLEFINANCE(A62,""trail_dividend""),"""")"),"") | D62: =IFERROR(__xludf.DUMMYFUNCTION("IFERROR(INDEX(IMPORTXML(""https://finance.yahoo.com/quote/""&A62, ""//td[@data-test='EX_DIVIDEND_DATE-value']""),1),"""")"),"")
B63: =IFERROR(__xludf.DUMMYFUNCTION("IFERROR(GOOGLEFINANCE(A63,""yield"")*100,"""")"),"") | C63: =IFERROR(__xludf.DUMMYFUNCTION("IFERROR(GOOGLEFINANCE(A63,""trail_dividend""),"""")"),"") | D63: =IFERROR(__xludf.DUMMYFUNCTION("IFERROR(INDEX(IMPORTXML(""https://finance.yahoo.com/quote/""&A63, ""//td[@data-test='EX_DIVIDEND_DATE-value']""),1),"""")"),"")
B64: =IFERROR(__xludf.DUMMYFUNCTION("IFERROR(GOOGLEFINANCE(A64,""yield"")*100,"""")"),"") | C64: =IFERROR(__xludf.DUMMYFUNCTION("IFERROR(GOOGLEFINANCE(A64,""trail_dividend""),"""")"),"") | D64: =IFERROR(__xludf.DUMMYFUNCTION("IFERROR(INDEX(IMPORTXML(""https://finance.yahoo.com/quote/""&A64, ""//td[@data-test='EX_DIVIDEND_DATE-value']""),1),"""")"),"")
B65: =IFERROR(__xludf.DUMMYFUNCTION("IFERROR(GOOGLEFINANCE(A65,""yield"")*100,"""")"),"") | C65: =IFERROR(__xludf.DUMMYFUNCTION("IFERROR(GOOGLEFINANCE(A65,""trail_dividend""),"""")"),"") | D65: =IFERROR(__xludf.DUMMYFUNCTION("IFERROR(INDEX(IMPORTXML(""https://finance.yahoo.com/quote/""&A65, ""//td[@data-test='EX_DIVIDEND_DATE-value']""),1),"""")"),"")
B66: =IFERROR(__xludf.DUMMYFUNCTION("IFERROR(GOOGLEFINANCE(A66,""yield"")*100,"""")"),"") | C66: =IFERROR(__xludf.DUMMYFUNCTION("IFERROR(GOOGLEFINANCE(A66,""trail_dividend""),"""")"),"") | D66: =IFERROR(__xludf.DUMMYFUNCTION("IFERROR(INDEX(IMPORTXML(""https://finance.yahoo.com/quote/""&A66, ""//td[@data-test='EX_DIVIDEND_DATE-value']""),1),"""")"),"")
B67: =IFERROR(__xludf.DUMMYFUNCTION("IFERROR(GOOGLEFINANCE(A67,""yield"")*100,"""")"),"") | C67: =IFERROR(__xludf.DUMMYFUNCTION("IFERROR(GOOGLEFINANCE(A67,""trail_dividend""),"""")"),"") | D67: =IFERROR(__xludf.DUMMYFUNCTION("IFERROR(INDEX(IMPORTXML(""https://finance.yahoo.com/quote/""&A67, ""//td[@data-test='EX_DIVIDEND_DATE-value']""),1),"""")"),"")
B68: =IFERROR(__xludf.DUMMYFUNCTION("IFERROR(GOOGLEFINANCE(A68,""yield"")*100,"""")"),"") | C68: =IFERROR(__xludf.DUMMYFUNCTION("IFERROR(GOOGLEFINANCE(A68,""trail_dividend""),"""")"),"") | D68: =IFERROR(__xludf.DUMMYFUNCTION("IFERROR(INDEX(IMPORTXML(""https://finance.yahoo.com/quote/""&A68, ""//td[@data-test='EX_DIVIDEND_DATE-value']""),1),"""")"),"")
B69: =IFERROR(__xludf.DUMMYFUNCTION("IFERROR(GOOGLEFINANCE(A69,""yield"")*100,"""")"),"") | C69: =IFERROR(__xludf.DUMMYFUNCTION("IFERROR(GOOGLEFINANCE(A69,""trail_dividend""),"""")"),"") | D69: =IFERROR(__xludf.DUMMYFUNCTION("IFERROR(INDEX(IMPORTXML(""https://finance.yahoo.com/quote/""&A69, ""//td[@data-test='EX_DIVIDEND_DATE-value']""),1),"""")"),"")
B70: =IFERROR(__xludf.DUMMYFUNCTION("IFERROR(GOOGLEFINANCE(A70,""yield"")*100,"""")"),"") | C70: =IFERROR(__xludf.DUMMYFUNCTION("IFERROR(GOOGLEFINANCE(A70,""trail_dividend""),"""")"),"") | D70: =IFERROR(__xludf.DUMMYFUNCTION("IFERROR(INDEX(IMPORTXML(""https://finance.yahoo.com/quote/""&A70, ""//td[@data-test='EX_DIVIDEND_DATE-value']""),1),"""")"),"")
B71: =IFERROR(__xludf.DUMMYFUNCTION("IFERROR(GOOGLEFINANCE(A71,""yield"")*100,"""")"),"") | C71: =IFERROR(__xludf.DUMMYFUNCTION("IFERROR(GOOGLEFINANCE(A71,""trail_dividend""),"""")"),"") | D71: =IFERROR(__xludf.DUMMYFUNCTION("IFERROR(INDEX(IMPORTXML(""https://finance.yahoo.com/quote/""&A71, ""//td[@data-test='EX_DIVIDEND_DATE-value']""),1),"""")"),"")
B72: =IFERROR(__xludf.DUMMYFUNCTION("IFERROR(GOOGLEFINANCE(A72,""yield"")*100,"""")"),"") | C72: =IFERROR(__xludf.DUMMYFUNCTION("IFERROR(GOOGLEFINANCE(A72,""trail_dividend""),"""")"),"") | D72: =IFERROR(__xludf.DUMMYFUNCTION("IFERROR(INDEX(IMPORTXML(""https://finance.yahoo.com/quote/""&A72, ""//td[@data-test='EX_DIVIDEND_DATE-value']""),1),"""")"),"")
B73: =IFERROR(__xludf.DUMMYFUNCTION("IFERROR(GOOGLEFINANCE(A73,""yield"")*100,"""")"),"") | C73: =IFERROR(__xludf.DUMMYFUNCTION("IFERROR(GOOGLEFINANCE(A73,""trail_dividend""),"""")"),"") | D73: =IFERROR(__xludf.DUMMYFUNCTION("IFERROR(INDEX(IMPORTXML(""https://finance.yahoo.com/quote/""&A73, ""//td[@data-test='EX_DIVIDEND_DATE-value']""),1),"""")"),"")
B74: =IFERROR(__xludf.DUMMYFUNCTION("IFERROR(GOOGLEFINANCE(A74,""yield"")*100,"""")"),"") | C74: =IFERROR(__xludf.DUMMYFUNCTION("IFERROR(GOOGLEFINANCE(A74,""trail_dividend""),"""")"),"") | D74: =IFERROR(__xludf.DUMMYFUNCTION("IFERROR(INDEX(IMPORTXML(""https://finance.yahoo.com/quote/""&A74, ""//td[@data-test='EX_DIVIDEND_DATE-value']""),1),"""")"),"")
B75: =IFERROR(__xludf.DUMMYFUNCTION("IFERROR(GOOGLEFINANCE(A75,""yield"")*100,"""")"),"") | C75: =IFERROR(__xludf.DUMMYFUNCTION("IFERROR(GOOGLEFINANCE(A75,""trail_dividend""),"""")"),"") | D75: =IFERROR(__xludf.DUMMYFUNCTION("IFERROR(INDEX(IMPORTXML(""https://finance.yahoo.com/quote/""&A75, ""//td[@data-test='EX_DIVIDEND_DATE-value']""),1),"""")"),"")
B76: =IFERROR(__xludf.DUMMYFUNCTION("IFERROR(GOOGLEFINANCE(A76,""yield"")*100,"""")"),"") | C76: =IFERROR(__xludf.DUMMYFUNCTION("IFERROR(GOOGLEFINANCE(A76,""trail_dividend""),"""")"),"") | D76: =IFERROR(__xludf.DUMMYFUNCTION("IFERROR(INDEX(IMPORTXML(""https://finance.yahoo.com/quote/""&A76, ""//td[@data-test='EX_DIVIDEND_DATE-value']""),1),"""")"),"")
B77: =IFERROR(__xludf.DUMMYFUNCTION("IFERROR(GOOGLEFINANCE(A77,""yield"")*100,"""")"),"") | C77: =IFERROR(__xludf.DUMMYFUNCTION("IFERROR(GOOGLEFINANCE(A77,""trail_dividend""),"""")"),"") | D77: =IFERROR(__xludf.DUMMYFUNCTION("IFERROR(INDEX(IMPORTXML(""https://finance.yahoo.com/quote/""&A77, ""//td[@data-test='EX_DIVIDEND_DATE-value']""),1),"""")"),"")
B78: =IFERROR(__xludf.DUMMYFUNCTION("IFERROR(GOOGLEFINANCE(A78,""yield"")*100,"""")"),"") | C78: =IFERROR(__xludf.DUMMYFUNCTION("IFERROR(GOOGLEFINANCE(A78,""trail_dividend""),"""")"),"") | D78: =IFERROR(__xludf.DUMMYFUNCTION("IFERROR(INDEX(IMPORTXML(""https://finance.yahoo.com/quote/""&A78, ""//td[@data-test='EX_DIVIDEND_DATE-value']""),1),"""")"),"")
B79: =IFERROR(__xludf.DUMMYFUNCTION("IFERROR(GOOGLEFINANCE(A79,""yield"")*100,"""")"),"") | C79: =IFERROR(__xludf.DUMMYFUNCTION("IFERROR(GOOGLEFINANCE(A79,""trail_dividend""),"""")"),"") | D79: =IFERROR(__xludf.DUMMYFUNCTION("IFERROR(INDEX(IMPORTXML(""https://finance.yahoo.com/quote/""&A79, ""//td[@data-test='EX_DIVIDEND_DATE-value']""),1),"""")"),"")
B80: =IFERROR(__xludf.DUMMYFUNCTION("IFERROR(GOOGLEFINANCE(A80,""yield"")*100,"""")"),"") | C80: =IFERROR(__xludf.DUMMYFUNCTION("IFERROR(GOOGLEFINANCE(A80,""trail_dividend""),"""")"),"") | D80: =IFERROR(__xludf.DUMMYFUNCTION("IFERROR(INDEX(IMPORTXML(""https://finance.yahoo.com/quote/""&A80, ""//td[@data-test='EX_DIVIDEND_DATE-value']""),1),"""")"),"")
B81: =IFERROR(__xludf.DUMMYFUNCTION("IFERROR(GOOGLEFINANCE(A81,""yield"")*100,"""")"),"") | C81: =IFERROR(__xludf.DUMMYFUNCTION("IFERROR(GOOGLEFINANCE(A81,""trail_dividend""),"""")"),"") | D81: =IFERROR(__xludf.DUMMYFUNCTION("IFERROR(INDEX(IMPORTXML(""https://finance.yahoo.com/quote/""&A81, ""//td[@data-test='EX_DIVIDEND_DATE-value']""),1),"""")"),"")
B82: =IFERROR(__xludf.DUMMYFUNCTION("IFERROR(GOOGLEFINANCE(A82,""yield"")*100,"""")"),"") | C82: =IFERROR(__xludf.DUMMYFUNCTION("IFERROR(GOOGLEFINANCE(A82,""trail_dividend""),"""")"),"") | D82: =IFERROR(__xludf.DUMMYFUNCTION("IFERROR(INDEX(IMPORTXML(""https://finance.yahoo.com/quote/""&A82, ""//td[@data-test='EX_DIVIDEND_DATE-value']""),1),"""")"),"")
B83: =IFERROR(__xludf.DUMMYFUNCTION("IFERROR(GOOGLEFINANCE(A83,""yield"")*100,"""")"),"") | C83: =IFERROR(__xludf.DUMMYFUNCTION("IFERROR(GOOGLEFINANCE(A83,""trail_dividend""),"""")"),"") | D83: =IFERROR(__xludf.DUMMYFUNCTION("IFERROR(INDEX(IMPORTXML(""https://finance.yahoo.com/quote/""&A83, ""//td[@data-test='EX_DIVIDEND_DATE-value']""),1),"""")"),"")
B84: =IFERROR(__xludf.DUMMYFUNCTION("IFERROR(GOOGLEFINANCE(A84,""yield"")*100,"""")"),"") | C84: =IFERROR(__xludf.DUMMYFUNCTION("IFERROR(GOOGLEFINANCE(A84,""trail_dividend""),"""")"),"") | D84: =IFERROR(__xludf.DUMMYFUNCTION("IFERROR(INDEX(IMPORTXML(""https://finance.yahoo.com/quote/""&A84, ""//td[@data-test='EX_DIVIDEND_DATE-value']""),1),"""")"),"")
B85: =IFERROR(__xludf.DUMMYFUNCTION("IFERROR(GOOGLEFINANCE(A85,""yield"")*100,"""")"),"") | C85: =IFERROR(__xludf.DUMMYFUNCTION("IFERROR(GOOGLEFINANCE(A85,""trail_dividend""),"""")"),"") | D85: =IFERROR(__xludf.DUMMYFUNCTION("IFERROR(INDEX(IMPORTXML(""https://finance.yahoo.com/quote/""&A85, ""//td[@data-test='EX_DIVIDEND_DATE-value']""),1),"""")"),"")
B86: =IFERROR(__xludf.DUMMYFUNCTION("IFERROR(GOOGLEFINANCE(A86,""yield"")*100,"""")"),"") | C86: =IFERROR(__xludf.DUMMYFUNCTION("IFERROR(GOOGLEFINANCE(A86,""trail_dividend""),"""")"),"") | D86: =IFERROR(__xludf.DUMMYFUNCTION("IFERROR(INDEX(IMPORTXML(""https://finance.yahoo.com/quote/""&A86, ""//td[@data-test='EX_DIVIDEND_DATE-value']""),1),"""")"),"")
B87: =IFERROR(__xludf.DUMMYFUNCTION("IFERROR(GOOGLEFINANCE(A87,""yield"")*100,"""")"),"") | C87: =IFERROR(__xludf.DUMMYFUNCTION("IFERROR(GOOGLEFINANCE(A87,""trail_dividend""),"""")"),"") | D87: =IFERROR(__xludf.DUMMYFUNCTION("IFERROR(INDEX(IMPORTXML(""https://finance.yahoo.com/quote/""&A87, ""//td[@data-test='EX_DIVIDEND_DATE-value']""),1),"""")"),"")
B88: =IFERROR(__xludf.DUMMYFUNCTION("IFERROR(GOOGLEFINANCE(A88,""yield"")*100,"""")"),"") | C88: =IFERROR(__xludf.DUMMYFUNCTION("IFERROR(GOOGLEFINANCE(A88,""trail_dividend""),"""")"),"") | D88: =IFERROR(__xludf.DUMMYFUNCTION("IFERROR(INDEX(IMPORTXML(""https://finance.yahoo.com/quote/""&A88, ""//td[@data-test='EX_DIVIDEND_DATE-value']""),1),"""")"),"")
B89: =IFERROR(__xludf.DUMMYFUNCTION("IFERROR(GOOGLEFINANCE(A89,""yield"")*100,"""")"),"") | C89: =IFERROR(__xludf.DUMMYFUNCTION("IFERROR(GOOGLEFINANCE(A89,""trail_dividend""),"""")"),"") | D89: =IFERROR(__xludf.DUMMYFUNCTION("IFERROR(INDEX(IMPORTXML(""https://finance.yahoo.com/quote/""&A89, ""//td[@data-test='EX_DIVIDEND_DATE-value']""),1),"""")"),"")
B90: =IFERROR(__xludf.DUMMYFUNCTION("IFERROR(GOOGLEFINANCE(A90,""yield"")*100,"""")"),"") | C90: =IFERROR(__xludf.DUMMYFUNCTION("IFERROR(GOOGLEFINANCE(A90,""trail_dividend""),"""")"),"") | D90: =IFERROR(__xludf.DUMMYFUNCTION("IFERROR(INDEX(IMPORTXML(""https://finance.yahoo.com/quote/""&A90, ""//td[@data-test='EX_DIVIDEND_DATE-value']""),1),"""")"),"")
B91: =IFERROR(__xludf.DUMMYFUNCTION("IFERROR(GOOGLEFINANCE(A91,""yield"")*100,"""")"),"") | C91: =IFERROR(__xludf.DUMMYFUNCTION("IFERROR(GOOGLEFINANCE(A91,""trail_dividend""),"""")"),"") | D91: =IFERROR(__xludf.DUMMYFUNCTION("IFERROR(INDEX(IMPORTXML(""https://finance.yahoo.com/quote/""&A91, ""//td[@data-test='EX_DIVIDEND_DATE-value']""),1),"""")"),"")
B92: =IFERROR(__xludf.DUMMYFUNCTION("IFERROR(GOOGLEFINANCE(A92,""yield"")*100,"""")"),"") | C92: =IFERROR(__xludf.DUMMYFUNCTION("IFERROR(GOOGLEFINANCE(A92,""trail_dividend""),"""")"),"") | D92: =IFERROR(__xludf.DUMMYFUNCTION("IFERROR(INDEX(IMPORTXML(""https://finance.yahoo.com/quote/""&A92, ""//td[@data-test='EX_DIVIDEND_DATE-value']""),1),"""")"),"")
B93: =IFERROR(__xludf.DUMMYFUNCTION("IFERROR(GOOGLEFINANCE(A93,""yield"")*100,"""")"),"") | C93: =IFERROR(__xludf.DUMMYFUNCTION("IFERROR(GOOGLEFINANCE(A93,""trail_dividend""),"""")"),"") | D93: =IFERROR(__xludf.DUMMYFUNCTION("IFERROR(INDEX(IMPORTXML(""https://finance.yahoo.com/quote/""&A93, ""//td[@data-test='EX_DIVIDEND_DATE-value']""),1),"""")"),"")
B94: =IFERROR(__xludf.DUMMYFUNCTION("IFERROR(GOOGLEFINANCE(A94,""yield"")*100,"""")"),"") | C94: =IFERROR(__xludf.DUMMYFUNCTION("IFERROR(GOOGLEFINANCE(A94,""trail_dividend""),"""")"),"") | D94: =IFERROR(__xludf.DUMMYFUNCTION("IFERROR(INDEX(IMPORTXML(""https://finance.yahoo.com/quote/""&A94, ""//td[@data-test='EX_DIVIDEND_DATE-value']""),1),"""")"),"")
B95: =IFERROR(__xludf.DUMMYFUNCTION("IFERROR(GOOGLEFINANCE(A95,""yield"")*100,"""")"),"") | C95: =IFERROR(__xludf.DUMMYFUNCTION("IFERROR(GOOGLEFINANCE(A95,""trail_dividend""),"""")"),"") | D95: =IFERROR(__xludf.DUMMYFUNCTION("IFERROR(INDEX(IMPORTXML(""https://finance.yahoo.com/quote/""&A95, ""//td[@data-test='EX_DIVIDEND_DATE-value']""),1),"""")"),"")
B96: =IFERROR(__xludf.DUMMYFUNCTION("IFERROR(GOOGLEFINANCE(A96,""yield"")*100,"""")"),"") | C96: =IFERROR(__xludf.DUMMYFUNCTION("IFERROR(GOOGLEFINANCE(A96,""trail_dividend""),"""")"),"") | D96: =IFERROR(__xludf.DUMMYFUNCTION("IFERROR(INDEX(IMPORTXML(""https://finance.yahoo.com/quote/""&A96, ""//td[@data-test='EX_DIVIDEND_DATE-value']""),1),"""")"),"")
B97: =IFERROR(__xludf.DUMMYFUNCTION("IFERROR(GOOGLEFINANCE(A97,""yield"")*100,"""")"),"") | C97: =IFERROR(__xludf.DUMMYFUNCTION("IFERROR(GOOGLEFINANCE(A97,""trail_dividend""),"""")"),"") | D97: =IFERROR(__xludf.DUMMYFUNCTION("IFERROR(INDEX(IMPORTXML(""https://finance.yahoo.com/quote/""&A97, ""//td[@data-test='EX_DIVIDEND_DATE-value']""),1),"""")"),"")
B98: =IFERROR(__xludf.DUMMYFUNCTION("IFERROR(GOOGLEFINANCE(A98,""yield"")*100,"""")"),"") | C98: =IFERROR(__xludf.DUMMYFUNCTION("IFERROR(GOOGLEFINANCE(A98,""trail_dividend""),"""")"),"") | D98: =IFERROR(__xludf.DUMMYFUNCTION("IFERROR(INDEX(IMPORTXML(""https://finance.yahoo.com/quote/""&A98, ""//td[@data-test='EX_DIVIDEND_DATE-value']""),1),"""")"),"")
B99: =IFERROR(__xludf.DUMMYFUNCTION("IFERROR(GOOGLEFINANCE(A99,""yield"")*100,"""")"),"") | C99: =IFERROR(__xludf.DUMMYFUNCTION("IFERROR(GOOGLEFINANCE(A99,""trail_dividend""),"""")"),"") | D99: =IFERROR(__xludf.DUMMYFUNCTION("IFERROR(INDEX(IMPORTXML(""https://finance.yahoo.com/quote/""&A99, ""//td[@data-test='EX_DIVIDEND_DATE-value']""),1),"""")"),"")
B100: =IFERROR(__xludf.DUMMYFUNCTION("IFERROR(GOOGLEFINANCE(A100,""yield"")*100,"""")"),"") | C100: =IFERROR(__xludf.DUMMYFUNCTION("IFERROR(GOOGLEFINANCE(A100,""trail_dividend""),"""")"),"") | D100: =IFERROR(__xludf.DUMMYFUNCTION("IFERROR(INDEX(IMPORTXML(""https://finance.yahoo.com/quote/""&A100, ""//td[@data-test='EX_DIVIDEND_DATE-value']""),1),"""")"),"")
...

Sheet Fetched Finviz Data

Sheet Dashboard
A1: KPI | B1: Value | C1: Goal | D1: Remaining | E1: AsOf
A2: Stocks/ETFs Equity | B2: 0 | E2: 45906.471 | H2: Tile | I2: Value
A3: Crypto Equity | B3: 0 | E3: 45906.471 | H3: Stocks/ETFs Equity | I3: 0
A4: Monthly Income (est) | B4: 0 | E4: 45906.471 | H4: Anchor Equity | I4: 0
A5: Total Maint Req | B5: 0 | E5: 45906.471 | H5: High-Risk Equity | I5: 0
H6: Crypto Equity | I6: 0
A8: Bucket | B8: Equity | D8: Date | E8: Projected Monthly $
A9: Anchor | B9: 60 | D9: 45906 | E9: 0
A10: High-Risk | B10: 40 | D10: 45936 | E10: 0
A11: Crypto | B11: 0 | D11: 45967 | E11: 0
D12: 45997 | E12: 0
D13: 46028 | E13: 0
D14: 46059 | E14: 0
D15: 46087 | E15: 0
D16: 46118 | E16: 0
D17: 46148 | E17: 0
D18: 46179 | E18: 0
D19: 46209 | E19: 0
D20: 46240 | E20: 0

Sheet Holdings
A1: Symbol | B1: Cat_EQTY Split | C1: StartShares | D1: CumShares | E1: Current Price | F1: Avg Price | G1: UsedAnnualYield (%) | H1: NewShares (from Purchases) | I1: TotalShares | J1: Equity ($) | K1: MonthlyIncome ($) | L1: Weight
A2: YSPY | B2: Anchor 60% | C2: 16 | F2: =IFERROR(VLOOKUP(A2, Prices!A:B, 2, FALSE), ) -> 19.95 | G2: =IFERROR(VLOOKUP(A2, Dividends!$A:$B, 2, FALSE), IFERROR( (VLOOKUP(A2, Dividends!$A:$C, 3, FALSE) / VLOOKUP(A2, Prices!$A:$B, 2, FALSE)) * 100, Inputs!$B$4*100 )) -> 65 | H2: =IFERROR(SUMIF(Purchases!B:B, A2, Purchases!D:D), 0) -> 0 | I2: =C2+H2 -> 16 | J2: =IF(I2>0, I2*F2, 0) -> 319.2 | K2: =IF(J2>0, J2 * IF(G2>0, G2/100, IFERROR( VLOOKUP(A2, Dividends!$A:$C, 3, FALSE) / VLOOKUP(A2, Prices!$A:$B, 2, FALSE), Inputs!$B$4) ) / 12, 0) -> 17.29 | L2: =IFERROR(J2 / SUM($J$2:$J1000), 0) -> 0.15906871
A3: IWMY | B3: Anchor 60% | C3: 14 | F3: =IFERROR(VLOOKUP(A3, Prices!A:B, 2, FALSE), ) -> 23.14 | G3: =IFERROR(VLOOKUP(A3, Dividends!$A:$B, 2, FALSE), IFERROR( (VLOOKUP(A3, Dividends!$A:$C, 3, FALSE) / VLOOKUP(A3, Prices!$A:$B, 2, FALSE)) * 100, Inputs!$B$4*100 )) -> 80.929127 | H3: =IFERROR(SUMIF(Purchases!B:B, A3, Purchases!D:D), 0) -> 0 | I3: =C3+H3 -> 14 | J3: =IF(I3>0, I3*F3, 0) -> 323.96 | K3: =IF(J3>0, J3 * IF(G3>0, G3/100, IFERROR( VLOOKUP(A3, Dividends!$A:$C, 3, FALSE) / VLOOKUP(A3, Prices!$A:$B, 2, FALSE), Inputs!$B$4) ) / 12, 0) -> 21.848167 | L3: =IFERROR(J3 / SUM($J$2:$J1001), 0) -> 0.16144079
A4: ULTY | B4: Anchor 60% | C4: 116 | F4: =IFERROR(VLOOKUP(A4, Prices!A:B, 2, FALSE), ) -> 5.55 | G4: =IFERROR(VLOOKUP(A4, Dividends!$A:$B, 2, FALSE), IFERROR( (VLOOKUP(A4, Dividends!$A:$C, 3, FALSE) / VLOOKUP(A4, Prices!$A:$B, 2, FALSE)) * 100, Inputs!$B$4*100 )) -> 132.30631 | H4: =IFERROR(SUMIF(Purchases!B:B, A4, Purchases!D:D), 0) -> 0 | I4: =C4+H4 -> 116 | J4: =IF(I4>0, I4*F4, 0) -> 643.8 | K4: =IF(J4>0, J4 * IF(G4>0, G4/100, IFERROR( VLOOKUP(A4, Dividends!$A:$C, 3, FALSE) / VLOOKUP(A4, Prices!$A:$B, 2, FALSE), Inputs!$B$4) ) / 12, 0) -> 70.982333 | L4: =IFERROR(J4 / SUM($J$2:$J1002), 0) -> 0.32082843
A5: TQQY | B5: Anchor 60% | C5: 17 | F5: =IFERROR(VLOOKUP(A5, Prices!A:B, 2, FALSE), ) -> 18.75 | G5: =IFERROR(VLOOKUP(A5, Dividends!$A:$B, 2, FALSE), IFERROR( (VLOOKUP(A5, Dividends!$A:$C, 3, FALSE) / VLOOKUP(A5, Prices!$A:$B, 2, FALSE)) * 100, Inputs!$B$4*100 )) -> 25.957333 | H5: =IFERROR(SUMIF(Purchases!B:B, A5, Purchases!D:D), 0) -> 0 | I5: =C5+H5 -> 17 | J5: =IF(I5>0, I5*F5, 0) -> 318.75 | K5: =IF(J5>0, J5 * IF(G5>0, G5/100, IFERROR( VLOOKUP(A5, Dividends!$A:$C, 3, FALSE) / VLOOKUP(A5, Prices!$A:$B, 2, FALSE), Inputs!$B$4) ) / 12, 0) -> 6.8949167 | L5: =IFERROR(J5 / SUM($J$2:$J1003), 0) -> 0.15884446
A6: PLTY | B6: High 40% | C6: 2 | F6: =IFERROR(VLOOKUP(A6, Prices!A:B, 2, FALSE), ) -> 62.2 | G6: =IFERROR(VLOOKUP(A6, Dividends!$A:$B, 2, FALSE), IFERROR( (VLOOKUP(A6, Dividends!$A:$C, 3, FALSE) / VLOOKUP(A6, Prices!$A:$B, 2, FALSE)) * 100, Inputs!$B$4*100 )) -> 77.808682 | H6: =IFERROR(SUMIF(Purchases!B:B, A6, Purchases!D:D), 0) -> 0 | I6: =C6+H6 -> 2 | J6: =IF(I6>0, I6*F6, 0) -> 124.4 | K6: =IF(J6>0, J6 * IF(G6>0, G6/100, IFERROR( VLOOKUP(A6, Dividends!$A:$C, 3, FALSE) / VLOOKUP(A6, Prices!$A:$B, 2, FALSE), Inputs!$B$4) ) / 12, 0) -> 8.0661667 | L6: =IFERROR(J6 / SUM($J$2:$J1004), 0) -> 0.061992944
A7: COIW | B7: High 40% | C7: 7 | F7: =IFERROR(VLOOKUP(A7, Prices!A:B, 2, FALSE), ) -> 39.51 | G7: =IFERROR(VLOOKUP(A7, Dividends!$A:$B, 2, FALSE), IFERROR( (VLOOKUP(A7, Dividends!$A:$C, 3, FALSE) / VLOOKUP(A7, Prices!$A:$B, 2, FALSE)) * 100, Inputs!$B$4*100 )) -> 34.859529 | H7: =IFERROR(SUMIF(Purchases!B:B, A7, Purchases!D:D), 0) -> 0 | I7: =C7+H7 -> 7 | J7: =IF(I7>0, I7*F7, 0) -> 276.57 | K7: =IF(J7>0, J7 * IF(G7>0, G7/100, IFERROR( VLOOKUP(A7, Dividends!$A:$C, 3, FALSE) / VLOOKUP(A7, Prices!$A:$B, 2, FALSE), Inputs!$B$4) ) / 12, 0) -> 8.03425 | L7: =IFERROR(J7 / SUM($J$2:$J1005), 0) -> 0.13782467
A8: TOTALS | F8: =IFERROR(VLOOKUP(A8, Prices!A:B, 2, FALSE), ) | G8: =IFERROR(VLOOKUP(A8, Dividends!$A:$B, 2, FALSE), IFERROR( (VLOOKUP(A8, Dividends!$A:$C, 3, FALSE) / VLOOKUP(A8, Prices!$A:$B, 2, FALSE)) * 100, Inputs!$B$4*100 )) -> 65 | H8: =IFERROR(SUMIF(Purchases!B:B, A8, Purchases!D:D), 0) -> 0 | I8: =C8+H8 -> 0 | J8: =IF(I8>0, I8*F8, 0) -> 0 | K8: =IF(J8>0, J8 * IF(G8>0, G8/100, IFERROR( VLOOKUP(A8, Dividends!$A:$C, 3, FALSE) / VLOOKUP(A8, Prices!$A:$B, 2, FALSE), Inputs!$B$4) ) / 12, 0) -> 0 | L8: =IFERROR(J8 / SUM($J$2:$J1006), 0) -> 0
F9: =IFERROR(VLOOKUP(A9, Prices!A:B, 2, FALSE), ) | G9: =IFERROR(VLOOKUP(A9, Dividends!$A:$B, 2, FALSE), IFERROR( (VLOOKUP(A9, Dividends!$A:$C, 3, FALSE) / VLOOKUP(A9, Prices!$A:$B, 2, FALSE)) * 100, Inputs!$B$4*100 )) -> 65 | H9: =IFERROR(SUMIF(Purchases!B:B, A9, Purchases!D:D), 0) -> 0 | I9: =C9+H9 -> 0 | J9: =IF(I9>0, I9*F9, 0) -> 0 | K9: =IF(J9>0, J9 * IF(G9>0, G9/100, IFERROR( VLOOKUP(A9, Dividends!$A:$C, 3, FALSE) / VLOOKUP(A9, Prices!$A:$B, 2, FALSE), Inputs!$B$4) ) / 12, 0) -> 0 | L9: =IFERROR(J9 / SUM($J$2:$J1007), 0) -> 0
F10: =IFERROR(VLOOKUP(A10, Prices!A:B, 2, FALSE), ) | G10: =IFERROR(VLOOKUP(A10, Dividends!$A:$B, 2, FALSE), IFERROR( (VLOOKUP(A10, Dividends!$A:$C, 3, FALSE) / VLOOKUP(A10, Prices!$A:$B, 2, FALSE)) * 100, Inputs!$B$4*100 )) -> 65 | H10: =IFERROR(SUMIF(Purchases!B:B, A10, Purchases!D:D), 0) -> 0 | I10: =C10+H10 -> 0 | J10: =IF(I10>0, I10*F10, 0) -> 0 | K10: =IF(J10>0, J10 * IF(G10>0, G10/100, IFERROR( VLOOKUP(A10, Dividends!$A:$C, 3, FALSE) / VLOOKUP(A10, Prices!$A:$B, 2, FALSE), Inputs!$B$4) ) / 12, 0) -> 0 | L10: =IFERROR(J10 / SUM($J$2:$J1008), 0) -> 0
F11: =IFERROR(VLOOKUP(A11, Prices!A:B, 2, FALSE), ) | G11: =IFERROR(VLOOKUP(A11, Dividends!$A:$B, 2, FALSE), IFERROR( (VLOOKUP(A11, Dividends!$A:$C, 3, FALSE) / VLOOKUP(A11, Prices!$A:$B, 2, FALSE)) * 100, Inputs!$B$4*100 )) -> 65 | H11: =IFERROR(SUMIF(Purchases!B:B, A11, Purchases!D:D), 0) -> 0 | I11: =C11+H11 -> 0 | J11: =IF(I11>0, I11*F11, 0) -> 0 | K11: =IF(J11>0, J11 * IF(G11>0, G11/100, IFERROR( VLOOKUP(A11, Dividends!$A:$C, 3, FALSE) / VLOOKUP(A11, Prices!$A:$B, 2, FALSE), Inputs!$B$4) ) / 12, 0) -> 0 | L11: =IFERROR(J11 / SUM($J$2:$J1009), 0) -> 0
F12: =IFERROR(VLOOKUP(A12, Prices!A:B, 2, FALSE), ) | G12: =IFERROR(VLOOKUP(A12, Dividends!$A:$B, 2, FALSE), IFERROR( (VLOOKUP(A12, Dividends!$A:$C, 3, FALSE) / VLOOKUP(A12, Prices!$A:$B, 2, FALSE)) * 100, Inputs!$B$4*100 )) -> 65 | H12: =IFERROR(SUMIF(Purchases!B:B, A12, Purchases!D:D), 0) -> 0 | I12: =C12+H12 -> 0 | J12: =IF(I12>0, I12*F12, 0) -> 0 | K12: =IF(J12>0, J12 * IF(G12>0, G12/100, IFERROR( VLOOKUP(A12, Dividends!$A:$C, 3, FALSE) / VLOOKUP(A12, Prices!$A:$B, 2, FALSE), Inputs!$B$4) ) / 12, 0) -> 0 | L12: =IFERROR(J12 / SUM($J$2:$J1010), 0) -> 0
F13: =IFERROR(VLOOKUP(A13, Prices!A:B, 2, FALSE), ) | G13: =IFERROR(VLOOKUP(A13, Dividends!$A:$B, 2, FALSE), IFERROR( (VLOOKUP(A13, Dividends!$A:$C, 3, FALSE) / VLOOKUP(A13, Prices!$A:$B, 2, FALSE)) * 100, Inputs!$B$4*100 )) -> 65 | H13: =IFERROR(SUMIF(Purchases!B:B, A13, Purchases!D:D), 0) -> 0 | I13: =C13+H13 -> 0 | J13: =IF(I13>0, I13*F13, 0) -> 0 | K13: =IF(J13>0, J13 * IF(G13>0, G13/100, IFERROR( VLOOKUP(A13, Dividends!$A:$C, 3, FALSE) / VLOOKUP(A13, Prices!$A:$B, 2, FALSE), Inputs!$B$4) ) / 12, 0) -> 0 | L13: =IFERROR(J13 / SUM($J$2:$J1011), 0) -> 0
F14: =IFERROR(VLOOKUP(A14, Prices!A:B, 2, FALSE), ) | G14: =IFERROR(VLOOKUP(A14, Dividends!$A:$B, 2, FALSE), IFERROR( (VLOOKUP(A14, Dividends!$A:$C, 3, FALSE) / VLOOKUP(A14, Prices!$A:$B, 2, FALSE)) * 100, Inputs!$B$4*100 )) -> 65 | H14: =IFERROR(SUMIF(Purchases!B:B, A14, Purchases!D:D), 0) -> 0 | I14: =C14+H14 -> 0 | J14: =IF(I14>0, I14*F14, 0) -> 0 | K14: =IF(J14>0, J14 * IF(G14>0, G14/100, IFERROR( VLOOKUP(A14, Dividends!$A:$C, 3, FALSE) / VLOOKUP(A14, Prices!$A:$B, 2, FALSE), Inputs!$B$4) ) / 12, 0) -> 0 | L14: =IFERROR(J14 / SUM($J$2:$J1012), 0) -> 0
F15: =IFERROR(VLOOKUP(A15, Prices!A:B, 2, FALSE), ) | G15: =IFERROR(VLOOKUP(A15, Dividends!$A:$B, 2, FALSE), IFERROR( (VLOOKUP(A15, Dividends!$A:$C, 3, FALSE) / VLOOKUP(A15, Prices!$A:$B, 2, FALSE)) * 100, Inputs!$B$4*100 )) -> 65 | H15: =IFERROR(SUMIF(Purchases!B:B, A15, Purchases!D:D), 0) -> 0 | I15: =C15+H15 -> 0 | J15: =IF(I15>0, I15*F15, 0) -> 0 | K15: =IF(J15>0, J15 * IF(G15>0, G15/100, IFERROR( VLOOKUP(A15, Dividends!$A:$C, 3, FALSE) / VLOOKUP(A15, Prices!$A:$B, 2, FALSE), Inputs!$B$4) ) / 12, 0) -> 0 | L15: =IFERROR(J15 / SUM($J$2:$J1013), 0) -> 0
F16: =IFERROR(VLOOKUP(A16, Prices!A:B, 2, FALSE), ) | G16: =IFERROR(VLOOKUP(A16, Dividends!$A:$B, 2, FALSE), IFERROR( (VLOOKUP(A16, Dividends!$A:$C, 3, FALSE) / VLOOKUP(A16, Prices!$A:$B, 2, FALSE)) * 100, Inputs!$B$4*100 )) -> 65 | H16: =IFERROR(SUMIF(Purchases!B:B, A16, Purchases!D:D), 0) -> 0 | I16: =C16+H16 -> 0 | J16: =IF(I16>0, I16*F16, 0) -> 0 | K16: =IF(J16>0, J16 * IF(G16>0, G16/100, IFERROR( VLOOKUP(A16, Dividends!$A:$C, 3, FALSE) / VLOOKUP(A16, Prices!$A:$B, 2, FALSE), Inputs!$B$4) ) / 12, 0) -> 0 | L16: =IFERROR(J16 / SUM($J$2:$J1014), 0) -> 0
F17: =IFERROR(VLOOKUP(A17, Prices!A:B, 2, FALSE), ) | G17: =IFERROR(VLOOKUP(A17, Dividends!$A:$B, 2, FALSE), IFERROR( (VLOOKUP(A17, Dividends!$A:$C, 3, FALSE) / VLOOKUP(A17, Prices!$A:$B, 2, FALSE)) * 100, Inputs!$B$4*100 )) -> 65 | H17: =IFERROR(SUMIF(Purchases!B:B, A17, Purchases!D:D), 0) -> 0 | I17: =C17+H17 -> 0 | J17: =IF(I17>0, I17*F17, 0) -> 0 | K17: =IF(J17>0, J17 * IF(G17>0, G17/100, IFERROR( VLOOKUP(A17, Dividends!$A:$C, 3, FALSE) / VLOOKUP(A17, Prices!$A:$B, 2, FALSE), Inputs!$B$4) ) / 12, 0) -> 0 | L17: =IFERROR(J17 / SUM($J$2:$J1015), 0) -> 0
F18: =IFERROR(VLOOKUP(A18, Prices!A:B, 2, FALSE), ) | G18: =IFERROR(VLOOKUP(A18, Dividends!$A:$B, 2, FALSE), IFERROR( (VLOOKUP(A18, Dividends!$A:$C, 3, FALSE) / VLOOKUP(A18, Prices!$A:$B, 2, FALSE)) * 100, Inputs!$B$4*100 )) -> 65 | H18: =IFERROR(SUMIF(Purchases!B:B, A18, Purchases!D:D), 0) -> 0 | I18: =C18+H18 -> 0 | J18: =IF(I18>0, I18*F18, 0) -> 0 | K18: =IF(J18>0, J18 * IF(G18>0, G18/100, IFERROR( VLOOKUP(A18, Dividends!$A:$C, 3, FALSE) / VLOOKUP(A18, Prices!$A:$B, 2, FALSE), Inputs!$B$4) ) / 12, 0) -> 0 | L18: =IFERROR(J18 / SUM($J$2:$J1016), 0) -> 0
F19: =IFERROR(VLOOKUP(A19, Prices!A:B, 2, FALSE), ) | G19: =IFERROR(VLOOKUP(A19, Dividends!$A:$B, 2, FALSE), IFERROR( (VLOOKUP(A19, Dividends!$A:$C, 3, FALSE) / VLOOKUP(A19, Prices!$A:$B, 2, FALSE)) * 100, Inputs!$B$4*100 )) -> 65 | H19: =IFERROR(SUMIF(Purchases!B:B, A19, Purchases!D:D), 0) -> 0 | I19: =C19+H19 -> 0 | J19: =IF(I19>0, I19*F19, 0) -> 0 | K19: =IF(J19>0, J19 * IF(G19>0, G19/100, IFERROR( VLOOKUP(A19, Dividends!$A:$C, 3, FALSE) / VLOOKUP(A19, Prices!$A:$B, 2, FALSE), Inputs!$B$4) ) / 12, 0) -> 0 | L19: =IFERROR(J19 / SUM($J$2:$J1017), 0) -> 0
F20: =IFERROR(VLOOKUP(A20, Prices!A:B, 2, FALSE), ) | G20: =IFERROR(VLOOKUP(A20, Dividends!$A:$B, 2, FALSE), IFERROR( (VLOOKUP(A20, Dividends!$A:$C, 3, FALSE) / VLOOKUP(A20, Prices!$A:$B, 2, FALSE)) * 100, Inputs!$B$4*100 )) -> 65 | H20: =IFERROR(SUMIF(Purchases!B:B, A20, Purchases!D:D), 0) -> 0 | I20: =C20+H20 -> 0 | J20: =IF(I20>0, I20*F20, 0) -> 0 | K20: =IF(J20>0, J20 * IF(G20>0, G20/100, IFERROR( VLOOKUP(A20, Dividends!$A:$C, 3, FALSE) / VLOOKUP(A20, Prices!$A:$B, 2, FALSE), Inputs!$B$4) ) / 12, 0) -> 0 | L20: =IFERROR(J20 / SUM($J$2:$J1018), 0) -> 0
... F1000: =IFERROR(VLOOKUP(A1000, Prices!A:B, 2, FALSE), ) | G1000: =IFERROR(VLOOKUP(A1000, Dividends!$A:$B, 2, FALSE), IFERROR( (VLOOKUP(A1000, Dividends!$A:$C, 3, FALSE) / VLOOKUP(A1000, Prices!$A:$B, 2, FALSE)) * 100, Inputs!$B$4*100 )) -> 65 | H1000: =IFERROR(SUMIF(Purchases!B:B, A1000, Purchases!D:D), 0) -> 0 | I1000: =C1000+H1000 -> 0 | J1000: =IF(I1000>0, I1000*F1000, 0) -> 0 | K1000: =IF(J1000>0, J1000 * IF(G1000>0, G1000/100, IFERROR( VLOOKUP(A1000, Dividends!$A:$C, 3, FALSE) / VLOOKUP(A1000, Prices!$A:$B, 2, FALSE), Inputs!$B$4) ) / 12, 0) -> 0 | L1000: =IFERROR(J1000 / SUM($J$2:$J1998), 0) -> 0

Sheet Purchases
A1: Date | B1: Symbol | C1: Price | D1: Shares | E1: Amount ($) | F1: Notes
E2: =IF(D2<>"", C2*D2, "")
E3: =IF(D3<>"", C3*D3, "")
E4: =IF(D4<>"", C4*D4, "")
E5: =IF(D5<>"", C5*D5, "")
E6: =IF(D6<>"", C6*D6, "")
E7: =IF(D7<>"", C7*D7, "")
E8: =IF(D8<>"", C8*D8, "")
E9: =IF(D9<>"", C9*D9, "")
E10: =IF(D10<>"", C10*D10, "")
E11: =IF(D11<>"", C11*D11, "")
E12: =IF(D12<>"", C12*D12, "")
E13: =IF(D13<>"", C13*D13, "")
... E1000: =IF(D1000<>"", C1000*D1000, "")

Sheet Projection_Biweekly
A1: Line | B1: Date | C1: CumulativeContrib ($) | D1: Equity ($) | E1: WeeklyIncome ($) | F1: MonthlyIncome ($) | G1: YearlyIncome ($) | H1: SafeMarginWithdrawal ($)
A2: 1 | B2: =DATEVALUE(Inputs!B$2) + (A2-1)*14 -> 45897 | C2: =(1-1)*Inputs!B3 -> 0 | D2: =SUM(Holdings!J2:J1000) + C2 -> 2006.68 | E2: =D2 * IFERROR((SUM(Holdings!K2:K1000)*12)/(SUM(Holdings!J2:J1000)), Inputs!B4) / 52 -> 30.719038 | F2: =E2*4.33 -> 133.01344 | G2: =E2*52 -> 1597.39 | H2: =D2 * Inputs!B6 * Inputs!B7 -> 173.07615
A3: 2 | B3: =DATEVALUE(Inputs!B$2) + (A3-1)*14 -> 45911 | C3: =(2-1)*Inputs!B3 -> 2200 | D3: =SUM(Holdings!J2:J1000) + C3 -> 4206.68 | E3: =D3 * IFERROR((SUM(Holdings!K2:K1000)*12)/(SUM(Holdings!J2:J1000)), Inputs!B4) / 52 -> 64.397495 | F3: =E3*4.33 -> 278.84115 | G3: =E3*52 -> 3348.6697 | H3: =D3 * Inputs!B6 * Inputs!B7 -> 362.82615
A4: 3 | B4: =DATEVALUE(Inputs!B$2) + (A4-1)*14 -> 45925 | C4: =(3-1)*Inputs!B3 -> 4400 | D4: =SUM(Holdings!J2:J1000) + C4 -> 6406.68 | E4: =D4 * IFERROR((SUM(Holdings!K2:K1000)*12)/(SUM(Holdings!J2:J1000)), Inputs!B4) / 52 -> 98.075951 | F4: =E4*4.33 -> 424.66887 | G4: =E4*52 -> 5099.9495 | H4: =D4 * Inputs!B6 * Inputs!B7 -> 552.57615
A5: 4 | B5: =DATEVALUE(Inputs!B$2) + (A5-1)*14 -> 45939 | C5: =(4-1)*Inputs!B3 -> 6600 | D5: =SUM(Holdings!J2:J1000) + C5 -> 8606.68 | E5: =D5 * IFERROR((SUM(Holdings!K2:K1000)*12)/(SUM(Holdings!J2:J1000)), Inputs!B4) / 52 -> 131.75441 | F5: =E5*4.33 -> 570.49658 | G5: =E5*52 -> 6851.2292 | H5: =D5 * Inputs!B6 * Inputs!B7 -> 742.32615
A6: 5 | B6: =DATEVALUE(Inputs!B$2) + (A6-1)*14 -> 45953 | C6: =(5-1)*Inputs!B3 -> 8800 | D6: =SUM(Holdings!J2:J1000) + C6 -> 10806.68 | E6: =D6 * IFERROR((SUM(Holdings!K2:K1000)*12)/(SUM(Holdings!J2:J1000)), Inputs!B4) / 52 -> 165.43286 | F6: =E6*4.33 -> 716.3243 | G6: =E6*52 -> 8602.5089 | H6: =D6 * Inputs!B6 * Inputs!B7 -> 932.07615
A7: 6 | B7: =DATEVALUE(Inputs!B$2) + (A7-1)*14 -> 45967 | C7: =(6-1)*Inputs!B3 -> 11000 | D7: =SUM(Holdings!J2:J1000) + C7 -> 13006.68 | E7: =D7 * IFERROR((SUM(Holdings!K2:K1000)*12)/(SUM(Holdings!J2:J1000)), Inputs!B4) / 52 -> 199.11132 | F7: =E7*4.33 -> 862.15201 | G7: =E7*52 -> 10353.789 | H7: =D7 * Inputs!B6 * Inputs!B7 -> 1121.8262
A8: 7 | B8: =DATEVALUE(Inputs!B$2) + (A8-1)*14 -> 45981 | C8: =(7-1)*Inputs!B3 -> 13200 | D8: =SUM(Holdings!J2:J1000) + C8 -> 15206.68 | E8: =D8 * IFERROR((SUM(Holdings!K2:K1000)*12)/(SUM(Holdings!J2:J1000)), Inputs!B4) / 52 -> 232.78978 | F8: =E8*4.33 -> 1007.9797 | G8: =E8*52 -> 12105.068 | H8: =D8 * Inputs!B6 * Inputs!B7 -> 1311.5762
A9: 8 | B9: =DATEVALUE(Inputs!B$2) + (A9-1)*14 -> 45995 | C9: =(8-1)*Inputs!B3 -> 15400 | D9: =SUM(Holdings!J2:J1000) + C9 -> 17406.68 | E9: =D9 * IFERROR((SUM(Holdings!K2:K1000)*12)/(SUM(Holdings!J2:J1000)), Inputs!B4) / 52 -> 266.46823 | F9: =E9*4.33 -> 1153.8074 | G9: =E9*52 -> 13856.348 | H9: =D9 * Inputs!B6 * Inputs!B7 -> 1501.3262
A10: 9 | B10: =DATEVALUE(Inputs!B$2) + (A10-1)*14 -> 46009 | C10: =(9-1)*Inputs!B3 -> 17600 | D10: =SUM(Holdings!J2:J1000) + C10 -> 19606.68 | E10: =D10 * IFERROR((SUM(Holdings!K2:K1000)*12)/(SUM(Holdings!J2:J1000)), Inputs!B4) / 52 -> 300.14669 | F10: =E10*4.33 -> 1299.6352 | G10: =E10*52 -> 15607.628 | H10: =D10 * Inputs!B6 * Inputs!B7 -> 1691.0762
A11: 10 | B11: =DATEVALUE(Inputs!B$2) + (A11-1)*14 -> 46023 | C11: =(10-1)*Inputs!B3 -> 19800 | D11: =SUM(Holdings!J2:J1000) + C11 -> 21806.68 | E11: =D11 * IFERROR((SUM(Holdings!K2:K1000)*12)/(SUM(Holdings!J2:J1000)), Inputs!B4) / 52 -> 333.82514 | F11: =E11*4.33 -> 1445.4629 | G11: =E11*52 -> 17358.908 | H11: =D11 * Inputs!B6 * Inputs!B7 -> 1880.8262
A12: 11 | B12: =DATEVALUE(Inputs!B$2) + (A12-1)*14 -> 46037 | C12: =(11-1)*Inputs!B3 -> 22000 | D12: =SUM(Holdings!J2:J1000) + C12 -> 24006.68 | E12: =D12 * IFERROR((SUM(Holdings!K2:K1000)*12)/(SUM(Holdings!J2:J1000)), Inputs!B4) / 52 -> 367.5036 | F12: =E12*4.33 -> 1591.2906 | G12: =E12*52 -> 19110.187 | H12: =D12 * Inputs!B6 * Inputs!B7 -> 2070.5761
A13: 12 | B13: =DATEVALUE(Inputs!B$2) + (A13-1)*14 -> 46051 | C13: =(12-1)*Inputs!B3 -> 24200 | D13: =SUM(Holdings!J2:J1000) + C13 -> 26206.68 | E13: =D13 * IFERROR((SUM(Holdings!K2:K1000)*12)/(SUM(Holdings!J2:J1000)), Inputs!B4) / 52 -> 401.18206 | F13: =E13*4.33 -> 1737.1183 | G13: =E13*52 -> 20861.467 | H13: =D13 * Inputs!B6 * Inputs!B7 -> 2260.3261
A14: 13 | B14: =DATEVALUE(Inputs!B$2) + (A14-1)*14 -> 46065 | C14: =(13-1)*Inputs!B3 -> 26400 | D14: =SUM(Holdings!J2:J1000) + C14 -> 28406.68 | E14: =D14 * IFERROR((SUM(Holdings!K2:K1000)*12)/(SUM(Holdings!J2:J1000)), Inputs!B4) / 52 -> 434.86051 | F14: =E14*4.33 -> 1882.946 | G14: =E14*52 -> 22612.747 | H14: =D14 * Inputs!B6 * Inputs!B7 -> 2450.0761
A15: 14 | B15: =DATEVALUE(Inputs!B$2) + (A15-1)*14 -> 46079 | C15: =(14-1)*Inputs!B3 -> 28600 | D15: =SUM(Holdings!J2:J1000) + C15 -> 30606.68 | E15: =D15 * IFERROR((SUM(Holdings!K2:K1000)*12)/(SUM(Holdings!J2:J1000)), Inputs!B4) / 52 -> 468.53897 | F15: =E15*4.33 -> 2028.7737 | G15: =E15*52 -> 24364.026 | H15: =D15 * Inputs!B6 * Inputs!B7 -> 2639.8261
A16: 15 | B16: =DATEVALUE(Inputs!B$2) + (A16-1)*14 -> 46093 | C16: =(15-1)*Inputs!B3 -> 30800 | D16: =SUM(Holdings!J2:J1000) + C16 -> 32806.68 | E16: =D16 * IFERROR((SUM(Holdings!K2:K1000)*12)/(SUM(Holdings!J2:J1000)), Inputs!B4) / 52 -> 502.21743 | F16: =E16*4.33 -> 2174.6015 | G16: =E16*52 -> 26115.306 | H16: =D16 * Inputs!B6 * Inputs!B7 -> 2829.5761
A17: 16 | B17: =DATEVALUE(Inputs!B$2) + (A17-1)*14 -> 46107 | C17: =(16-1)*Inputs!B3 -> 33000 | D17: =SUM(Holdings!J2:J1000) + C17 -> 35006.68 | E17: =D17 * IFERROR((SUM(Holdings!K2:K1000)*12)/(SUM(Holdings!J2:J1000)), Inputs!B4) / 52 -> 535.89588 | F17: =E17*4.33 -> 2320.4292 | G17: =E17*52 -> 27866.586 | H17: =D17 * Inputs!B6 * Inputs!B7 -> 3019.3261
A18: 17 | B18: =DATEVALUE(Inputs!B$2) + (A18-1)*14 -> 46121 | C18: =(17-1)*Inputs!B3 -> 35200 | D18: =SUM(Holdings!J2:J1000) + C18 -> 37206.68 | E18: =D18 * IFERROR((SUM(Holdings!K2:K1000)*12)/(SUM(Holdings!J2:J1000)), Inputs!B4) / 52 -> 569.57434 | F18: =E18*4.33 -> 2466.2569 | G18: =E18*52 -> 29617.866 | H18: =D18 * Inputs!B6 * Inputs!B7 -> 3209.0761
A19: 18 | B19: =DATEVALUE(Inputs!B$2) + (A19-1)*14 -> 46135 | C19: =(18-1)*Inputs!B3 -> 37400 | D19: =SUM(Holdings!J2:J1000) + C19 -> 39406.68 | E19: =D19 * IFERROR((SUM(Holdings!K2:K1000)*12)/(SUM(Holdings!J2:J1000)), Inputs!B4) / 52 -> 603.25279 | F19: =E19*4.33 -> 2612.0846 | G19: =E19*52 -> 31369.145 | H19: =D19 * Inputs!B6 * Inputs!B7 -> 3398.8261
A20: 19 | B20: =DATEVALUE(Inputs!B$2) + (A20-1)*14 -> 46149 | C20: =(19-1)*Inputs!B3 -> 39600 | D20: =SUM(Holdings!J2:J1000) + C20 -> 41606.68 | E20: =D20 * IFERROR((SUM(Holdings!K2:K1000)*12)/(SUM(Holdings!J2:J1000)), Inputs!B4) / 52 -> 636.93125 | F20: =E20*4.33 -> 2757.9123 | G20: =E20*52 -> 33120.425 | H20: =D20 * Inputs!B6 * Inputs!B7 -> 3588.5761
A21: 20 | B21: =DATEVALUE(Inputs!B$2) + (A21-1)*14 -> 46163 | C21: =(20-1)*Inputs!B3 -> 41800 | D21: =SUM(Holdings!J2:J1000) + C21 -> 43806.68 | E21: =D21 * IFERROR((SUM(Holdings!K2:K1000)*12)/(SUM(Holdings!J2:J1000)), Inputs!B4) / 52 -> 670.60971 | F21: =E21*4.33 -> 2903.74 | G21: =E21*52 -> 34871.705 | H21: =D21 * Inputs!B6 * Inputs!B7 -> 3778.3261
A22: 21 | B22: =DATEVALUE(Inputs!B$2) + (A22-1)*14 -> 46177 | C22: =(21-1)*Inputs!B3 -> 44000 | D22: =SUM(Holdings!J2:J1000) + C22 -> 46006.68 | E22: =D22 * IFERROR((SUM(Holdings!K2:K1000)*12)/(SUM(Holdings!J2:J1000)), Inputs!B4) / 52 -> 704.28816 | F22: =E22*4.33 -> 3049.5677 | G22: =E22*52 -> 36622.985 | H22: =D22 * Inputs!B6 * Inputs!B7 -> 3968.0761
A23: 22 | B23: =DATEVALUE(Inputs!B$2) + (A23-1)*14 -> 46191 | C23: =(22-1)*Inputs!B3 -> 46200 | D23: =SUM(Holdings!J2:J1000) + C23 -> 48206.68 | E23: =D23 * IFERROR((SUM(Holdings!K2:K1000)*12)/(SUM(Holdings!J2:J1000)), Inputs!B4) / 52 -> 737.96662 | F23: =E23*4.33 -> 3195.3955 | G23: =E23*52 -> 38374.264 | H23: =D23 * Inputs!B6 * Inputs!B7 -> 4157.8261
A24: 23 | B24: =DATEVALUE(Inputs!B$2) + (A24-1)*14 -> 46205 | C24: =(23-1)*Inputs!B3 -> 48400 | D24: =SUM(Holdings!J2:J1000) + C24 -> 50406.68 | E24: =D24 * IFERROR((SUM(Holdings!K2:K1000)*12)/(SUM(Holdings!J2:J1000)), Inputs!B4) / 52 -> 771.64508 | F24: =E24*4.33 -> 3341.2232 | G24: =E24*52 -> 40125.544 | H24: =D24 * Inputs!B6 * Inputs!B7 -> 4347.5761
A25: 24 | B25: =DATEVALUE(Inputs!B$2) + (A25-1)*14 -> 46219 | C25: =(24-1)*Inputs!B3 -> 50600 | D25: =SUM(Holdings!J2:J1000) + C25 -> 52606.68 | E25: =D25 * IFERROR((SUM(Holdings!K2:K1000)*12)/(SUM(Holdings!J2:J1000)), Inputs!B4) / 52 -> 805.32353 | F25: =E25*4.33 -> 3487.0509 | G25: =E25*52 -> 41876.824 | H25: =D25 * Inputs!B6 * Inputs!B7 -> 4537.3261
A26: 25 | B26: =DATEVALUE(Inputs!B$2) + (A26-1)*14 -> 46233 | C26: =(25-1)*Inputs!B3 -> 52800 | D26: =SUM(Holdings!J2:J1000) + C26 -> 54806.68 | E26: =D26 * IFERROR((SUM(Holdings!K2:K1000)*12)/(SUM(Holdings!J2:J1000)), Inputs!B4) / 52 -> 839.00199 | F26: =E26*4.33 -> 3632.8786 | G26: =E26*52 -> 43628.103 | H26: =D26 * Inputs!B6 * Inputs!B7 -> 4727.0761
A27: 26 | B27: =DATEVALUE(Inputs!B$2) + (A27-1)*14 -> 46247 | C27: =(26-1)*Inputs!B3 -> 55000 | D27: =SUM(Holdings!J2:J1000) + C27 -> 57006.68 | E27: =D27 * IFERROR((SUM(Holdings!K2:K1000)*12)/(SUM(Holdings!J2:J1000)), Inputs!B4) / 52 -> 872.68045 | F27: =E27*4.33 -> 3778.7063 | G27: =E27*52 -> 45379.383 | H27: =D27 * Inputs!B6 * Inputs!B7 -> 4916.8261
A28: 27 | B28: =DATEVALUE(Inputs!B$2) + (A28-1)*14 -> 46261 | C28: =(27-1)*Inputs!B3 -> 57200 | D28: =SUM(Holdings!J2:J1000) + C28 -> 59206.68 | E28: =D28 * IFERROR((SUM(Holdings!K2:K1000)*12)/(SUM(Holdings!J2:J1000)), Inputs!B4) / 52 -> 906.3589 | F28: =E28*4.33 -> 3924.534 | G28: =E28*52 -> 47130.663 | H28: =D28 * Inputs!B6 * Inputs!B7 -> 5106.5761
A29: 28 | B29: =DATEVALUE(Inputs!B$2) + (A29-1)*14 -> 46275 | C29: =(28-1)*Inputs!B3 -> 59400 | D29: =SUM(Holdings!J2:J1000) + C29 -> 61406.68 | E29: =D29 * IFERROR((SUM(Holdings!K2:K1000)*12)/(SUM(Holdings!J2:J1000)), Inputs!B4) / 52 -> 940.03736 | F29: =E29*4.33 -> 4070.3618 | G29: =E29*52 -> 48881.943 | H29: =D29 * Inputs!B6 * Inputs!B7 -> 5296.3261
A30: 29 | B30: =DATEVALUE(Inputs!B$2) + (A30-1)*14 -> 46289 | C30: =(29-1)*Inputs!B3 -> 61600 | D30: =SUM(Holdings!J2:J1000) + C30 -> 63606.68 | E30: =D30 * IFERROR((SUM(Holdings!K2:K1000)*12)/(SUM(Holdings!J2:J1000)), Inputs!B4) / 52 -> 973.71581 | F30: =E30*4.33 -> 4216.1895 | G30: =E30*52 -> 50633.222 | H30: =D30 * Inputs!B6 * Inputs!B7 -> 5486.0761
A31: 30 | B31: =DATEVALUE(Inputs!B$2) + (A31-1)*14 -> 46303 | C31: =(30-1)*Inputs!B3 -> 63800 | D31: =SUM(Holdings!J2:J1000) + C31 -> 65806.68 | E31: =D31 * IFERROR((SUM(Holdings!K2:K1000)*12)/(SUM(Holdings!J2:J1000)), Inputs!B4) / 52 -> 1007.3943 | F31: =E31*4.33 -> 4362.0172 | G31: =E31*52 -> 52384.502 | H31: =D31 * Inputs!B6 * Inputs!B7 -> 5675.8261
A32: 31 | B32: =DATEVALUE(Inputs!B$2) + (A32-1)*14 -> 46317 | C32: =(31-1)*Inputs!B3 -> 66000 | D32: =SUM(Holdings!J2:J1000) + C32 -> 68006.68 | E32: =D32 * IFERROR((SUM(Holdings!K2:K1000)*12)/(SUM(Holdings!J2:J1000)), Inputs!B4) / 52 -> 1041.0727 | F32: =E32*4.33 -> 4507.8449 | G32: =E32*52 -> 54135.782 | H32: =D32 * Inputs!B6 * Inputs!B7 -> 5865.5761
A33: 32 | B33: =DATEVALUE(Inputs!B$2) + (A33-1)*14 -> 46331 | C33: =(32-1)*Inputs!B3 -> 68200 | D33: =SUM(Holdings!J2:J1000) + C33 -> 70206.68 | E33: =D33 * IFERROR((SUM(Holdings!K2:K1000)*12)/(SUM(Holdings!J2:J1000)), Inputs!B4) / 52 -> 1074.7512 | F33: =E33*4.33 -> 4653.6726 | G33: =E33*52 -> 55887.062 | H33: =D33 * Inputs!B6 * Inputs!B7 -> 6055.3261
A34: 33 | B34: =DATEVALUE(Inputs!B$2) + (A34-1)*14 -> 46345 | C34: =(33-1)*Inputs!B3 -> 70400 | D34: =SUM(Holdings!J2:J1000) + C34 -> 72406.68 | E34: =D34 * IFERROR((SUM(Holdings!K2:K1000)*12)/(SUM(Holdings!J2:J1000)), Inputs!B4) / 52 -> 1108.4296 | F34: =E34*4.33 -> 4799.5003 | G34: =E34*52 -> 57638.341 | H34: =D34 * Inputs!B6 * Inputs!B7 -> 6245.0761
A35: 34 | B35: =DATEVALUE(Inputs!B$2) + (A35-1)*14 -> 46359 | C35: =(34-1)*Inputs!B3 -> 72600 | D35: =SUM(Holdings!J2:J1000) + C35 -> 74606.68 | E35: =D35 * IFERROR((SUM(Holdings!K2:K1000)*12)/(SUM(Holdings!J2:J1000)), Inputs!B4) / 52 -> 1142.1081 | F35: =E35*4.33 -> 4945.3281 | G35: =E35*52 -> 59389.621 | H35: =D35 * Inputs!B6 * Inputs!B7 -> 6434.8261
A36: 35 | B36: =DATEVALUE(Inputs!B$2) + (A36-1)*14 -> 46373 | C36: =(35-1)*Inputs!B3 -> 74800 | D36: =SUM(Holdings!J2:J1000) + C36 -> 76806.68 | E36: =D36 * IFERROR((SUM(Holdings!K2:K1000)*12)/(SUM(Holdings!J2:J1000)), Inputs!B4) / 52 -> 1175.7866 | F36: =E36*4.33 -> 5091.1558 | G36: =E36*52 -> 61140.901 | H36: =D36 * Inputs!B6 * Inputs!B7 -> 6624.5761
A37: 36 | B37: =DATEVALUE(Inputs!B$2) + (A37-1)*14 -> 46387 | C37: =(36-1)*Inputs!B3 -> 77000 | D37: =SUM(Holdings!J2:J1000) + C37 -> 79006.68 | E37: =D37 * IFERROR((SUM(Holdings!K2:K1000)*12)/(SUM(Holdings!J2:J1000)), Inputs!B4) / 52 -> 1209.465 | F37: =E37*4.33 -> 5236.9835 | G37: =E37*52 -> 62892.18 | H37: =D37 * Inputs!B6 * Inputs!B7 -> 6814.3261
A38: 37 | B38: =DATEVALUE(Inputs!B$2) + (A38-1)*14 -> 46401 | C38: =(37-1)*Inputs!B3 -> 79200 | D38: =SUM(Holdings!J2:J1000) + C38 -> 81206.68 | E38: =D38 * IFERROR((SUM(Holdings!K2:K1000)*12)/(SUM(Holdings!J2:J1000)), Inputs!B4) / 52 -> 1243.1435 | F38: =E38*4.33 -> 5382.8112 | G38: =E38*52 -> 64643.46 | H38: =D38 * Inputs!B6 * Inputs!B7 -> 7004.0761
A39: 38 | B39: =DATEVALUE(Inputs!B$2) + (A39-1)*14 -> 46415 | C39: =(38-1)*Inputs!B3 -> 81400 | D39: =SUM(Holdings!J2:J1000) + C39 -> 83406.68 | E39: =D39 * IFERROR((SUM(Holdings!K2:K1000)*12)/(SUM(Holdings!J2:J1000)), Inputs!B4) / 52 -> 1276.8219 | F39: =E39*4.33 -> 5528.6389 | G39: =E39*52 -> 66394.74 | H39: =D39 * Inputs!B6 * Inputs!B7 -> 7193.8261
A40: 39 | B40: =DATEVALUE(Inputs!B$2) + (A40-1)*14 -> 46429 | C40: =(39-1)*Inputs!B3 -> 83600 | D40: =SUM(Holdings!J2:J1000) + C40 -> 85606.68 | E40: =D40 * IFERROR((SUM(Holdings!K2:K1000)*12)/(SUM(Holdings!J2:J1000)), Inputs!B4) / 52 -> 1310.5004 | F40: =E40*4.33 -> 5674.4666 | G40: =E40*52 -> 68146.02 | H40: =D40 * Inputs!B6 * Inputs!B7 -> 7383.5761
A41: 40 | B41: =DATEVALUE(Inputs!B$2) + (A41-1)*14 -> 46443 | C41: =(40-1)*Inputs!B3 -> 85800 | D41: =SUM(Holdings!J2:J1000) + C41 -> 87806.68 | E41: =D41 * IFERROR((SUM(Holdings!K2:K1000)*12)/(SUM(Holdings!J2:J1000)), Inputs!B4) / 52 -> 1344.1788 | F41: =E41*4.33 -> 5820.2943 | G41: =E41*52 -> 69897.299 | H41: =D41 * Inputs!B6 * Inputs!B7 -> 7573.3261
A42: 41 | B42: =DATEVALUE(Inputs!B$2) + (A42-1)*14 -> 46457 | C42: =(41-1)*Inputs!B3 -> 88000 | D42: =SUM(Holdings!J2:J1000) + C42 -> 90006.68 | E42: =D42 * IFERROR((SUM(Holdings!K2:K1000)*12)/(SUM(Holdings!J2:J1000)), Inputs!B4) / 52 -> 1377.8573 | F42: =E42*4.33 -> 5966.1221 | G42: =E42*52 -> 71648.579 | H42: =D42 * Inputs!B6 * Inputs!B7 -> 7763.0761
A43: 42 | B43: =DATEVALUE(Inputs!B$2) + (A43-1)*14 -> 46471 | C43: =(42-1)*Inputs!B3 -> 90200 | D43: =SUM(Holdings!J2:J1000) + C43 -> 92206.68 | E43: =D43 * IFERROR((SUM(Holdings!K2:K1000)*12)/(SUM(Holdings!J2:J1000)), Inputs!B4) / 52 -> 1411.5357 | F43: =E43*4.33 -> 6111.9498 | G43: =E43*52 -> 73399.859 | H43: =D43 * Inputs!B6 * Inputs!B7 -> 7952.8261
A44: 43 | B44: =DATEVALUE(Inputs!B$2) + (A44-1)*14 -> 46485 | C44: =(43-1)*Inputs!B3 -> 92400 | D44: =SUM(Holdings!J2:J1000) + C44 -> 94406.68 | E44: =D44 * IFERROR((SUM(Holdings!K2:K1000)*12)/(SUM(Holdings!J2:J1000)), Inputs!B4) / 52 -> 1445.2142 | F44: =E44*4.33 -> 6257.7775 | G44: =E44*52 -> 75151.138 | H44: =D44 * Inputs!B6 * Inputs!B7 -> 8142.5761
A45: 44 | B45: =DATEVALUE(Inputs!B$2) + (A45-1)*14 -> 46499 | C45: =(44-1)*Inputs!B3 -> 94600 | D45: =SUM(Holdings!J2:J1000) + C45 -> 96606.68 | E45: =D45 * IFERROR((SUM(Holdings!K2:K1000)*12)/(SUM(Holdings!J2:J1000)), Inputs!B4) / 52 -> 1478.8927 | F45: =E45*4.33 -> 6403.6052 | G45: =E45*52 -> 76902.418 | H45: =D45 * Inputs!B6 * Inputs!B7 -> 8332.3262
A46: 45 | B46: =DATEVALUE(Inputs!B$2) + (A46-1)*14 -> 46513 | C46: =(45-1)*Inputs!B3 -> 96800 | D46: =SUM(Holdings!J2:J1000) + C46 -> 98806.68 | E46: =D46 * IFERROR((SUM(Holdings!K2:K1000)*12)/(SUM(Holdings!J2:J1000)), Inputs!B4) / 52 -> 1512.5711 | F46: =E46*4.33 -> 6549.4329 | G46: =E46*52 -> 78653.698 | H46: =D46 * Inputs!B6 * Inputs!B7 -> 8522.0762
A47: 46 | B47: =DATEVALUE(Inputs!B$2) + (A47-1)*14 -> 46527 | C47: =(46-1)*Inputs!B3 -> 99000 | D47: =SUM(Holdings!J2:J1000) + C47 -> 101006.68 | E47: =D47 * IFERROR((SUM(Holdings!K2:K1000)*12)/(SUM(Holdings!J2:J1000)), Inputs!B4) / 52 -> 1546.2496 | F47: =E47*4.33 -> 6695.2606 | G47: =E47*52 -> 80404.978 | H47: =D47 * Inputs!B6 * Inputs!B7 -> 8711.8262
A48: 47 | B48: =DATEVALUE(Inputs!B$2) + (A48-1)*14 -> 46541 | C48: =(47-1)*Inputs!B3 -> 101200 | D48: =SUM(Holdings!J2:J1000) + C48 -> 103206.68 | E48: =D48 * IFERROR((SUM(Holdings!K2:K1000)*12)/(SUM(Holdings!J2:J1000)), Inputs!B4) / 52 -> 1579.928 | F48: =E48*4.33 -> 6841.0884 | G48: =E48*52 -> 82156.257 | H48: =D48 * Inputs!B6 * Inputs!B7 -> 8901.5762
A49: 48 | B49: =DATEVALUE(Inputs!B$2) + (A49-1)*14 -> 46555 | C49: =(48-1)*Inputs!B3 -> 103400 | D49: =SUM(Holdings!J2:J1000) + C49 -> 105406.68 | E49: =D49 * IFERROR((SUM(Holdings!K2:K1000)*12)/(SUM(Holdings!J2:J1000)), Inputs!B4) / 52 -> 1613.6065 | F49: =E49*4.33 -> 6986.9161 | G49: =E49*52 -> 83907.537 | H49: =D49 * Inputs!B6 * Inputs!B7 -> 9091.3262
A50: 49 | B50: =DATEVALUE(Inputs!B$2) + (A50-1)*14 -> 46569 | C50: =(49-1)*Inputs!B3 -> 105600 | D50: =SUM(Holdings!J2:J1000) + C50 -> 107606.68 | E50: =D50 * IFERROR((SUM(Holdings!K2:K1000)*12)/(SUM(Holdings!J2:J1000)), Inputs!B4) / 52 -> 1647.2849 | F50: =E50*4.33 -> 7132.7438 | G50: =E50*52 -> 85658.817 | H50: =D50 * Inputs!B6 * Inputs!B7 -> 9281.0762
A51: 50 | B51: =DATEVALUE(Inputs!B$2) + (A51-1)*14 -> 46583 | C51: =(50-1)*Inputs!B3 -> 107800 | D51: =SUM(Holdings!J2:J1000) + C51 -> 109806.68 | E51: =D51 * IFERROR((SUM(Holdings!K2:K1000)*12)/(SUM(Holdings!J2:J1000)), Inputs!B4) / 52 -> 1680.9634 | F51: =E51*4.33 -> 7278.5715 | G51: =E51*52 -> 87410.097 | H51: =D51 * Inputs!B6 * Inputs!B7 -> 9470.8262
A52: 51 | B52: =DATEVALUE(Inputs!B$2) + (A52-1)*14 -> 46597 | C52: =(51-1)*Inputs!B3 -> 110000 | D52: =SUM(Holdings!J2:J1000) + C52 -> 112006.68 | E52: =D52 * IFERROR((SUM(Holdings!K2:K1000)*12)/(SUM(Holdings!J2:J1000)), Inputs!B4) / 52 -> 1714.6419 | F52: =E52*4.33 -> 7424.3992 | G52: =E52*52 -> 89161.376 | H52: =D52 * Inputs!B6 * Inputs!B7 -> 9660.5762
A53: 52 | B53: =DATEVALUE(Inputs!B$2) + (A53-1)*14 -> 46611 | C53: =(52-1)*Inputs!B3 -> 112200 | D53: =SUM(Holdings!J2:J1000) + C53 -> 114206.68 | E53: =D53 * IFERROR((SUM(Holdings!K2:K1000)*12)/(SUM(Holdings!J2:J1000)), Inputs!B4) / 52 -> 1748.3203 | F53: =E53*4.33 -> 7570.2269 | G53: =E53*52 -> 90912.656 | H53: =D53 * Inputs!B6 * Inputs!B7 -> 9850.3262
A54: 53 | B54: =DATEVALUE(Inputs!B$2) + (A54-1)*14 -> 46625 | C54: =(53-1)*Inputs!B3 -> 114400 | D54: =SUM(Holdings!J2:J1000) + C54 -> 116406.68 | E54: =D54 * IFERROR((SUM(Holdings!K2:K1000)*12)/(SUM(Holdings!J2:J1000)), Inputs!B4) / 52 -> 1781.9988 | F54: =E54*4.33 -> 7716.0546 | G54: =E54*52 -> 92663.936 | H54: =D54 * Inputs!B6 * Inputs!B7 -> 10040.076
A55: 54 | B55: =DATEVALUE(Inputs!B$2) + (A55-1)*14 -> 46639 | C55: =(54-1)*Inputs!B3 -> 116600 | D55: =SUM(Holdings!J2:J1000) + C55 -> 118606.68 | E55: =D55 * IFERROR((SUM(Holdings!K2:K1000)*12)/(SUM(Holdings!J2:J1000)), Inputs!B4) / 52 -> 1815.6772 | F55: =E55*4.33 -> 7861.8824 | G55: =E55*52 -> 94415.215 | H55: =D55 * Inputs!B6 * Inputs!B7 -> 10229.826
A56: 55 | B56: =DATEVALUE(Inputs!B$2) + (A56-1)*14 -> 46653 | C56: =(55-1)*Inputs!B3 -> 118800 | D56: =SUM(Holdings!J2:J1000) + C56 -> 120806.68 | E56: =D56 * IFERROR((SUM(Holdings!K2:K1000)*12)/(SUM(Holdings!J2:J1000)), Inputs!B4) / 52 -> 1849.3557 | F56: =E56*4.33 -> 8007.7101 | G56: =E56*52 -> 96166.495 | H56: =D56 * Inputs!B6 * Inputs!B7 -> 10419.576
A57: 56 | B57: =DATEVALUE(Inputs!B$2) + (A57-1)*14 -> 46667 | C57: =(56-1)*Inputs!B3 -> 121000 | D57: =SUM(Holdings!J2:J1000) + C57 -> 123006.68 | E57: =D57 * IFERROR((SUM(Holdings!K2:K1000)*12)/(SUM(Holdings!J2:J1000)), Inputs!B4) / 52 -> 1883.0341 | F57: =E57*4.33 -> 8153.5378 | G57: =E57*52 -> 97917.775 | H57: =D57 * Inputs!B6 * Inputs!B7 -> 10609.326
A58: 57 | B58: =DATEVALUE(Inputs!B$2) + (A58-1)*14 -> 46681 | C58: =(57-1)*Inputs!B3 -> 123200 | D58: =SUM(Holdings!J2:J1000) + C58 -> 125206.68 | E58: =D58 * IFERROR((SUM(Holdings!K2:K1000)*12)/(SUM(Holdings!J2:J1000)), Inputs!B4) / 52 -> 1916.7126 | F58: =E58*4.33 -> 8299.3655 | G58: =E58*52 -> 99669.055 | H58: =D58 * Inputs!B6 * Inputs!B7 -> 10799.076
A59: 58 | B59: =DATEVALUE(Inputs!B$2) + (A59-1)*14 -> 46695 | C59: =(58-1)*Inputs!B3 -> 125400 | D59: =SUM(Holdings!J2:J1000) + C59 -> 127406.68 | E59: =D59 * IFERROR((SUM(Holdings!K2:K1000)*12)/(SUM(Holdings!J2:J1000)), Inputs!B4) / 52 -> 1950.391 | F59: =E59*4.33 -> 8445.1932 | G59: =E59*52 -> 101420.33 | H59: =D59 * Inputs!B6 * Inputs!B7 -> 10988.826
A60: 59 | B60: =DATEVALUE(Inputs!B$2) + (A60-1)*14 -> 46709 | C60: =(59-1)*Inputs!B3 -> 127600 | D60: =SUM(Holdings!J2:J1000) + C60 -> 129606.68 | E60: =D60 * IFERROR((SUM(Holdings!K2:K1000)*12)/(SUM(Holdings!J2:J1000)), Inputs!B4) / 52 -> 1984.0695 | F60: =E60*4.33 -> 8591.0209 | G60: =E60*52 -> 103171.61 | H60: =D60 * Inputs!B6 * Inputs!B7 -> 11178.576
A61: 60 | B61: =DATEVALUE(Inputs!B$2) + (A61-1)*14 -> 46723 | C61: =(60-1)*Inputs!B3 -> 129800 | D61: =SUM(Holdings!J2:J1000) + C61 -> 131806.68 | E61: =D61 * IFERROR((SUM(Holdings!K2:K1000)*12)/(SUM(Holdings!J2:J1000)), Inputs!B4) / 52 -> 2017.748 | F61: =E61*4.33 -> 8736.8487 | G61: =E61*52 -> 104922.89 | H61: =D61 * Inputs!B6 * Inputs!B7 -> 11368.326
A62: 61 | B62: =DATEVALUE(Inputs!B$2) + (A62-1)*14 -> 46737 | C62: =(61-1)*Inputs!B3 -> 132000 | D62: =SUM(Holdings!J2:J1000) + C62 -> 134006.68 | E62: =D62 * IFERROR((SUM(Holdings!K2:K1000)*12)/(SUM(Holdings!J2:J1000)), Inputs!B4) / 52 -> 2051.4264 | F62: =E62*4.33 -> 8882.6764 | G62: =E62*52 -> 106674.17 | H62: =D62 * Inputs!B6 * Inputs!B7 -> 11558.076
A63: 62 | B63: =DATEVALUE(Inputs!B$2) + (A63-1)*14 -> 46751 | C63: =(62-1)*Inputs!B3 -> 134200 | D63: =SUM(Holdings!J2:J1000) + C63 -> 136206.68 | E63: =D63 * IFERROR((SUM(Holdings!K2:K1000)*12)/(SUM(Holdings!J2:J1000)), Inputs!B4) / 52 -> 2085.1049 | F63: =E63*4.33 -> 9028.5041 | G63: =E63*52 -> 108425.45 | H63: =D63 * Inputs!B6 * Inputs!B7 -> 11747.826
A64: 63 | B64: =DATEVALUE(Inputs!B$2) + (A64-1)*14 -> 46765 | C64: =(63-1)*Inputs!B3 -> 136400 | D64: =SUM(Holdings!J2:J1000) + C64 -> 138406.68 | E64: =D64 * IFERROR((SUM(Holdings!K2:K1000)*12)/(SUM(Holdings!J2:J1000)), Inputs!B4) / 52 -> 2118.7833 | F64: =E64*4.33 -> 9174.3318 | G64: =E64*52 -> 110176.73 | H64: =D64 * Inputs!B6 * Inputs!B7 -> 11937.576
A65: 64 | B65: =DATEVALUE(Inputs!B$2) + (A65-1)*14 -> 46779 | C65: =(64-1)*Inputs!B3 -> 138600 | D65: =SUM(Holdings!J2:J1000) + C65 -> 140606.68 | E65: =D65 * IFERROR((SUM(Holdings!K2:K1000)*12)/(SUM(Holdings!J2:J1000)), Inputs!B4) / 52 -> 2152.4618 | F65: =E65*4.33 -> 9320.1595 | G65: =E65*52 -> 111928.01 | H65: =D65 * Inputs!B6 * Inputs!B7 -> 12127.326
A66: 65 | B66: =DATEVALUE(Inputs!B$2) + (A66-1)*14 -> 46793 | C66: =(65-1)*Inputs!B3 -> 140800 | D66: =SUM(Holdings!J2:J1000) + C66 -> 142806.68 | E66: =D66 * IFERROR((SUM(Holdings!K2:K1000)*12)/(SUM(Holdings!J2:J1000)), Inputs!B4) / 52 -> 2186.1402 | F66: =E66*4.33 -> 9465.9872 | G66: =E66*52 -> 113679.29 | H66: =D66 * Inputs!B6 * Inputs!B7 -> 12317.076
A67: 66 | B67: =DATEVALUE(Inputs!B$2) + (A67-1)*14 -> 46807 | C67: =(66-1)*Inputs!B3 -> 143000 | D67: =SUM(Holdings!J2:J1000) + C67 -> 145006.68 | E67: =D67 * IFERROR((SUM(Holdings!K2:K1000)*12)/(SUM(Holdings!J2:J1000)), Inputs!B4) / 52 -> 2219.8187 | F67: =E67*4.33 -> 9611.815 | G67: =E67*52 -> 115430.57 | H67: =D67 * Inputs!B6 * Inputs!B7 -> 12506.826
A68: 67 | B68: =DATEVALUE(Inputs!B$2) + (A68-1)*14 -> 46821 | C68: =(67-1)*Inputs!B3 -> 145200 | D68: =SUM(Holdings!J2:J1000) + C68 -> 147206.68 | E68: =D68 * IFERROR((SUM(Holdings!K2:K1000)*12)/(SUM(Holdings!J2:J1000)), Inputs!B4) / 52 -> 2253.4972 | F68: =E68*4.33 -> 9757.6427 | G68: =E68*52 -> 117181.85 | H68: =D68 * Inputs!B6 * Inputs!B7 -> 12696.576
A69: 68 | B69: =DATEVALUE(Inputs!B$2) + (A69-1)*14 -> 46835 | C69: =(68-1)*Inputs!B3 -> 147400 | D69: =SUM(Holdings!J2:J1000) + C69 -> 149406.68 | E69: =D69 * IFERROR((SUM(Holdings!K2:K1000)*12)/(SUM(Holdings!J2:J1000)), Inputs!B4) / 52 -> 2287.1756 | F69: =E69*4.33 -> 9903.4704 | G69: =E69*52 -> 118933.13 | H69: =D69 * Inputs!B6 * Inputs!B7 -> 12886.326
A70: 69 | B70: =DATEVALUE(Inputs!B$2) + (A70-1)*14 -> 46849 | C70: =(69-1)*Inputs!B3 -> 149600 | D70: =SUM(Holdings!J2:J1000) + C70 -> 151606.68 | E70: =D70 * IFERROR((SUM(Holdings!K2:K1000)*12)/(SUM(Holdings!J2:J1000)), Inputs!B4) / 52 -> 2320.8541 | F70: =E70*4.33 -> 10049.298 | G70: =E70*52 -> 120684.41 | H70: =D70 * Inputs!B6 * Inputs!B7 -> 13076.076
A71: 70 | B71: =DATEVALUE(Inputs!B$2) + (A71-1)*14 -> 46863 | C71: =(70-1)*Inputs!B3 -> 151800 | D71: =SUM(Holdings!J2:J1000) + C71 -> 153806.68 | E71: =D71 * IFERROR((SUM(Holdings!K2:K1000)*12)/(SUM(Holdings!J2:J1000)), Inputs!B4) / 52 -> 2354.5325 | F71: =E71*4.33 -> 10195.126 | G71: =E71*52 -> 122435.69 | H71: =D71 * Inputs!B6 * Inputs!B7 -> 13265.826
A72: 71 | B72: =DATEVALUE(Inputs!B$2) + (A72-1)*14 -> 46877 | C72: =(71-1)*Inputs!B3 -> 154000 | D72: =SUM(Holdings!J2:J1000) + C72 -> 156006.68 | E72: =D72 * IFERROR((SUM(Holdings!K2:K1000)*12)/(SUM(Holdings!J2:J1000)), Inputs!B4) / 52 -> 2388.211 | F72: =E72*4.33 -> 10340.954 | G72: =E72*52 -> 124186.97 | H72: =D72 * Inputs!B6 * Inputs!B7 -> 13455.576
A73: 72 | B73: =DATEVALUE(Inputs!B$2) + (A73-1)*14 -> 46891 | C73: =(72-1)*Inputs!B3 -> 156200 | D73: =SUM(Holdings!J2:J1000) + C73 -> 158206.68 | E73: =D73 * IFERROR((SUM(Holdings!K2:K1000)*12)/(SUM(Holdings!J2:J1000)), Inputs!B4) / 52 -> 2421.8894 | F73: =E73*4.33 -> 10486.781 | G73: =E73*52 -> 125938.25 | H73: =D73 * Inputs!B6 * Inputs!B7 -> 13645.326
A74: 73 | B74: =DATEVALUE(Inputs!B$2) + (A74-1)*14 -> 46905 | C74: =(73-1)*Inputs!B3 -> 158400 | D74: =SUM(Holdings!J2:J1000) + C74 -> 160406.68 | E74: =D74 * IFERROR((SUM(Holdings!K2:K1000)*12)/(SUM(Holdings!J2:J1000)), Inputs!B4) / 52 -> 2455.5679 | F74: =E74*4.33 -> 10632.609 | G74: =E74*52 -> 127689.53 | H74: =D74 * Inputs!B6 * Inputs!B7 -> 13835.076
A75: 74 | B75: =DATEVALUE(Inputs!B$2) + (A75-1)*14 -> 46919 | C75: =(74-1)*Inputs!B3 -> 160600 | D75: =SUM(Holdings!J2:J1000) + C75 -> 162606.68 | E75: =D75 * IFERROR((SUM(Holdings!K2:K1000)*12)/(SUM(Holdings!J2:J1000)), Inputs!B4) / 52 -> 2489.2463 | F75: =E75*4.33 -> 10778.437 | G75: =E75*52 -> 129440.81 | H75: =D75 * Inputs!B6 * Inputs!B7 -> 14024.826
A76: 75 | B76: =DATEVALUE(Inputs!B$2) + (A76-1)*14 -> 46933 | C76: =(75-1)*Inputs!B3 -> 162800 | D76: =SUM(Holdings!J2:J1000) + C76 -> 164806.68 | E76: =D76 * IFERROR((SUM(Holdings!K2:K1000)*12)/(SUM(Holdings!J2:J1000)), Inputs!B4) / 52 -> 2522.9248 | F76: =E76*4.33 -> 10924.264 | G76: =E76*52 -> 131192.09 | H76: =D76 * Inputs!B6 * Inputs!B7 -> 14214.576
A77: 76 | B77: =DATEVALUE(Inputs!B$2) + (A77-1)*14 -> 46947 | C77: =(76-1)*Inputs!B3 -> 165000 | D77: =SUM(Holdings!J2:J1000) + C77 -> 167006.68 | E77: =D77 * IFERROR((SUM(Holdings!K2:K1000)*12)/(SUM(Holdings!J2:J1000)), Inputs!B4) / 52 -> 2556.6033 | F77: =E77*4.33 -> 11070.092 | G77: =E77*52 -> 132943.37 | H77: =D77 * Inputs!B6 * Inputs!B7 -> 14404.326
A78: 77 | B78: =DATEVALUE(Inputs!B$2) + (A78-1)*14 -> 46961 | C78: =(77-1)*Inputs!B3 -> 167200 | D78: =SUM(Holdings!J2:J1000) + C78 -> 169206.68 | E78: =D78 * IFERROR((SUM(Holdings!K2:K1000)*12)/(SUM(Holdings!J2:J1000)), Inputs!B4) / 52 -> 2590.2817 | F78: =E78*4.33 -> 11215.92 | G78: =E78*52 -> 134694.65 | H78: =D78 * Inputs!B6 * Inputs!B7 -> 14594.076
A79: 78 | B79: =DATEVALUE(Inputs!B$2) + (A79-1)*14 -> 46975 | C79: =(78-1)*Inputs!B3 -> 169400 | D79: =SUM(Holdings!J2:J1000) + C79 -> 171406.68 | E79: =D79 * IFERROR((SUM(Holdings!K2:K1000)*12)/(SUM(Holdings!J2:J1000)), Inputs!B4) / 52 -> 2623.9602 | F79: =E79*4.33 -> 11361.748 | G79: =E79*52 -> 136445.93 | H79: =D79 * Inputs!B6 * Inputs!B7 -> 14783.826
A80: 79 | B80: =DATEVALUE(Inputs!B$2) + (A80-1)*14 -> 46989 | C80: =(79-1)*Inputs!B3 -> 171600 | D80: =SUM(Holdings!J2:J1000) + C80 -> 173606.68 | E80: =D80 * IFERROR((SUM(Holdings!K2:K1000)*12)/(SUM(Holdings!J2:J1000)), Inputs!B4) / 52 -> 2657.6386 | F80: =E80*4.33 -> 11507.575 | G80: =E80*52 -> 138197.21 | H80: =D80 * Inputs!B6 * Inputs!B7 -> 14973.576
A81: 80 | B81: =DATEVALUE(Inputs!B$2) + (A81-1)*14 -> 47003 | C81: =(80-1)*Inputs!B3 -> 173800 | D81: =SUM(Holdings!J2:J1000) + C81 -> 175806.68 | E81: =D81 * IFERROR((SUM(Holdings!K2:K1000)*12)/(SUM(Holdings!J2:J1000)), Inputs!B4) / 52 -> 2691.3171 | F81: =E81*4.33 -> 11653.403 | G81: =E81*52 -> 139948.49 | H81: =D81 * Inputs!B6 * Inputs!B7 -> 15163.326
A82: 81 | B82: =DATEVALUE(Inputs!B$2) + (A82-1)*14 -> 47017 | C82: =(81-1)*Inputs!B3 -> 176000 | D82: =SUM(Holdings!J2:J1000) + C82 -> 178006.68 | E82: =D82 * IFERROR((SUM(Holdings!K2:K1000)*12)/(SUM(Holdings!J2:J1000)), Inputs!B4) / 52 -> 2724.9955 | F82: =E82*4.33 -> 11799.231 | G82: =E82*52 -> 141699.77 | H82: =D82 * Inputs!B6 * Inputs!B7 -> 15353.076
A83: 82 | B83: =DATEVALUE(Inputs!B$2) + (A83-1)*14 -> 47031 | C83: =(82-1)*Inputs!B3 -> 178200 | D83: =SUM(Holdings!J2:J1000) + C83 -> 180206.68 | E83: =D83 * IFERROR((SUM(Holdings!K2:K1000)*12)/(SUM(Holdings!J2:J1000)), Inputs!B4) / 52 -> 2758.674 | F83: =E83*4.33 -> 11945.058 | G83: =E83*52 -> 143451.05 | H83: =D83 * Inputs!B6 * Inputs!B7 -> 15542.826
A84: 83 | B84: =DATEVALUE(Inputs!B$2) + (A84-1)*14 -> 47045 | C84: =(83-1)*Inputs!B3 -> 180400 | D84: =SUM(Holdings!J2:J1000) + C84 -> 182406.68 | E84: =D84 * IFERROR((SUM(Holdings!K2:K1000)*12)/(SUM(Holdings!J2:J1000)), Inputs!B4) / 52 -> 2792.3525 | F84: =E84*4.33 -> 12090.886 | G84: =E84*52 -> 145202.33 | H84: =D84 * Inputs!B6 * Inputs!B7 -> 15732.576
A85: 84 | B85: =DATEVALUE(Inputs!B$2) + (A85-1)*14 -> 47059 | C85: =(84-1)*Inputs!B3 -> 182600 | D85: =SUM(Holdings!J2:J1000) + C85 -> 184606.68 | E85: =D85 * IFERROR((SUM(Holdings!K2:K1000)*12)/(SUM(Holdings!J2:J1000)), Inputs!B4) / 52 -> 2826.0309 | F85: =E85*4.33 -> 12236.714 | G85: =E85*52 -> 146953.61 | H85: =D85 * Inputs!B6 * Inputs!B7 -> 15922.326
A86: 85 | B86: =DATEVALUE(Inputs!B$2) + (A86-1)*14 -> 47073 | C86: =(85-1)*Inputs!B3 -> 184800 | D86: =SUM(Holdings!J2:J1000) + C86 -> 186806.68 | E86: =D86 * IFERROR((SUM(Holdings!K2:K1000)*12)/(SUM(Holdings!J2:J1000)), Inputs!B4) / 52 -> 2859.7094 | F86: =E86*4.33 -> 12382.542 | G86: =E86*52 -> 148704.89 | H86: =D86 * Inputs!B6 * Inputs!B7 -> 16112.076
A87: 86 | B87: =DATEVALUE(Inputs!B$2) + (A87-1)*14 -> 47087 | C87: =(86-1)*Inputs!B3 -> 187000 | D87: =SUM(Holdings!J2:J1000) + C87 -> 189006.68 | E87: =D87 * IFERROR((SUM(Holdings!K2:K1000)*12)/(SUM(Holdings!J2:J1000)), Inputs!B4) / 52 -> 2893.3878 | F87: =E87*4.33 -> 12528.369 | G87: =E87*52 -> 150456.17 | H87: =D87 * Inputs!B6 * Inputs!B7 -> 16301.826
A88: 87 | B88: =DATEVALUE(Inputs!B$2) + (A88-1)*14 -> 47101 | C88: =(87-1)*Inputs!B3 -> 189200 | D88: =SUM(Holdings!J2:J1000) + C88 -> 191206.68 | E88: =D88 * IFERROR((SUM(Holdings!K2:K1000)*12)/(SUM(Holdings!J2:J1000)), Inputs!B4) / 52 -> 2927.0663 | F88: =E88*4.33 -> 12674.197 | G88: =E88*52 -> 152207.45 | H88: =D88 * Inputs!B6 * Inputs!B7 -> 16491.576
A89: 88 | B89: =DATEVALUE(Inputs!B$2) + (A89-1)*14 -> 47115 | C89: =(88-1)*Inputs!B3 -> 191400 | D89: =SUM(Holdings!J2:J1000) + C89 -> 193406.68 | E89: =D89 * IFERROR((SUM(Holdings!K2:K1000)*12)/(SUM(Holdings!J2:J1000)), Inputs!B4) / 52 -> 2960.7447 | F89: =E89*4.33 -> 12820.025 | G89: =E89*52 -> 153958.73 | H89: =D89 * Inputs!B6 * Inputs!B7 -> 16681.326
A90: 89 | B90: =DATEVALUE(Inputs!B$2) + (A90-1)*14 -> 47129 | C90: =(89-1)*Inputs!B3 -> 193600 | D90: =SUM(Holdings!J2:J1000) + C90 -> 195606.68 | E90: =D90 * IFERROR((SUM(Holdings!K2:K1000)*12)/(SUM(Holdings!J2:J1000)), Inputs!B4) / 52 -> 2994.4232 | F90: =E90*4.33 -> 12965.852 | G90: =E90*52 -> 155710.01 | H90: =D90 * Inputs!B6 * Inputs!B7 -> 16871.076
A91: 90 | B91: =DATEVALUE(Inputs!B$2) + (A91-1)*14 -> 47143 | C91: =(90-1)*Inputs!B3 -> 195800 | D91: =SUM(Holdings!J2:J1000) + C91 -> 197806.68 | E91: =D91 * IFERROR((SUM(Holdings!K2:K1000)*12)/(SUM(Holdings!J2:J1000)), Inputs!B4) / 52 -> 3028.1016 | F91: =E91*4.33 -> 13111.68 | G91: =E91*52 -> 157461.29 | H91: =D91 * Inputs!B6 * Inputs!B7 -> 17060.826
A92: 91 | B92: =DATEVALUE(Inputs!B$2) + (A92-1)*14 -> 47157 | C92: =(91-1)*Inputs!B3 -> 198000 | D92: =SUM(Holdings!J2:J1000) + C92 -> 200006.68 | E92: =D92 * IFERROR((SUM(Holdings!K2:K1000)*12)/(SUM(Holdings!J2:J1000)), Inputs!B4) / 52 -> 3061.7801 | F92: =E92*4.33 -> 13257.508 | G92: =E92*52 -> 159212.57 | H92: =D92 * Inputs!B6 * Inputs!B7 -> 17250.576
A93: 92 | B93: =DATEVALUE(Inputs!B$2) + (A93-1)*14 -> 47171 | C93: =(92-1)*Inputs!B3 -> 200200 | D93: =SUM(Holdings!J2:J1000) + C93 -> 202206.68 | E93: =D93 * IFERROR((SUM(Holdings!K2:K1000)*12)/(SUM(Holdings!J2:J1000)), Inputs!B4) / 52 -> 3095.4586 | F93: =E93*4.33 -> 13403.336 | G93: =E93*52 -> 160963.85 | H93: =D93 * Inputs!B6 * Inputs!B7 -> 17440.326
A94: 93 | B94: =DATEVALUE(Inputs!B$2) + (A94-1)*14 -> 47185 | C94: =(93-1)*Inputs!B3 -> 202400 | D94: =SUM(Holdings!J2:J1000) + C94 -> 204406.68 | E94: =D94 * IFERROR((SUM(Holdings!K2:K1000)*12)/(SUM(Holdings!J2:J1000)), Inputs!B4) / 52 -> 3129.137 | F94: =E94*4.33 -> 13549.163 | G94: =E94*52 -> 162715.12 | H94: =D94 * Inputs!B6 * Inputs!B7 -> 17630.076
A95: 94 | B95: =DATEVALUE(Inputs!B$2) + (A95-1)*14 -> 47199 | C95: =(94-1)*Inputs!B3 -> 204600 | D95: =SUM(Holdings!J2:J1000) + C95 -> 206606.68 | E95: =D95 * IFERROR((SUM(Holdings!K2:K1000)*12)/(SUM(Holdings!J2:J1000)), Inputs!B4) / 52 -> 3162.8155 | F95: =E95*4.33 -> 13694.991 | G95: =E95*52 -> 164466.4 | H95: =D95 * Inputs!B6 * Inputs!B7 -> 17819.826
A96: 95 | B96: =DATEVALUE(Inputs!B$2) + (A96-1)*14 -> 47213 | C96: =(95-1)*Inputs!B3 -> 206800 | D96: =SUM(Holdings!J2:J1000) + C96 -> 208806.68 | E96: =D96 * IFERROR((SUM(Holdings!K2:K1000)*12)/(SUM(Holdings!J2:J1000)), Inputs!B4) / 52 -> 3196.4939 | F96: =E96*4.33 -> 13840.819 | G96: =E96*52 -> 166217.68 | H96: =D96 * Inputs!B6 * Inputs!B7 -> 18009.576
A97: 96 | B97: =DATEVALUE(Inputs!B$2) + (A97-1)*14 -> 47227 | C97: =(96-1)*Inputs!B3 -> 209000 | D97: =SUM(Holdings!J2:J1000) + C97 -> 211006.68 | E97: =D97 * IFERROR((SUM(Holdings!K2:K1000)*12)/(SUM(Holdings!J2:J1000)), Inputs!B4) / 52 -> 3230.1724 | F97: =E97*4.33 -> 13986.646 | G97: =E97*52 -> 167968.96 | H97: =D97 * Inputs!B6 * Inputs!B7 -> 18199.326
A98: 97 | B98: =DATEVALUE(Inputs!B$2) + (A98-1)*14 -> 47241 | C98: =(97-1)*Inputs!B3 -> 211200 | D98: =SUM(Holdings!J2:J1000) + C98 -> 213206.68 | E98: =D98 * IFERROR((SUM(Holdings!K2:K1000)*12)/(SUM(Holdings!J2:J1000)), Inputs!B4) / 52 -> 3263.8508 | F98: =E98*4.33 -> 14132.474 | G98: =E98*52 -> 169720.24 | H98: =D98 * Inputs!B6 * Inputs!B7 -> 18389.076
A99: 98 | B99: =DATEVALUE(Inputs!B$2) + (A99-1)*14 -> 47255 | C99: =(98-1)*Inputs!B3 -> 213400 | D99: =SUM(Holdings!J2:J1000) + C99 -> 215406.68 | E99: =D99 * IFERROR((SUM(Holdings!K2:K1000)*12)/(SUM(Holdings!J2:J1000)), Inputs!B4) / 52 -> 3297.5293 | F99: =E99*4.33 -> 14278.302 | G99: =E99*52 -> 171471.52 | H99: =D99 * Inputs!B6 * Inputs!B7 -> 18578.826
A100: 99 | B100: =DATEVALUE(Inputs!B$2) + (A100-1)*14 -> 47269 | C100: =(99-1)*Inputs!B3 -> 215600 | D100: =SUM(Holdings!J2:J1000) + C100 -> 217606.68 | E100: =D100 * IFERROR((SUM(Holdings!K2:K1000)*12)/(SUM(Holdings!J2:J1000)), Inputs!B4) / 52 -> 3331.2078 | F100: =E100*4.33 -> 14424.13 | G100: =E100*52 -> 173222.8 | H100: =D100 * Inputs!B6 * Inputs!B7 -> 18768.576
...

Sheet Projection_Monthly
A1: Line | B1: Date | C1: CumulativeContrib ($) | D1: Equity ($) | E1: MonthlyIncome ($) | F1: YearlyIncome ($) | G1: SafeMarginWithdrawal ($)
A2: 1 | B2: =EDATE(Inputs!B2, 1-1) -> 45897 | C2: =(1-1) * (Inputs!B3*2) -> 0 | D2: =SUM(Holdings!J2:J1000) + C2 -> 2006.68 | E2: =D2 * IFERROR((SUM(Holdings!K2:K1000)*12)/(SUM(Holdings!J2:J1000)), Inputs!B4) / 12 -> 133.11583 | F2: =E2*12 -> 1597.39 | G2: =D2 * Inputs!B6 * Inputs!B7 -> 173.07615
A3: 2 | B3: =EDATE(Inputs!B2, 2-1) -> 45928 | C3: =(2-1) * (Inputs!B3*2) -> 4400 | D3: =SUM(Holdings!J2:J1000) + C3 -> 6406.68 | E3: =D3 * IFERROR((SUM(Holdings!K2:K1000)*12)/(SUM(Holdings!J2:J1000)), Inputs!B4) / 12 -> 424.99579 | F3: =E3*12 -> 5099.9495 | G3: =D3 * Inputs!B6 * Inputs!B7 -> 552.57615
A4: 3 | B4: =EDATE(Inputs!B2, 3-1) -> 45958 | C4: =(3-1) * (Inputs!B3*2) -> 8800 | D4: =SUM(Holdings!J2:J1000) + C4 -> 10806.68 | E4: =D4 * IFERROR((SUM(Holdings!K2:K1000)*12)/(SUM(Holdings!J2:J1000)), Inputs!B4) / 12 -> 716.87574 | F4: =E4*12 -> 8602.5089 | G4: =D4 * Inputs!B6 * Inputs!B7 -> 932.07615
A5: 4 | B5: =EDATE(Inputs!B2, 4-1) -> 45989 | C5: =(4-1) * (Inputs!B3*2) -> 13200 | D5: =SUM(Holdings!J2:J1000) + C5 -> 15206.68 | E5: =D5 * IFERROR((SUM(Holdings!K2:K1000)*12)/(SUM(Holdings!J2:J1000)), Inputs!B4) / 12 -> 1008.7557 | F5: =E5*12 -> 12105.068 | G5: =D5 * Inputs!B6 * Inputs!B7 -> 1311.5762
A6: 5 | B6: =EDATE(Inputs!B2, 5-1) -> 46019 | C6: =(5-1) * (Inputs!B3*2) -> 17600 | D6: =SUM(Holdings!J2:J1000) + C6 -> 19606.68 | E6: =D6 * IFERROR((SUM(Holdings!K2:K1000)*12)/(SUM(Holdings!J2:J1000)), Inputs!B4) / 12 -> 1300.6356 | F6: =E6*12 -> 15607.628 | G6: =D6 * Inputs!B6 * Inputs!B7 -> 1691.0762
A7: 6 | B7: =EDATE(Inputs!B2, 6-1) -> 46050 | C7: =(6-1) * (Inputs!B3*2) -> 22000 | D7: =SUM(Holdings!J2:J1000) + C7 -> 24006.68 | E7: =D7 * IFERROR((SUM(Holdings!K2:K1000)*12)/(SUM(Holdings!J2:J1000)), Inputs!B4) / 12 -> 1592.5156 | F7: =E7*12 -> 19110.187 | G7: =D7 * Inputs!B6 * Inputs!B7 -> 2070.5761
A8: 7 | B8: =EDATE(Inputs!B2, 7-1) -> 46081 | C8: =(7-1) * (Inputs!B3*2) -> 26400 | D8: =SUM(Holdings!J2:J1000) + C8 -> 28406.68 | E8: =D8 * IFERROR((SUM(Holdings!K2:K1000)*12)/(SUM(Holdings!J2:J1000)), Inputs!B4) / 12 -> 1884.3956 | F8: =E8*12 -> 22612.747 | G8: =D8 * Inputs!B6 * Inputs!B7 -> 2450.0761
A9: 8 | B9: =EDATE(Inputs!B2, 8-1) -> 46109 | C9: =(8-1) * (Inputs!B3*2) -> 30800 | D9: =SUM(Holdings!J2:J1000) + C9 -> 32806.68 | E9: =D9 * IFERROR((SUM(Holdings!K2:K1000)*12)/(SUM(Holdings!J2:J1000)), Inputs!B4) / 12 -> 2176.2755 | F9: =E9*12 -> 26115.306 | G9: =D9 * Inputs!B6 * Inputs!B7 -> 2829.5761
A10: 9 | B10: =EDATE(Inputs!B2, 9-1) -> 46140 | C10: =(9-1) * (Inputs!B3*2) -> 35200 | D10: =SUM(Holdings!J2:J1000) + C10 -> 37206.68 | E10: =D10 * IFERROR((SUM(Holdings!K2:K1000)*12)/(SUM(Holdings!J2:J1000)), Inputs!B4) / 12 -> 2468.1555 | F10: =E10*12 -> 29617.866 | G10: =D10 * Inputs!B6 * Inputs!B7 -> 3209.0761
A11: 10 | B11: =EDATE(Inputs!B2, 10-1) -> 46170 | C11: =(10-1) * (Inputs!B3*2) -> 39600 | D11: =SUM(Holdings!J2:J1000) + C11 -> 41606.68 | E11: =D11 * IFERROR((SUM(Holdings!K2:K1000)*12)/(SUM(Holdings!J2:J1000)), Inputs!B4) / 12 -> 2760.0354 | F11: =E11*12 -> 33120.425 | G11: =D11 * Inputs!B6 * Inputs!B7 -> 3588.5761
A12: 11 | B12: =EDATE(Inputs!B2, 11-1) -> 46201 | C12: =(11-1) * (Inputs!B3*2) -> 44000 | D12: =SUM(Holdings!J2:J1000) + C12 -> 46006.68 | E12: =D12 * IFERROR((SUM(Holdings!K2:K1000)*12)/(SUM(Holdings!J2:J1000)), Inputs!B4) / 12 -> 3051.9154 | F12: =E12*12 -> 36622.985 | G12: =D12 * Inputs!B6 * Inputs!B7 -> 3968.0761
A13: 12 | B13: =EDATE(Inputs!B2, 12-1) -> 46231 | C13: =(12-1) * (Inputs!B3*2) -> 48400 | D13: =SUM(Holdings!J2:J1000) + C13 -> 50406.68 | E13: =D13 * IFERROR((SUM(Holdings!K2:K1000)*12)/(SUM(Holdings!J2:J1000)), Inputs!B4) / 12 -> 3343.7953 | F13: =E13*12 -> 40125.544 | G13: =D13 * Inputs!B6 * Inputs!B7 -> 4347.5761
A14: 13 | B14: =EDATE(Inputs!B2, 13-1) -> 46262 | C14: =(13-1) * (Inputs!B3*2) -> 52800 | D14: =SUM(Holdings!J2:J1000) + C14 -> 54806.68 | E14: =D14 * IFERROR((SUM(Holdings!K2:K1000)*12)/(SUM(Holdings!J2:J1000)), Inputs!B4) / 12 -> 3635.6753 | F14: =E14*12 -> 43628.103 | G14: =D14 * Inputs!B6 * Inputs!B7 -> 4727.0761
A15: 14 | B15: =EDATE(Inputs!B2, 14-1) -> 46293 | C15: =(14-1) * (Inputs!B3*2) -> 57200 | D15: =SUM(Holdings!J2:J1000) + C15 -> 59206.68 | E15: =D15 * IFERROR((SUM(Holdings!K2:K1000)*12)/(SUM(Holdings!J2:J1000)), Inputs!B4) / 12 -> 3927.5552 | F15: =E15*12 -> 47130.663 | G15: =D15 * Inputs!B6 * Inputs!B7 -> 5106.5761
A16: 15 | B16: =EDATE(Inputs!B2, 15-1) -> 46323 | C16: =(15-1) * (Inputs!B3*2) -> 61600 | D16: =SUM(Holdings!J2:J1000) + C16 -> 63606.68 | E16: =D16 * IFERROR((SUM(Holdings!K2:K1000)*12)/(SUM(Holdings!J2:J1000)), Inputs!B4) / 12 -> 4219.4352 | F16: =E16*12 -> 50633.222 | G16: =D16 * Inputs!B6 * Inputs!B7 -> 5486.0761
A17: 16 | B17: =EDATE(Inputs!B2, 16-1) -> 46354 | C17: =(16-1) * (Inputs!B3*2) -> 66000 | D17: =SUM(Holdings!J2:J1000) + C17 -> 68006.68 | E17: =D17 * IFERROR((SUM(Holdings!K2:K1000)*12)/(SUM(Holdings!J2:J1000)), Inputs!B4) / 12 -> 4511.3151 | F17: =E17*12 -> 54135.782 | G17: =D17 * Inputs!B6 * Inputs!B7 -> 5865.5761
A18: 17 | B18: =EDATE(Inputs!B2, 17-1) -> 46384 | C18: =(17-1) * (Inputs!B3*2) -> 70400 | D18: =SUM(Holdings!J2:J1000) + C18 -> 72406.68 | E18: =D18 * IFERROR((SUM(Holdings!K2:K1000)*12)/(SUM(Holdings!J2:J1000)), Inputs!B4) / 12 -> 4803.1951 | F18: =E18*12 -> 57638.341 | G18: =D18 * Inputs!B6 * Inputs!B7 -> 6245.0761
A19: 18 | B19: =EDATE(Inputs!B2, 18-1) -> 46415 | C19: =(18-1) * (Inputs!B3*2) -> 74800 | D19: =SUM(Holdings!J2:J1000) + C19 -> 76806.68 | E19: =D19 * IFERROR((SUM(Holdings!K2:K1000)*12)/(SUM(Holdings!J2:J1000)), Inputs!B4) / 12 -> 5095.0751 | F19: =E19*12 -> 61140.901 | G19: =D19 * Inputs!B6 * Inputs!B7 -> 6624.5761
A20: 19 | B20: =EDATE(Inputs!B2, 19-1) -> 46446 | C20: =(19-1) * (Inputs!B3*2) -> 79200 | D20: =SUM(Holdings!J2:J1000) + C20 -> 81206.68 | E20: =D20 * IFERROR((SUM(Holdings!K2:K1000)*12)/(SUM(Holdings!J2:J1000)), Inputs!B4) / 12 -> 5386.955 | F20: =E20*12 -> 64643.46 | G20: =D20 * Inputs!B6 * Inputs!B7 -> 7004.0761
A21: 20 | B21: =EDATE(Inputs!B2, 20-1) -> 46474 | C21: =(20-1) * (Inputs!B3*2) -> 83600 | D21: =SUM(Holdings!J2:J1000) + C21 -> 85606.68 | E21: =D21 * IFERROR((SUM(Holdings!K2:K1000)*12)/(SUM(Holdings!J2:J1000)), Inputs!B4) / 12 -> 5678.835 | F21: =E21*12 -> 68146.02 | G21: =D21 * Inputs!B6 * Inputs!B7 -> 7383.5761
A22: 21 | B22: =EDATE(Inputs!B2, 21-1) -> 46505 | C22: =(21-1) * (Inputs!B3*2) -> 88000 | D22: =SUM(Holdings!J2:J1000) + C22 -> 90006.68 | E22: =D22 * IFERROR((SUM(Holdings!K2:K1000)*12)/(SUM(Holdings!J2:J1000)), Inputs!B4) / 12 -> 5970.7149 | F22: =E22*12 -> 71648.579 | G22: =D22 * Inputs!B6 * Inputs!B7 -> 7763.0761
A23: 22 | B23: =EDATE(Inputs!B2, 22-1) -> 46535 | C23: =(22-1) * (Inputs!B3*2) -> 92400 | D23: =SUM(Holdings!J2:J1000) + C23 -> 94406.68 | E23: =D23 * IFERROR((SUM(Holdings!K2:K1000)*12)/(SUM(Holdings!J2:J1000)), Inputs!B4) / 12 -> 6262.5949 | F23: =E23*12 -> 75151.138 | G23: =D23 * Inputs!B6 * Inputs!B7 -> 8142.5761
A24: 23 | B24: =EDATE(Inputs!B2, 23-1) -> 46566 | C24: =(23-1) * (Inputs!B3*2) -> 96800 | D24: =SUM(Holdings!J2:J1000) + C24 -> 98806.68 | E24: =D24 * IFERROR((SUM(Holdings!K2:K1000)*12)/(SUM(Holdings!J2:J1000)), Inputs!B4) / 12 -> 6554.4748 | F24: =E24*12 -> 78653.698 | G24: =D24 * Inputs!B6 * Inputs!B7 -> 8522.0762
A25: 24 | B25: =EDATE(Inputs!B2, 24-1) -> 46596 | C25: =(24-1) * (Inputs!B3*2) -> 101200 | D25: =SUM(Holdings!J2:J1000) + C25 -> 103206.68 | E25: =D25 * IFERROR((SUM(Holdings!K2:K1000)*12)/(SUM(Holdings!J2:J1000)), Inputs!B4) / 12 -> 6846.3548 | F25: =E25*12 -> 82156.257 | G25: =D25 * Inputs!B6 * Inputs!B7 -> 8901.5762
A26: 25 | B26: =EDATE(Inputs!B2, 25-1) -> 46627 | C26: =(25-1) * (Inputs!B3*2) -> 105600 | D26: =SUM(Holdings!J2:J1000) + C26 -> 107606.68 | E26: =D26 * IFERROR((SUM(Holdings!K2:K1000)*12)/(SUM(Holdings!J2:J1000)), Inputs!B4) / 12 -> 7138.2347 | F26: =E26*12 -> 85658.817 | G26: =D26 * Inputs!B6 * Inputs!B7 -> 9281.0762
A27: 26 | B27: =EDATE(Inputs!B2, 26-1) -> 46658 | C27: =(26-1) * (Inputs!B3*2) -> 110000 | D27: =SUM(Holdings!J2:J1000) + C27 -> 112006.68 | E27: =D27 * IFERROR((SUM(Holdings!K2:K1000)*12)/(SUM(Holdings!J2:J1000)), Inputs!B4) / 12 -> 7430.1147 | F27: =E27*12 -> 89161.376 | G27: =D27 * Inputs!B6 * Inputs!B7 -> 9660.5762
A28: 27 | B28: =EDATE(Inputs!B2, 27-1) -> 46688 | C28: =(27-1) * (Inputs!B3*2) -> 114400 | D28: =SUM(Holdings!J2:J1000) + C28 -> 116406.68 | E28: =D28 * IFERROR((SUM(Holdings!K2:K1000)*12)/(SUM(Holdings!J2:J1000)), Inputs!B4) / 12 -> 7721.9946 | F28: =E28*12 -> 92663.936 | G28: =D28 * Inputs!B6 * Inputs!B7 -> 10040.076
A29: 28 | B29: =EDATE(Inputs!B2, 28-1) -> 46719 | C29: =(28-1) * (Inputs!B3*2) -> 118800 | D29: =SUM(Holdings!J2:J1000) + C29 -> 120806.68 | E29: =D29 * IFERROR((SUM(Holdings!K2:K1000)*12)/(SUM(Holdings!J2:J1000)), Inputs!B4) / 12 -> 8013.8746 | F29: =E29*12 -> 96166.495 | G29: =D29 * Inputs!B6 * Inputs!B7 -> 10419.576
A30: 29 | B30: =EDATE(Inputs!B2, 29-1) -> 46749 | C30: =(29-1) * (Inputs!B3*2) -> 123200 | D30: =SUM(Holdings!J2:J1000) + C30 -> 125206.68 | E30: =D30 * IFERROR((SUM(Holdings!K2:K1000)*12)/(SUM(Holdings!J2:J1000)), Inputs!B4) / 12 -> 8305.7546 | F30: =E30*12 -> 99669.055 | G30: =D30 * Inputs!B6 * Inputs!B7 -> 10799.076
A31: 30 | B31: =EDATE(Inputs!B2, 30-1) -> 46780 | C31: =(30-1) * (Inputs!B3*2) -> 127600 | D31: =SUM(Holdings!J2:J1000) + C31 -> 129606.68 | E31: =D31 * IFERROR((SUM(Holdings!K2:K1000)*12)/(SUM(Holdings!J2:J1000)), Inputs!B4) / 12 -> 8597.6345 | F31: =E31*12 -> 103171.61 | G31: =D31 * Inputs!B6 * Inputs!B7 -> 11178.576
A32: 31 | B32: =EDATE(Inputs!B2, 31-1) -> 46811 | C32: =(31-1) * (Inputs!B3*2) -> 132000 | D32: =SUM(Holdings!J2:J1000) + C32 -> 134006.68 | E32: =D32 * IFERROR((SUM(Holdings!K2:K1000)*12)/(SUM(Holdings!J2:J1000)), Inputs!B4) / 12 -> 8889.5145 | F32: =E32*12 -> 106674.17 | G32: =D32 * Inputs!B6 * Inputs!B7 -> 11558.076
A33: 32 | B33: =EDATE(Inputs!B2, 32-1) -> 46840 | C33: =(32-1) * (Inputs!B3*2) -> 136400 | D33: =SUM(Holdings!J2:J1000) + C33 -> 138406.68 | E33: =D33 * IFERROR((SUM(Holdings!K2:K1000)*12)/(SUM(Holdings!J2:J1000)), Inputs!B4) / 12 -> 9181.3944 | F33: =E33*12 -> 110176.73 | G33: =D33 * Inputs!B6 * Inputs!B7 -> 11937.576
A34: 33 | B34: =EDATE(Inputs!B2, 33-1) -> 46871 | C34: =(33-1) * (Inputs!B3*2) -> 140800 | D34: =SUM(Holdings!J2:J1000) + C34 -> 142806.68 | E34: =D34 * IFERROR((SUM(Holdings!K2:K1000)*12)/(SUM(Holdings!J2:J1000)), Inputs!B4) / 12 -> 9473.2744 | F34: =E34*12 -> 113679.29 | G34: =D34 * Inputs!B6 * Inputs!B7 -> 12317.076
A35: 34 | B35: =EDATE(Inputs!B2, 34-1) -> 46901 | C35: =(34-1) * (Inputs!B3*2) -> 145200 | D35: =SUM(Holdings!J2:J1000) + C35 -> 147206.68 | E35: =D35 * IFERROR((SUM(Holdings!K2:K1000)*12)/(SUM(Holdings!J2:J1000)), Inputs!B4) / 12 -> 9765.1543 | F35: =E35*12 -> 117181.85 | G35: =D35 * Inputs!B6 * Inputs!B7 -> 12696.576
A36: 35 | B36: =EDATE(Inputs!B2, 35-1) -> 46932 | C36: =(35-1) * (Inputs!B3*2) -> 149600 | D36: =SUM(Holdings!J2:J1000) + C36 -> 151606.68 | E36: =D36 * IFERROR((SUM(Holdings!K2:K1000)*12)/(SUM(Holdings!J2:J1000)), Inputs!B4) / 12 -> 10057.034 | F36: =E36*12 -> 120684.41 | G36: =D36 * Inputs!B6 * Inputs!B7 -> 13076.076
A37: 36 | B37: =EDATE(Inputs!B2, 36-1) -> 46962 | C37: =(36-1) * (Inputs!B3*2) -> 154000 | D37: =SUM(Holdings!J2:J1000) + C37 -> 156006.68 | E37: =D37 * IFERROR((SUM(Holdings!K2:K1000)*12)/(SUM(Holdings!J2:J1000)), Inputs!B4) / 12 -> 10348.914 | F37: =E37*12 -> 124186.97 | G37: =D37 * Inputs!B6 * Inputs!B7 -> 13455.576
A38: 37 | B38: =EDATE(Inputs!B2, 37-1) -> 46993 | C38: =(37-1) * (Inputs!B3*2) -> 158400 | D38: =SUM(Holdings!J2:J1000) + C38 -> 160406.68 | E38: =D38 * IFERROR((SUM(Holdings!K2:K1000)*12)/(SUM(Holdings!J2:J1000)), Inputs!B4) / 12 -> 10640.794 | F38: =E38*12 -> 127689.53 | G38: =D38 * Inputs!B6 * Inputs!B7 -> 13835.076
A39: 38 | B39: =EDATE(Inputs!B2, 38-1) -> 47024 | C39: =(38-1) * (Inputs!B3*2) -> 162800 | D39: =SUM(Holdings!J2:J1000) + C39 -> 164806.68 | E39: =D39 * IFERROR((SUM(Holdings!K2:K1000)*12)/(SUM(Holdings!J2:J1000)), Inputs!B4) / 12 -> 10932.674 | F39: =E39*12 -> 131192.09 | G39: =D39 * Inputs!B6 * Inputs!B7 -> 14214.576
A40: 39 | B40: =EDATE(Inputs!B2, 39-1) -> 47054 | C40: =(39-1) * (Inputs!B3*2) -> 167200 | D40: =SUM(Holdings!J2:J1000) + C40 -> 169206.68 | E40: =D40 * IFERROR((SUM(Holdings!K2:K1000)*12)/(SUM(Holdings!J2:J1000)), Inputs!B4) / 12 -> 11224.554 | F40: =E40*12 -> 134694.65 | G40: =D40 * Inputs!B6 * Inputs!B7 -> 14594.076
A41: 40 | B41: =EDATE(Inputs!B2, 40-1) -> 47085 | C41: =(40-1) * (Inputs!B3*2) -> 171600 | D41: =SUM(Holdings!J2:J1000) + C41 -> 173606.68 | E41: =D41 * IFERROR((SUM(Holdings!K2:K1000)*12)/(SUM(Holdings!J2:J1000)), Inputs!B4) / 12 -> 11516.434 | F41: =E41*12 -> 138197.21 | G41: =D41 * Inputs!B6 * Inputs!B7 -> 14973.576
A42: 41 | B42: =EDATE(Inputs!B2, 41-1) -> 47115 | C42: =(41-1) * (Inputs!B3*2) -> 176000 | D42: =SUM(Holdings!J2:J1000) + C42 -> 178006.68 | E42: =D42 * IFERROR((SUM(Holdings!K2:K1000)*12)/(SUM(Holdings!J2:J1000)), Inputs!B4) / 12 -> 11808.314 | F42: =E42*12 -> 141699.77 | G42: =D42 * Inputs!B6 * Inputs!B7 -> 15353.076
A43: 42 | B43: =EDATE(Inputs!B2, 42-1) -> 47146 | C43: =(42-1) * (Inputs!B3*2) -> 180400 | D43: =SUM(Holdings!J2:J1000) + C43 -> 182406.68 | E43: =D43 * IFERROR((SUM(Holdings!K2:K1000)*12)/(SUM(Holdings!J2:J1000)), Inputs!B4) / 12 -> 12100.194 | F43: =E43*12 -> 145202.33 | G43: =D43 * Inputs!B6 * Inputs!B7 -> 15732.576
A44: 43 | B44: =EDATE(Inputs!B2, 43-1) -> 47177 | C44: =(43-1) * (Inputs!B3*2) -> 184800 | D44: =SUM(Holdings!J2:J1000) + C44 -> 186806.68 | E44: =D44 * IFERROR((SUM(Holdings!K2:K1000)*12)/(SUM(Holdings!J2:J1000)), Inputs!B4) / 12 -> 12392.074 | F44: =E44*12 -> 148704.89 | G44: =D44 * Inputs!B6 * Inputs!B7 -> 16112.076
A45: 44 | B45: =EDATE(Inputs!B2, 44-1) -> 47205 | C45: =(44-1) * (Inputs!B3*2) -> 189200 | D45: =SUM(Holdings!J2:J1000) + C45 -> 191206.68 | E45: =D45 * IFERROR((SUM(Holdings!K2:K1000)*12)/(SUM(Holdings!J2:J1000)), Inputs!B4) / 12 -> 12683.954 | F45: =E45*12 -> 152207.45 | G45: =D45 * Inputs!B6 * Inputs!B7 -> 16491.576
A46: 45 | B46: =EDATE(Inputs!B2, 45-1) -> 47236 | C46: =(45-1) * (Inputs!B3*2) -> 193600 | D46: =SUM(Holdings!J2:J1000) + C46 -> 195606.68 | E46: =D46 * IFERROR((SUM(Holdings!K2:K1000)*12)/(SUM(Holdings!J2:J1000)), Inputs!B4) / 12 -> 12975.834 | F46: =E46*12 -> 155710.01 | G46: =D46 * Inputs!B6 * Inputs!B7 -> 16871.076
A47: 46 | B47: =EDATE(Inputs!B2, 46-1) -> 47266 | C47: =(46-1) * (Inputs!B3*2) -> 198000 | D47: =SUM(Holdings!J2:J1000) + C47 -> 200006.68 | E47: =D47 * IFERROR((SUM(Holdings!K2:K1000)*12)/(SUM(Holdings!J2:J1000)), Inputs!B4) / 12 -> 13267.714 | F47: =E47*12 -> 159212.57 | G47: =D47 * Inputs!B6 * Inputs!B7 -> 17250.576
A48: 47 | B48: =EDATE(Inputs!B2, 47-1) -> 47297 | C48: =(47-1) * (Inputs!B3*2) -> 202400 | D48: =SUM(Holdings!J2:J1000) + C48 -> 204406.68 | E48: =D48 * IFERROR((SUM(Holdings!K2:K1000)*12)/(SUM(Holdings!J2:J1000)), Inputs!B4) / 12 -> 13559.594 | F48: =E48*12 -> 162715.12 | G48: =D48 * Inputs!B6 * Inputs!B7 -> 17630.076
A49: 48 | B49: =EDATE(Inputs!B2, 48-1) -> 47327 | C49: =(48-1) * (Inputs!B3*2) -> 206800 | D49: =SUM(Holdings!J2:J1000) + C49 -> 208806.68 | E49: =D49 * IFERROR((SUM(Holdings!K2:K1000)*12)/(SUM(Holdings!J2:J1000)), Inputs!B4) / 12 -> 13851.474 | F49: =E49*12 -> 166217.68 | G49: =D49 * Inputs!B6 * Inputs!B7 -> 18009.576
A50: 49 | B50: =EDATE(Inputs!B2, 49-1) -> 47358 | C50: =(49-1) * (Inputs!B3*2) -> 211200 | D50: =SUM(Holdings!J2:J1000) + C50 -> 213206.68 | E50: =D50 * IFERROR((SUM(Holdings!K2:K1000)*12)/(SUM(Holdings!J2:J1000)), Inputs!B4) / 12 -> 14143.354 | F50: =E50*12 -> 169720.24 | G50: =D50 * Inputs!B6 * Inputs!B7 -> 18389.076
A51: 50 | B51: =EDATE(Inputs!B2, 50-1) -> 47389 | C51: =(50-1) * (Inputs!B3*2) -> 215600 | D51: =SUM(Holdings!J2:J1000) + C51 -> 217606.68 | E51: =D51 * IFERROR((SUM(Holdings!K2:K1000)*12)/(SUM(Holdings!J2:J1000)), Inputs!B4) / 12 -> 14435.234 | F51: =E51*12 -> 173222.8 | G51: =D51 * Inputs!B6 * Inputs!B7 -> 18768.576
A52: 51 | B52: =EDATE(Inputs!B2, 51-1) -> 47419 | C52: =(51-1) * (Inputs!B3*2) -> 220000 | D52: =SUM(Holdings!J2:J1000) + C52 -> 222006.68 | E52: =D52 * IFERROR((SUM(Holdings!K2:K1000)*12)/(SUM(Holdings!J2:J1000)), Inputs!B4) / 12 -> 14727.114 | F52: =E52*12 -> 176725.36 | G52: =D52 * Inputs!B6 * Inputs!B7 -> 19148.076
A53: 52 | B53: =EDATE(Inputs!B2, 52-1) -> 47450 | C53: =(52-1) * (Inputs!B3*2) -> 224400 | D53: =SUM(Holdings!J2:J1000) + C53 -> 226406.68 | E53: =D53 * IFERROR((SUM(Holdings!K2:K1000)*12)/(SUM(Holdings!J2:J1000)), Inputs!B4) / 12 -> 15018.994 | F53: =E53*12 -> 180227.92 | G53: =D53 * Inputs!B6 * Inputs!B7 -> 19527.576
A54: 53 | B54: =EDATE(Inputs!B2, 53-1) -> 47480 | C54: =(53-1) * (Inputs!B3*2) -> 228800 | D54: =SUM(Holdings!J2:J1000) + C54 -> 230806.68 | E54: =D54 * IFERROR((SUM(Holdings!K2:K1000)*12)/(SUM(Holdings!J2:J1000)), Inputs!B4) / 12 -> 15310.873 | F54: =E54*12 -> 183730.48 | G54: =D54 * Inputs!B6 * Inputs!B7 -> 19907.076
A55: 54 | B55: =EDATE(Inputs!B2, 54-1) -> 47511 | C55: =(54-1) * (Inputs!B3*2) -> 233200 | D55: =SUM(Holdings!J2:J1000) + C55 -> 235206.68 | E55: =D55 * IFERROR((SUM(Holdings!K2:K1000)*12)/(SUM(Holdings!J2:J1000)), Inputs!B4) / 12 -> 15602.753 | F55: =E55*12 -> 187233.04 | G55: =D55 * Inputs!B6 * Inputs!B7 -> 20286.576
A56: 55 | B56: =EDATE(Inputs!B2, 55-1) -> 47542 | C56: =(55-1) * (Inputs!B3*2) -> 237600 | D56: =SUM(Holdings!J2:J1000) + C56 -> 239606.68 | E56: =D56 * IFERROR((SUM(Holdings!K2:K1000)*12)/(SUM(Holdings!J2:J1000)), Inputs!B4) / 12 -> 15894.633 | F56: =E56*12 -> 190735.6 | G56: =D56 * Inputs!B6 * Inputs!B7 -> 20666.076
A57: 56 | B57: =EDATE(Inputs!B2, 56-1) -> 47570 | C57: =(56-1) * (Inputs!B3*2) -> 242000 | D57: =SUM(Holdings!J2:J1000) + C57 -> 244006.68 | E57: =D57 * IFERROR((SUM(Holdings!K2:K1000)*12)/(SUM(Holdings!J2:J1000)), Inputs!B4) / 12 -> 16186.513 | F57: =E57*12 -> 194238.16 | G57: =D57 * Inputs!B6 * Inputs!B7 -> 21045.576
A58: 57 | B58: =EDATE(Inputs!B2, 57-1) -> 47601 | C58: =(57-1) * (Inputs!B3*2) -> 246400 | D58: =SUM(Holdings!J2:J1000) + C58 -> 248406.68 | E58: =D58 * IFERROR((SUM(Holdings!K2:K1000)*12)/(SUM(Holdings!J2:J1000)), Inputs!B4) / 12 -> 16478.393 | F58: =E58*12 -> 197740.72 | G58: =D58 * Inputs!B6 * Inputs!B7 -> 21425.076
A59: 58 | B59: =EDATE(Inputs!B2, 58-1) -> 47631 | C59: =(58-1) * (Inputs!B3*2) -> 250800 | D59: =SUM(Holdings!J2:J1000) + C59 -> 252806.68 | E59: =D59 * IFERROR((SUM(Holdings!K2:K1000)*12)/(SUM(Holdings!J2:J1000)), Inputs!B4) / 12 -> 16770.273 | F59: =E59*12 -> 201243.28 | G59: =D59 * Inputs!B6 * Inputs!B7 -> 21804.576
A60: 59 | B60: =EDATE(Inputs!B2, 59-1) -> 47662 | C60: =(59-1) * (Inputs!B3*2) -> 255200 | D60: =SUM(Holdings!J2:J1000) + C60 -> 257206.68 | E60: =D60 * IFERROR((SUM(Holdings!K2:K1000)*12)/(SUM(Holdings!J2:J1000)), Inputs!B4) / 12 -> 17062.153 | F60: =E60*12 -> 204745.84 | G60: =D60 * Inputs!B6 * Inputs!B7 -> 22184.076
A61: 60 | B61: =EDATE(Inputs!B2, 60-1) -> 47692 | C61: =(60-1) * (Inputs!B3*2) -> 259600 | D61: =SUM(Holdings!J2:J1000) + C61 -> 261606.68 | E61: =D61 * IFERROR((SUM(Holdings!K2:K1000)*12)/(SUM(Holdings!J2:J1000)), Inputs!B4) / 12 -> 17354.033 | F61: =E61*12 -> 208248.4 | G61: =D61 * Inputs!B6 * Inputs!B7 -> 22563.576

Sheet Paycheck_Plan
A1: Symbol | B1: Bucket | C1: WeightInBucket | D1: Allocation_$ | E1: Est_Shares | F1: Note
A2: TOTALS | B2: Anchor | C2: 1 | D2: 2200 | E2: 200
A3: TOTAL | C3: =SUM(C2) -> 1 | D3: =SUM(D2) -> 2200 | E3: =SUM(E2) -> 200

Sheet Milestones
A1: Milestone | B1: Reached On | C1: Projection(Line#) | D1: WeeklyIncome($) | E1: MonthlyIncome($) | F1: YearlyIncome($) | G1: Equity($) | H1: SafeMargin($) | I1: Goal | J1: Remaining to Goal
A2: Weekly income ≥ goal | I2: 0.1 | J2: 0.1
A3: Monthly income ≥ goal | I3: 1108.545 | J3: 1108.545
A4: Annual income ≥ goal | I4: 4800 | J4: 4800
